rtl/booth_radix8_multiplier_su_7_linear_155.v
`timescale 1ns / 1ps
`default_nettype none

// ============================================================================
// Module: booth_mult8
// Status: MANTIDO (Design compacto e eficiente)
// ============================================================================
module booth_mult8 (
    input  wire                  clk,
    input  wire                  rst_n,
    input  wire                  start,
    input  wire signed [7:0]     multiplicand,
    input  wire signed [7:0]     multiplier,
    input  wire [1:0]            sign_mode,
    output wire signed [15:0]    product,
    output wire                  done
);
    localparam integer WIDTH = 8;
    localparam integer SHIFT_BITS = 9;
    localparam integer ACC_WIDTH = 11;
    localparam integer REG_WIDTH = 21;

    reg active;
    reg signed [REG_WIDTH-1:0] prod_reg;
    reg [3:0] iter_shift;

    reg signed [ACC_WIDTH-1:0] m_3x_reg;
    reg signed [ACC_WIDTH-1:0] mcand_ext_reg;

    wire sign_bit_a = sign_mode[1] & multiplicand[WIDTH-1];
    wire signed [ACC_WIDTH-1:0] mcand_extended = { {(ACC_WIDTH-WIDTH){sign_bit_a}}, multiplicand };
    wire signed [ACC_WIDTH-1:0] calc_3x = mcand_extended + (mcand_extended <<< 1);

    wire sign_bit_b = sign_mode[0] & multiplier[WIDTH-1];
    wire [REG_WIDTH-1:0] prod_reg_init = {
        {ACC_WIDTH{1'b0}},
        {(SHIFT_BITS-WIDTH){sign_bit_b}},
        multiplier,
        1'b0
    };

    wire [3:0] booth_bits = prod_reg[3:0];
    wire signed [ACC_WIDTH-1:0] acc_upper = prod_reg[REG_WIDTH-1 : SHIFT_BITS+1];

    reg sel_1x, sel_2x, sel_3x, sel_4x;
    always @(*) begin
        sel_1x = (booth_bits == 4'b0001) || (booth_bits == 4'b0010) ||
                 (booth_bits == 4'b1101) || (booth_bits == 4'b1110);
        sel_2x = (booth_bits == 4'b0011) || (booth_bits == 4'b0100) ||
                 (booth_bits == 4'b1011) || (booth_bits == 4'b1100);
        sel_3x = (booth_bits == 4'b0101) || (booth_bits == 4'b0110) ||
                 (booth_bits == 4'b1001) || (booth_bits == 4'b1010);
        sel_4x = (booth_bits == 4'b0111) || (booth_bits == 4'b1000);
    end

    wire inv = booth_bits[3] & ~(&booth_bits[2:0]);
    wire signed [ACC_WIDTH-1:0] m_1x = mcand_ext_reg;
    wire signed [ACC_WIDTH-1:0] m_2x = mcand_ext_reg <<< 1;
    wire signed [ACC_WIDTH-1:0] m_4x = mcand_ext_reg <<< 2;

    reg signed [ACC_WIDTH-1:0] mag_sel;
    always @(*) begin
        mag_sel = ({ACC_WIDTH{sel_1x}} & m_1x) |
                  ({ACC_WIDTH{sel_2x}} & m_2x) |
                  ({ACC_WIDTH{sel_3x}} & m_3x_reg) |
                  ({ACC_WIDTH{sel_4x}} & m_4x);
    end

    wire signed [ACC_WIDTH-1:0] operand_inv = mag_sel ^ {ACC_WIDTH{inv}};
    wire signed [ACC_WIDTH-1:0] sum_result  = acc_upper + operand_inv + { {(ACC_WIDTH-1){1'b0}}, inv };

    assign done = iter_shift[0] && active;
    assign product = prod_reg[16:1];

    always @(posedge clk or negedge rst_n) begin
        if (!rst_n) begin
            active         <= 1'b0;
            iter_shift     <= 4'b0;
            prod_reg       <= {REG_WIDTH{1'b0}};
            m_3x_reg       <= {ACC_WIDTH{1'b0}};
            mcand_ext_reg  <= {ACC_WIDTH{1'b0}};
        end else begin
            if (active) begin
                if (iter_shift[0]) begin
                    active <= 1'b0;
                end else begin
                    prod_reg   <= { {3{sum_result[ACC_WIDTH-1]}}, sum_result, prod_reg[SHIFT_BITS:3] };
                    iter_shift <= iter_shift >> 1;
                end
            end else if (start) begin
                active        <= 1'b1;
                iter_shift    <= 4'b1000;
                mcand_ext_reg <= mcand_extended;
                m_3x_reg      <= calc_3x;
                prod_reg      <= prod_reg_init;
            end
        end
    end
endmodule

// ============================================================================
// Module: booth_radix8_multiplier (Top Level)
// Optimization: INPUT REGISTERS + PIPELINED ADDER
// ============================================================================
module booth_radix8_multiplier #(
    parameter integer WIDTH = 16
)(
    input  wire                         clk,
    input  wire                         rst_n,
    input  wire                         start,
    input  wire signed [WIDTH-1:0]      multiplicand,
    input  wire signed [WIDTH-1:0]      multiplier,
    input  wire [1:0]                   sign_mode,
    output reg  signed [2*WIDTH-1:0]    product,
    output reg                          done,
    output wire                         busy
);

    // ------------------------------------------------------------------------
    // 1. INPUT REGISTERS (Critical for High Fmax)
    // Isola os pinos de IO da lógica interna. 
    // Resolve o atraso de "start_SB_LUT4..."
    // ------------------------------------------------------------------------
    reg r_start;
    reg signed [WIDTH-1:0] r_mcand, r_mult;
    reg [1:0] r_sign_mode;

    always @(posedge clk or negedge rst_n) begin
        if (!rst_n) begin
            r_start <= 1'b0;
            r_mcand <= {WIDTH{1'b0}};
            r_mult  <= {WIDTH{1'b0}};
            r_sign_mode <= 2'b00;
        end else begin
            r_start <= start;
            if (start) begin
                r_mcand <= multiplicand;
                r_mult  <= multiplier;
                r_sign_mode <= sign_mode;
            end
        end
    end

    // ------------------------------------------------------------------------
    // 2. PARALLEL MULTIPLIERS
    // ------------------------------------------------------------------------
    wire [7:0] a_low  = r_mcand[7:0];
    wire [7:0] a_high = r_mcand[15:8];
    wire [7:0] b_low  = r_mult[7:0];
    wire [7:0] b_high = r_mult[15:8];

    wire [3:0] mult_done;
    wire signed [15:0] w_p0, w_p1, w_p2, w_p3;

    // Instâncias usam os sinais REGISTRADOS (r_*)
    booth_mult8 mult0 (
        .clk(clk), .rst_n(rst_n), .start(r_start),
        .multiplicand(a_low), .multiplier(b_low), .sign_mode(2'b00),
        .product(w_p0), .done(mult_done[0])
    );

    booth_mult8 mult1 (
        .clk(clk), .rst_n(rst_n), .start(r_start),
        .multiplicand(a_high), .multiplier(b_low), .sign_mode({r_sign_mode[1], 1'b0}),
        .product(w_p1), .done(mult_done[1])
    );

    booth_mult8 mult2 (
        .clk(clk), .rst_n(rst_n), .start(r_start),
        .multiplicand(a_low), .multiplier(b_high), .sign_mode({1'b0, r_sign_mode[0]}),
        .product(w_p2), .done(mult_done[2])
    );

    booth_mult8 mult3 (
        .clk(clk), .rst_n(rst_n), .start(r_start),
        .multiplicand(a_high), .multiplier(b_high), .sign_mode(r_sign_mode),
        .product(w_p3), .done(mult_done[3])
    );

    // ------------------------------------------------------------------------
    // 3. CONTROL & PIPELINED ADDER TREE
    // Removemos a FSM complexa e usamos um sinal de controle simples.
    // ------------------------------------------------------------------------
    
    // Registradores de Pipeline (Stage 1 da soma)
    reg signed [17:0] pipe_sum_p1_p2;
    reg signed [23:0] pipe_base;
    reg [7:0]         pipe_p0_low;
    reg               pipe_valid;

    // Lógica Combinacional do Estágio 1
    // Nota: Como r_sign_mode é registrado na entrada, ele é estável aqui
    wire s1 = w_p1[15] & r_sign_mode[1];
    wire s2 = w_p2[15] & r_sign_mode[0];
    
    // Calcula p1+p2 assim que os dados chegam dos multiplicadores
    wire signed [17:0] calc_sum_p1_p2 = {{2{s1}}, w_p1} + {{2{s2}}, w_p2};

    // Controle de estado simplificado
    // mult_busy indica se estamos processando. 
    // Como os 4 terminam juntos, olhamos apenas um ou o AND.
    reg mult_active;
    
    assign busy = mult_active || pipe_valid;

    always @(posedge clk or negedge rst_n) begin
        if (!rst_n) begin
            mult_active    <= 1'b0;
            pipe_valid     <= 1'b0;
            done           <= 1'b0;
            product        <= 32'b0;
            pipe_sum_p1_p2 <= 18'b0;
            pipe_base      <= 24'b0;
            pipe_p0_low    <= 8'b0;
        end else begin
            done <= 1'b0; // Pulso de 1 ciclo

            // Lógica de ativação baseada no registrador interno r_start
            if (r_start) begin
                mult_active <= 1'b1;
            end

            // Quando a multiplicação termina (sinal done dos submódulos)
            // Capturamos os dados para o registrador de pipeline
            if (mult_active && mult_done[0]) begin
                // STAGE 1: Captura e Primeira Soma
                pipe_sum_p1_p2 <= calc_sum_p1_p2;
                pipe_base      <= {w_p3, w_p0[15:8]};
                pipe_p0_low    <= w_p0[7:0];
                
                pipe_valid     <= 1'b1;
                mult_active    <= 1'b0;
            end else begin
                pipe_valid <= 1'b0;
            end

            // STAGE 2: Soma Final e Saída
            if (pipe_valid) begin
                // A extensão de sinal aqui (bit 17) é barata pois pipe_sum_p1_p2 é um Flip-Flop
                product[31:8] <= pipe_base + {{6{pipe_sum_p1_p2[17]}}, pipe_sum_p1_p2};
                product[7:0]  <= pipe_p0_low;
                done          <= 1'b1;
            end
        end
    end

endmodule
`default_nettype wire

tb/tb_booth_radix8_su_simple.v
`timescale 1ns / 1ps

module tb_booth_radix8_multiplier;

    // ========================================================================
    // Sinais e Parâmetros
    // ========================================================================
    parameter WIDTH = 16;

    reg                  clk;
    reg                  rst_n;
    reg                  start;
    reg  [WIDTH-1:0]     multiplicand; // Tratado genericamente como reg, sinal interpretado pelo modo
    reg  [WIDTH-1:0]     multiplier;
    reg  [1:0]           sign_mode;    // [1]: Multiplicando, [0]: Multiplicador

    wire [2*WIDTH-1:0]   product;
    wire                 done;
    wire                 busy;

    // Contadores para estatísticas
    integer pass_count = 0;
    integer fail_count = 0;

    // ========================================================================
    // Instância do DUT (Device Under Test)
    // ========================================================================
    booth_radix8_multiplier #(
        .WIDTH(WIDTH)
    ) dut (
        .clk(clk),
        .rst_n(rst_n),
        .start(start),
        .multiplicand(multiplicand),
        .multiplier(multiplier),
        .sign_mode(sign_mode),
        .product(product),
        .done(done),
        .busy(busy)
    );

    // ========================================================================
    // Geração de Clock (10ns período = 100MHz)
    // ========================================================================
    always #5 clk = ~clk;

    // ========================================================================
    // Procedimento de Teste Principal
    // ========================================================================
    initial begin
        // Configuração de arquivo de onda (para GTKWave/Simuladores)
        $dumpfile("booth_mult.vcd");
        $dumpvars(0, tb_booth_radix8_multiplier);

        // Inicialização
        clk = 0;
        rst_n = 0;
        start = 0;
        multiplicand = 0;
        multiplier = 0;
        sign_mode = 0;

        // Reset
        #20 rst_n = 1;
        #20;

        $display("=== Iniciando Testes do Multiplicador Booth Radix-8 (16-bit) ===");

        // --------------------------------------------------------------------
        // 1. Testes Básicos (Sanity Check)
        // --------------------------------------------------------------------
        $display("\n--- Testes Básicos ---");
        run_test(16'd10, 16'd5, 2'b00);   // 10 * 5 (Unsigned)
        run_test(16'd10, 16'd5, 2'b11);   // 10 * 5 (Signed)
        run_test(-16'd10, 16'd5, 2'b11);  // -10 * 5 (Signed)

        // --------------------------------------------------------------------
        // 2. Testes de Corner Cases (Casos de Borda)
        // --------------------------------------------------------------------
        $display("\n--- Testes de Corner Cases ---");

        // Zeros
        run_test(16'd0, 16'd1234, 2'b00);
        run_test(16'd5678, 16'd0, 2'b11);

        // Máximo Positivo (Signed) -> 32767 (0x7FFF)
        run_test(16'h7FFF, 16'h7FFF, 2'b11); // Max * Max
        run_test(16'h7FFF, 16'd1, 2'b11);

        // Máximo Negativo (Signed) -> -32768 (0x8000)
        // Este é um teste crítico para Booth, pois -Max não tem complemento de 2 positivo simétrico
        run_test(16'h8000, 16'd1, 2'b11);    // -32768 * 1
        run_test(16'h8000, 16'h7FFF, 2'b11); // -32768 * 32767
        run_test(16'h8000, 16'h8000, 2'b11); // -32768 * -32768 (Deve dar positivo grande)

        // Máximo Unsigned -> 65535 (0xFFFF)
        run_test(16'hFFFF, 16'hFFFF, 2'b00);
        run_test(16'hFFFF, 16'd0, 2'b00);

        // --------------------------------------------------------------------
        // 3. Testes de Modos Mistos
        // --------------------------------------------------------------------
        $display("\n--- Testes de Modos Mistos ---");
        // Mode 10: Multiplicando Signed, Multiplicador Unsigned
        // -10 (0xFFF6) * 10 (0x000A) = -100
        run_test(16'hFFF6, 16'h000A, 2'b10);

        // Mode 01: Multiplicando Unsigned, Multiplicador Signed
        // 10 (0x000A) * -10 (0xFFF6) = -100
        run_test(16'h000A, 16'hFFF6, 2'b01);

        // --------------------------------------------------------------------
        // 4. Testes Aleatórios
        // --------------------------------------------------------------------
        $display("\n--- Testes Aleatórios (200 iterações) ---");
        repeat (50) begin
            // Random Unsigned
            run_test($random, $random, 2'b00);
            // Random Signed
            run_test($random, $random, 2'b11);
            // Random Mixed
            run_test($random, $random, 2'b10);
            run_test($random, $random, 2'b01);
        end

        // ====================================================================
        // Resultado Final
        // ====================================================================
        $display("\n=======================================================");
        $display("RESULTADO FINAL:");
        $display("Passaram: %0d", pass_count);
        $display("Falharam: %0d", fail_count);
        $display("=======================================================");

        if (fail_count == 0)
            $display("SUCESSO: O design passou em todos os testes!");
        else
            $display("FALHA: Erros encontrados. Verifique o log.");

        $finish;
    end

    // ========================================================================
    // Task: Executa um teste individual
    // ========================================================================
    task run_test;
        input [WIDTH-1:0] in_a;
        input [WIDTH-1:0] in_b;
        input [1:0]       mode;

        reg signed [2*WIDTH-1:0] expected_product;

        // Variáveis temporárias estendidas para cálculo de referência correto
        reg signed [2*WIDTH-1:0] a_ext;
        reg signed [2*WIDTH-1:0] b_ext;

        begin
            // 1. Calcular o Resultado Esperado (Golden Model)
            // Estender os sinais baseado no modo antes de multiplicar

            // Tratamento do A (Multiplicando) - Mode[1]
            if (mode[1]) a_ext = $signed(in_a);      // Sign extend
            else         a_ext = $signed({16'b0, in_a}); // Zero extend

            // Tratamento do B (Multiplicador) - Mode[0]
            if (mode[0]) b_ext = $signed(in_b);      // Sign extend
            else         b_ext = $signed({16'b0, in_b}); // Zero extend

            expected_product = a_ext * b_ext;

            // 2. Aplicar estímulos ao DUT
            @(posedge clk);
            wait(!busy); // Garantir que não está ocupado (embora start force reinicio)

            multiplicand <= in_a;
            multiplier   <= in_b;
            sign_mode    <= mode;
            start        <= 1'b1;

            @(posedge clk);
            start        <= 1'b0;

            // 3. Esperar conclusão
            // O DUT leva alguns ciclos. Usamos wait(done)
            wait(done);
            @(negedge clk); // Verificar na borda de descida para estabilidade

            // 4. Verificar Resultado
            if (product !== expected_product) begin
                $display("ERRO no tempo %0t:", $time);
                $display("  Mode: %b | A: %h (%0d) | B: %h (%0d)",
                         mode, in_a, $signed(in_a), in_b, $signed(in_b));
                $display("  Esperado: %h (%0d)", expected_product, expected_product);
                $display("  Obtido:   %h (%0d)", product, product);
                fail_count = fail_count + 1;
            end else begin
                pass_count = pass_count + 1;
            end

            // Pequeno atraso entre testes
            repeat(2) @(posedge clk);
        end
    endtask

endmodule

sim/booth_radix8_multiplier_su_7_linear_155.vcd
$date
	Wed Dec 10 14:10:17 2025
$end
$version
	Icarus Verilog
$end
$timescale
	1ps
$end
$scope module tb_booth_radix8_multiplier $end
$var wire 32 ! product [31:0] $end
$var wire 1 " done $end
$var wire 1 # busy $end
$var parameter 32 $ WIDTH $end
$var reg 1 % clk $end
$var reg 16 & multiplicand [15:0] $end
$var reg 16 ' multiplier [15:0] $end
$var reg 1 ( rst_n $end
$var reg 2 ) sign_mode [1:0] $end
$var reg 1 * start $end
$var integer 32 + fail_count [31:0] $end
$var integer 32 , pass_count [31:0] $end
$scope module dut $end
$var wire 1 # busy $end
$var wire 1 % clk $end
$var wire 16 - multiplicand [15:0] $end
$var wire 16 . multiplier [15:0] $end
$var wire 1 ( rst_n $end
$var wire 1 / s1 $end
$var wire 1 0 s2 $end
$var wire 2 1 sign_mode [1:0] $end
$var wire 1 * start $end
$var wire 16 2 w_p3 [15:0] $end
$var wire 16 3 w_p2 [15:0] $end
$var wire 16 4 w_p1 [15:0] $end
$var wire 16 5 w_p0 [15:0] $end
$var wire 4 6 mult_done [3:0] $end
$var wire 18 7 calc_sum_p1_p2 [17:0] $end
$var wire 8 8 b_low [7:0] $end
$var wire 8 9 b_high [7:0] $end
$var wire 8 : a_low [7:0] $end
$var wire 8 ; a_high [7:0] $end
$var parameter 32 < WIDTH $end
$var reg 1 " done $end
$var reg 1 = mult_active $end
$var reg 24 > pipe_base [23:0] $end
$var reg 8 ? pipe_p0_low [7:0] $end
$var reg 18 @ pipe_sum_p1_p2 [17:0] $end
$var reg 1 A pipe_valid $end
$var reg 32 B product [31:0] $end
$var reg 16 C r_mcand [15:0] $end
$var reg 16 D r_mult [15:0] $end
$var reg 2 E r_sign_mode [1:0] $end
$var reg 1 F r_start $end
$scope module mult0 $end
$var wire 1 % clk $end
$var wire 1 G done $end
$var wire 1 H inv $end
$var wire 11 I m_1x [10:0] $end
$var wire 8 J multiplicand [7:0] $end
$var wire 8 K multiplier [7:0] $end
$var wire 11 L operand_inv [10:0] $end
$var wire 1 ( rst_n $end
$var wire 1 M sign_bit_a $end
$var wire 1 N sign_bit_b $end
$var wire 2 O sign_mode [1:0] $end
$var wire 1 F start $end
$var wire 11 P sum_result [10:0] $end
$var wire 16 Q product [15:0] $end
$var wire 21 R prod_reg_init [20:0] $end
$var wire 11 S mcand_extended [10:0] $end
$var wire 11 T m_4x [10:0] $end
$var wire 11 U m_2x [10:0] $end
$var wire 11 V calc_3x [10:0] $end
$var wire 4 W booth_bits [3:0] $end
$var wire 11 X acc_upper [10:0] $end
$var parameter 32 Y ACC_WIDTH $end
$var parameter 32 Z REG_WIDTH $end
$var parameter 32 [ SHIFT_BITS $end
$var parameter 32 \ WIDTH $end
$var reg 1 ] active $end
$var reg 4 ^ iter_shift [3:0] $end
$var reg 11 _ m_3x_reg [10:0] $end
$var reg 11 ` mag_sel [10:0] $end
$var reg 11 a mcand_ext_reg [10:0] $end
$var reg 21 b prod_reg [20:0] $end
$var reg 1 c sel_1x $end
$var reg 1 d sel_2x $end
$var reg 1 e sel_3x $end
$var reg 1 f sel_4x $end
$upscope $end
$scope module mult1 $end
$var wire 1 % clk $end
$var wire 1 g done $end
$var wire 1 h inv $end
$var wire 11 i m_1x [10:0] $end
$var wire 8 j multiplicand [7:0] $end
$var wire 8 k multiplier [7:0] $end
$var wire 11 l operand_inv [10:0] $end
$var wire 1 ( rst_n $end
$var wire 1 m sign_bit_a $end
$var wire 1 n sign_bit_b $end
$var wire 2 o sign_mode [1:0] $end
$var wire 1 F start $end
$var wire 11 p sum_result [10:0] $end
$var wire 16 q product [15:0] $end
$var wire 21 r prod_reg_init [20:0] $end
$var wire 11 s mcand_extended [10:0] $end
$var wire 11 t m_4x [10:0] $end
$var wire 11 u m_2x [10:0] $end
$var wire 11 v calc_3x [10:0] $end
$var wire 4 w booth_bits [3:0] $end
$var wire 11 x acc_upper [10:0] $end
$var parameter 32 y ACC_WIDTH $end
$var parameter 32 z REG_WIDTH $end
$var parameter 32 { SHIFT_BITS $end
$var parameter 32 | WIDTH $end
$var reg 1 } active $end
$var reg 4 ~ iter_shift [3:0] $end
$var reg 11 !" m_3x_reg [10:0] $end
$var reg 11 "" mag_sel [10:0] $end
$var reg 11 #" mcand_ext_reg [10:0] $end
$var reg 21 $" prod_reg [20:0] $end
$var reg 1 %" sel_1x $end
$var reg 1 &" sel_2x $end
$var reg 1 '" sel_3x $end
$var reg 1 (" sel_4x $end
$upscope $end
$scope module mult2 $end
$var wire 1 % clk $end
$var wire 1 )" done $end
$var wire 1 *" inv $end
$var wire 11 +" m_1x [10:0] $end
$var wire 8 ," multiplicand [7:0] $end
$var wire 8 -" multiplier [7:0] $end
$var wire 11 ." operand_inv [10:0] $end
$var wire 1 ( rst_n $end
$var wire 1 /" sign_bit_a $end
$var wire 1 0" sign_bit_b $end
$var wire 2 1" sign_mode [1:0] $end
$var wire 1 F start $end
$var wire 11 2" sum_result [10:0] $end
$var wire 16 3" product [15:0] $end
$var wire 21 4" prod_reg_init [20:0] $end
$var wire 11 5" mcand_extended [10:0] $end
$var wire 11 6" m_4x [10:0] $end
$var wire 11 7" m_2x [10:0] $end
$var wire 11 8" calc_3x [10:0] $end
$var wire 4 9" booth_bits [3:0] $end
$var wire 11 :" acc_upper [10:0] $end
$var parameter 32 ;" ACC_WIDTH $end
$var parameter 32 <" REG_WIDTH $end
$var parameter 32 =" SHIFT_BITS $end
$var parameter 32 >" WIDTH $end
$var reg 1 ?" active $end
$var reg 4 @" iter_shift [3:0] $end
$var reg 11 A" m_3x_reg [10:0] $end
$var reg 11 B" mag_sel [10:0] $end
$var reg 11 C" mcand_ext_reg [10:0] $end
$var reg 21 D" prod_reg [20:0] $end
$var reg 1 E" sel_1x $end
$var reg 1 F" sel_2x $end
$var reg 1 G" sel_3x $end
$var reg 1 H" sel_4x $end
$upscope $end
$scope module mult3 $end
$var wire 1 % clk $end
$var wire 1 I" done $end
$var wire 1 J" inv $end
$var wire 11 K" m_1x [10:0] $end
$var wire 8 L" multiplicand [7:0] $end
$var wire 8 M" multiplier [7:0] $end
$var wire 11 N" operand_inv [10:0] $end
$var wire 1 ( rst_n $end
$var wire 1 O" sign_bit_a $end
$var wire 1 P" sign_bit_b $end
$var wire 2 Q" sign_mode [1:0] $end
$var wire 1 F start $end
$var wire 11 R" sum_result [10:0] $end
$var wire 16 S" product [15:0] $end
$var wire 21 T" prod_reg_init [20:0] $end
$var wire 11 U" mcand_extended [10:0] $end
$var wire 11 V" m_4x [10:0] $end
$var wire 11 W" m_2x [10:0] $end
$var wire 11 X" calc_3x [10:0] $end
$var wire 4 Y" booth_bits [3:0] $end
$var wire 11 Z" acc_upper [10:0] $end
$var parameter 32 [" ACC_WIDTH $end
$var parameter 32 \" REG_WIDTH $end
$var parameter 32 ]" SHIFT_BITS $end
$var parameter 32 ^" WIDTH $end
$var reg 1 _" active $end
$var reg 4 `" iter_shift [3:0] $end
$var reg 11 a" m_3x_reg [10:0] $end
$var reg 11 b" mag_sel [10:0] $end
$var reg 11 c" mcand_ext_reg [10:0] $end
$var reg 21 d" prod_reg [20:0] $end
$var reg 1 e" sel_1x $end
$var reg 1 f" sel_2x $end
$var reg 1 g" sel_3x $end
$var reg 1 h" sel_4x $end
$upscope $end
$upscope $end
$scope task run_test $end
$var reg 32 i" a_ext [31:0] $end
$var reg 32 j" b_ext [31:0] $end
$var reg 32 k" expected_product [31:0] $end
$var reg 16 l" in_a [15:0] $end
$var reg 16 m" in_b [15:0] $end
$var reg 2 n" mode [1:0] $end
$upscope $end
$upscope $end
$enddefinitions $end
$comment Show the parameter values. $end
$dumpall
b1000 ^"
b1001 ]"
b10101 \"
b1011 ["
b1000 >"
b1001 ="
b10101 <"
b1011 ;"
b1000 |
b1001 {
b10101 z
b1011 y
b1000 \
b1001 [
b10101 Z
b1011 Y
b10000 <
b10000 $
$end
#0
$dumpvars
bx n"
bx m"
bx l"
bx k"
bx j"
bx i"
0h"
0g"
0f"
0e"
b0 d"
b0 c"
b0 b"
b0 a"
b0 `"
0_"
b0 Z"
b0 Y"
b0 X"
b0 W"
b0 V"
b0 U"
b0 T"
b0 S"
b0 R"
b0 Q"
0P"
0O"
b0 N"
b0 M"
b0 L"
b0 K"
0J"
0I"
0H"
0G"
0F"
0E"
b0 D"
b0 C"
b0 B"
b0 A"
b0 @"
0?"
b0 :"
b0 9"
b0 8"
b0 7"
b0 6"
b0 5"
b0 4"
b0 3"
b0 2"
b0 1"
00"
0/"
b0 ."
b0 -"
b0 ,"
b0 +"
0*"
0)"
0("
0'"
0&"
0%"
b0 $"
b0 #"
b0 ""
b0 !"
b0 ~
0}
b0 x
b0 w
b0 v
b0 u
b0 t
b0 s
b0 r
b0 q
b0 p
b0 o
0n
0m
b0 l
b0 k
b0 j
b0 i
0h
0g
0f
0e
0d
0c
b0 b
b0 a
b0 `
b0 _
b0 ^
0]
b0 X
b0 W
b0 V
b0 U
b0 T
b0 S
b0 R
b0 Q
b0 P
b0 O
0N
0M
b0 L
b0 K
b0 J
b0 I
0H
0G
0F
b0 E
b0 D
b0 C
b0 B
0A
b0 @
b0 ?
b0 >
0=
b0 ;
b0 :
b0 9
b0 8
b0 7
b0 6
b0 5
b0 4
b0 3
b0 2
b0 1
00
0/
b0 .
b0 -
b0 ,
b0 +
0*
b0 )
0(
b0 '
b0 &
0%
0#
0"
b0 !
$end
#5000
1%
#10000
0%
#15000
1%
#20000
0%
1(
#25000
1%
#30000
0%
#35000
1%
#40000
0%
b110010 k"
b101 j"
b1010 i"
b0 n"
b101 m"
b1010 l"
#45000
1*
b101 '
b101 .
b1010 &
b1010 -
1%
#50000
0%
#55000
b1010 R
b1010 r
b11110 V
b1010 S
b11110 8"
b1010 5"
b101 8
b101 K
b101 k
b1010 :
b1010 J
b1010 ,"
b101 D
b1010 C
1F
0*
1%
#60000
0%
#65000
b11111111111 l
b0 p
b11111100010 P
b11111100001 L
1h
1H
b11110 `
b10100 7"
b101000 6"
1'"
b101 7
1e
b10100 U
b101000 T
1#
b1010 w
b101 4
b101 q
b1010 W
b101 5
b101 Q
1=
0F
b1000 `"
1_"
b11110 A"
b1010 +"
b1010 C"
b1000 @"
1?"
b1010 $"
b1000 ~
1}
b1010 b
b11110 _
b1010 I
b1010 a
b1000 ^
1]
1%
#70000
0%
#75000
b1010 L
b0 l
b0 p
0H
b1010 `
0h
0e
1c
0'"
1%"
b0 7
b1 W
b110 P
b11111111100 X
b1111100010000000 5
b1111100010000000 Q
b1 w
b0 4
b0 q
b100 ^
b111111111000100000001 b
b100 ~
b1 $"
b100 @"
b100 `"
1%
#80000
0%
#85000
b0 L
b0 `
0%"
0c
b0 w
b0 W
b0 P
b0 X
b110010000 5
b110010000 Q
b10 `"
b10 @"
b10 ~
b0 $"
b10 ^
b1100100000 b
1%
#90000
0%
#95000
b10100 P
b10100 L
b10100 `
b1111 6
1G
1d
1g
1)"
1I"
b100 W
b110010 5
b110010 Q
b1 ^
b1100100 b
b1 ~
b1 @"
b1 `"
1%
#100000
0%
#105000
b0 6
0I"
0)"
0g
0G
0=
1A
b110010 ?
0_"
0?"
0}
0]
1%
#110000
0%
#115000
0#
1"
b110010 !
b110010 B
0A
1%
#120000
b1 ,
0%
#125000
0"
1%
#130000
0%
#135000
b11 n"
1%
#140000
0%
#145000
1*
b11 )
b11 1
1%
#150000
0%
#155000
b10 o
b1 1"
b11 E
b11 Q"
1F
0*
1%
#160000
0%
#165000
b11111111111 l
b0 p
b11111100010 P
b11111100001 L
1h
1H
b11110 `
1'"
b101 7
1e
0d
b0 6
1#
0I"
0)"
b1010 w
b101 4
b101 q
0g
b1010 W
b101 5
b101 Q
0G
1=
0F
b1000 `"
1_"
b1000 @"
1?"
b1010 $"
b1000 ~
1}
b1010 b
b1000 ^
1]
1%
#170000
0%
#175000
b1010 L
b0 l
b0 p
0H
b1010 `
0h
0e
1c
0'"
1%"
b0 7
b1 W
b110 P
b11111111100 X
b1111100010000000 5
b1111100010000000 Q
b1 w
b0 4
b0 q
b100 ^
b111111111000100000001 b
b100 ~
b1 $"
b100 @"
b100 `"
1%
#180000
0%
#185000
b0 L
b0 `
0%"
0c
b0 w
b0 W
b0 P
b0 X
b110010000 5
b110010000 Q
b10 `"
b10 @"
b10 ~
b0 $"
b10 ^
b1100100000 b
1%
#190000
0%
#195000
b10100 P
b10100 L
b10100 `
b1111 6
1G
1d
1g
1)"
1I"
b100 W
b110010 5
b110010 Q
b1 ^
b1100100 b
b1 ~
b1 @"
b1 `"
1%
#200000
0%
#205000
b0 6
0I"
0)"
0g
0G
0=
1A
0_"
0?"
0}
0]
1%
#210000
0%
#215000
0#
1"
0A
1%
#220000
b10 ,
0%
#225000
0"
1%
#230000
0%
#235000
b11111111111111111111111111001110 k"
b11111111111111111111111111110110 i"
b1111111111110110 l"
1%
#240000
0%
#245000
1*
b1111111111110110 &
b1111111111110110 -
1%
#250000
0%
#255000
1m
1O"
b1011100010 V
b11110110 S
b1011100010 8"
b11110110 5"
b11111111101 v
b11111111111 s
b11111111101 X"
b11111111111 U"
b11110110 :
b11110110 J
b11110110 ,"
b11111111 ;
b11111111 j
b11111111 L"
b1111111111110110 C
1F
0*
1%
#260000
0%
#265000
b11 p
b10 l
b10100011110 P
b10100011101 L
1h
b11111111101 ""
1H
b1011100010 `
b11111111110 W"
b11111111100 V"
b111101100 7"
b1111011000 6"
1'"
b101 7
b11111111110 u
b11111111100 t
1e
0d
b111101100 U
b1111011000 T
b0 6
1#
0I"
0)"
b1010 w
b101 4
b101 q
0g
b1010 W
b101 5
b101 Q
0G
1=
0F
b11111111101 a"
b11111111111 K"
b11111111111 c"
b1000 `"
1_"
b1011100010 A"
b11110110 +"
b11110110 C"
b1000 @"
1?"
b1010 $"
b11111111101 !"
b11111111111 i
b11111111111 #"
b1000 ~
1}
b1010 b
b1011100010 _
b11110110 I
b11110110 a
b1000 ^
1]
1%
#270000
0%
#275000
b11110110 L
b11111111111 p
b11111111111 l
0H
b11110110 `
0h
b11111111111 ""
0e
1c
0'"
1%"
b11000000 7
b1 W
b10011001 P
b11110100011 X
b100011110000000 5
b100011110000000 Q
b1 w
b11000000 4
b11000000 q
b100 ^
b111101000111100000001 b
b100 ~
b110000001 $"
b100 @"
b100 `"
1%
#280000
0%
#285000
b0 l
b0 L
b0 ""
1/
b0 `
0%"
b111111111111011000 7
0c
b0 w
b11111111111 p
b11111111111 x
b1111111111011000 4
b1111111111011000 q
b0 W
b10011 P
b10011 X
b10011001110000 5
b10011001110000 Q
b10 `"
b10 @"
b10 ~
b111111111111110110000 $"
b10 ^
b100110011100000 b
1%
#290000
0%
#295000
b11000010011 L
b11111111100 p
b11111111101 l
1H
b111101100 `
b11111111101 ""
b1111 6
1G
1d
1g
1'"
b111111111111111011 7
1)"
1I"
b1100 W
b11000010110 P
b10 X
b10011001110 5
b10011001110 Q
b110 w
b1111111111111011 4
b1111111111111011 q
b1 ^
b100110011100 b
b1 ~
b111111111111111110110 $"
b1 @"
b1 `"
1%
#300000
0%
#305000
b0 6
0I"
0)"
0g
0G
0=
1A
b11001110 ?
b100 >
b111111111111111011 @
0_"
0?"
0}
0]
1%
#310000
0%
#315000
0#
1"
b11111111111111111111111111001110 !
b11111111111111111111111111001110 B
0A
1%
#320000
b11 ,
0%
#325000
0"
1%
#330000
0%
#335000
b0 k"
b10011010010 j"
b0 i"
b0 n"
b10011010010 m"
b0 l"
1%
#340000
0%
