rtl/booth_radix8_multiplier_su_4_pipeline_144.v
`timescale 1ns / 1ps
`default_nettype none

module booth_core_4cycle (
    input  wire                  clk,
    input  wire                  load,
    input  wire signed [7:0]     multiplicand,
    input  wire signed [7:0]     multiplier,
    input  wire [1:0]            sign_mode,
    output wire signed [15:0]    product,
    output wire                  valid_out
);
    localparam integer WIDTH = 8;
    localparam integer SHIFT_BITS = 9;
    localparam integer ACC_WIDTH = 11;
    localparam integer REG_WIDTH = 21;

    reg signed [REG_WIDTH-1:0] prod_reg;
    reg [2:0] cycle_cnt;
    reg active;

    reg signed [ACC_WIDTH-1:0] m_3x_reg;
    reg signed [ACC_WIDTH-1:0] mcand_ext_reg;

    wire sign_bit_a = sign_mode[1] & multiplicand[WIDTH-1];
    wire signed [ACC_WIDTH-1:0] mcand_extended = { {(ACC_WIDTH-WIDTH){sign_bit_a}}, multiplicand };
    wire signed [ACC_WIDTH-1:0] calc_3x = mcand_extended + (mcand_extended <<< 1);

    wire sign_bit_b = sign_mode[0] & multiplier[WIDTH-1];
    wire [REG_WIDTH-1:0] prod_reg_init = {
        {ACC_WIDTH{1'b0}},
        {(SHIFT_BITS-WIDTH){sign_bit_b}},
        multiplier,
        1'b0
    };

    wire [3:0] booth_bits = prod_reg[3:0];
    wire signed [ACC_WIDTH-1:0] acc_upper = prod_reg[REG_WIDTH-1 : SHIFT_BITS+1];

    reg sel_1x, sel_2x, sel_3x, sel_4x;
    always @(*) begin
        sel_1x = (booth_bits == 4'b0001) || (booth_bits == 4'b0010) || (booth_bits == 4'b1101) || (booth_bits == 4'b1110);
        sel_2x = (booth_bits == 4'b0011) || (booth_bits == 4'b0100) || (booth_bits == 4'b1011) || (booth_bits == 4'b1100);
        sel_3x = (booth_bits == 4'b0101) || (booth_bits == 4'b0110) || (booth_bits == 4'b1001) || (booth_bits == 4'b1010);
        sel_4x = (booth_bits == 4'b0111) || (booth_bits == 4'b1000);
    end

    wire inv = booth_bits[3] & ~(&booth_bits[2:0]);
    wire signed [ACC_WIDTH-1:0] m_1x = mcand_ext_reg;
    wire signed [ACC_WIDTH-1:0] m_2x = mcand_ext_reg <<< 1;
    wire signed [ACC_WIDTH-1:0] m_4x = mcand_ext_reg <<< 2;

    reg signed [ACC_WIDTH-1:0] mag_sel;
    always @(*) begin
        mag_sel = ({ACC_WIDTH{sel_1x}} & m_1x) | ({ACC_WIDTH{sel_2x}} & m_2x) |
                  ({ACC_WIDTH{sel_3x}} & m_3x_reg) | ({ACC_WIDTH{sel_4x}} & m_4x);
    end

    wire signed [ACC_WIDTH-1:0] operand_inv = mag_sel ^ {ACC_WIDTH{inv}};
    wire signed [ACC_WIDTH-1:0] sum_result  = acc_upper + operand_inv + { {(ACC_WIDTH-1){1'b0}}, inv };

    assign valid_out = (cycle_cnt == 3) && active;
    assign product   = prod_reg[16:1];

    always @(posedge clk) begin
        if (load) begin
            active        <= 1'b1;
            cycle_cnt     <= 0;
            mcand_ext_reg <= mcand_extended;
            m_3x_reg      <= calc_3x;
            prod_reg      <= prod_reg_init;
        end else if (active) begin
            prod_reg <= { {3{sum_result[ACC_WIDTH-1]}}, sum_result, prod_reg[SHIFT_BITS:3] };
            if (cycle_cnt == 3) active <= 1'b0;
            else cycle_cnt <= cycle_cnt + 1;
        end
    end
endmodule

module booth_radix8_multiplier #(
    parameter integer WIDTH = 16
)(
    input  wire                         clk,
    input  wire                         rst_n,
    input  wire                         start,
    input  wire signed [WIDTH-1:0]      multiplicand,
    input  wire signed [WIDTH-1:0]      multiplier,
    input  wire [1:0]                   sign_mode,
    output reg  signed [2*WIDTH-1:0]    product,
    output reg                          done,
    output wire                         busy
);

    // 1. INPUT STAGE
    reg r_start_in;
    reg signed [WIDTH-1:0] r_mcand_in, r_mult_in;
    reg [1:0] r_sign_mode_in;

    always @(posedge clk or negedge rst_n) begin
        if (!rst_n) begin
            r_start_in <= 1'b0;
            r_mcand_in <= 0; r_mult_in <= 0; r_sign_mode_in <= 0;
        end else begin
            r_start_in <= start;
            if (start) begin
                r_mcand_in     <= multiplicand;
                r_mult_in      <= multiplier;
                r_sign_mode_in <= sign_mode;
            end
        end
    end

    // 2. DATA BUFFER
    reg signed [WIDTH-1:0] buf_mcand, buf_mult;
    reg [1:0] buf_sign_mode;
    reg buf_valid;

    wire core_ready;
    wire fire_core;

    // CORREÇÃO: Busy agora considera dados em trânsito no registrador de entrada (r_start_in).
    // Se o buffer já tem dados, ou se acabamos de receber um dado novo (r_start_in), estamos ocupados.
    // Isso garante que o testbench pare de enviar até que o buffer esvazie.
    assign busy = buf_valid || r_start_in;

    always @(posedge clk or negedge rst_n) begin
        if (!rst_n) begin
            buf_valid <= 1'b0;
            buf_mcand <= 0; buf_mult <= 0; buf_sign_mode <= 0;
        end else begin
            if (r_start_in) begin
                if (!buf_valid || core_ready) begin
                    buf_mcand     <= r_mcand_in;
                    buf_mult      <= r_mult_in;
                    buf_sign_mode <= r_sign_mode_in;
                    buf_valid     <= 1'b1;
                end
            end else if (fire_core) begin
                buf_valid <= 1'b0;
            end
        end
    end

    // 3. CORE SEQUENCER
    reg [2:0] core_timer;
    reg       core_active;

    assign core_ready = (!core_active) || (core_timer == 3);
    assign fire_core = buf_valid && core_ready;

    reg [1:0] active_sign_mode;

    always @(posedge clk or negedge rst_n) begin
        if (!rst_n) begin
            core_active <= 0;
            core_timer  <= 0;
            active_sign_mode <= 0;
        end else begin
            if (fire_core) begin
                core_active <= 1;
                core_timer  <= 0;
                active_sign_mode <= buf_sign_mode;
            end else if (core_active) begin
                if (core_timer == 3) core_active <= 0;
                else core_timer <= core_timer + 1;
            end
        end
    end

    // 4. INSTANCE CORES
    wire signed [15:0] w_p0, w_p1, w_p2, w_p3;
    wire core_done_pulse;

    booth_core_4cycle u0 (.clk(clk), .load(fire_core), .multiplicand(buf_mcand[7:0]),  .multiplier(buf_mult[7:0]),  .sign_mode(2'b00), .product(w_p0), .valid_out(core_done_pulse));
    booth_core_4cycle u1 (.clk(clk), .load(fire_core), .multiplicand(buf_mcand[15:8]), .multiplier(buf_mult[7:0]),  .sign_mode({buf_sign_mode[1], 1'b0}), .product(w_p1), .valid_out());
    booth_core_4cycle u2 (.clk(clk), .load(fire_core), .multiplicand(buf_mcand[7:0]),  .multiplier(buf_mult[15:8]), .sign_mode({1'b0, buf_sign_mode[0]}), .product(w_p2), .valid_out());
    booth_core_4cycle u3 (.clk(clk), .load(fire_core), .multiplicand(buf_mcand[15:8]), .multiplier(buf_mult[15:8]), .sign_mode(buf_sign_mode), .product(w_p3), .valid_out());

    // 5. OUTPUT RECONSTRUCTION
    reg signed [17:0] pipe_sum_p1_p2;
    reg signed [23:0] pipe_base;
    reg [7:0]         pipe_p0_low;
    reg               pipe_valid;

    wire s1 = w_p1[15] & active_sign_mode[1];
    wire s2 = w_p2[15] & active_sign_mode[0];
    wire signed [17:0] calc_sum_p1_p2 = {{2{s1}}, w_p1} + {{2{s2}}, w_p2};

    always @(posedge clk or negedge rst_n) begin
        if (!rst_n) begin
            pipe_valid <= 0;
            pipe_sum_p1_p2 <= 0; pipe_base <= 0; pipe_p0_low <= 0;
            product <= 0; done <= 0;
        end else begin
            done <= 0;
            if (core_done_pulse) begin
                pipe_sum_p1_p2 <= calc_sum_p1_p2;
                pipe_base      <= {w_p3, w_p0[15:8]};
                pipe_p0_low    <= w_p0[7:0];
                pipe_valid     <= 1;
            end else begin
                pipe_valid <= 0;
            end

            if (pipe_valid) begin
                product[31:8] <= pipe_base + {{6{pipe_sum_p1_p2[17]}}, pipe_sum_p1_p2};
                product[7:0]  <= pipe_p0_low;
                done          <= 1;
            end
        end
    end
endmodule
`default_nettype wire

tb/tb_booth_radix8_pipeline.v
`timescale 1ns / 1ps

module tb_booth_pipeline;

    // Sinais
    reg clk;
    reg rst_n;
    reg start;
    reg signed [15:0] multiplicand;
    reg signed [15:0] multiplier;
    reg [1:0] sign_mode;
    
    wire signed [31:0] product;
    wire done;
    wire busy;

    // Instanciação do DUT (Device Under Test)
    booth_radix8_multiplier #( .WIDTH(16) ) dut (
        .clk(clk), .rst_n(rst_n), .start(start),
        .multiplicand(multiplicand), .multiplier(multiplier), .sign_mode(sign_mode),
        .product(product), .done(done), .busy(busy)
    );

    // ========================================================================
    // GERAÇÃO DE VCD (ADICIONADO AQUI)
    // ========================================================================
    initial begin
        $dumpfile("booth_pipeline.vcd"); // Nome do arquivo de saída
        $dumpvars(0, tb_booth_pipeline); // 0 = Salva todos os sinais recursivamente
    end

    // Estruturas de Teste
    parameter FIFO_DEPTH = 256; 
    reg signed [31:0] fifo_expected [0:FIFO_DEPTH-1];
    integer           fifo_id       [0:FIFO_DEPTH-1];
    integer write_ptr, read_ptr, error_count, tx_count;

    always #3.333 clk = ~clk; 

    // Task de Estímulo
    task drive_transaction;
        input signed [15:0] in_a;
        input signed [15:0] in_b;
        input [1:0]         in_mode;
        
        reg signed [31:0] op_a_32;
        reg signed [31:0] op_b_32;
        begin
            // Espera Busy
            while (busy) @(negedge clk);

            // Calcula Expected
            if (in_mode[1]) op_a_32 = {{16{in_a[15]}}, in_a};
            else            op_a_32 = {16'b0, in_a};
            
            if (in_mode[0]) op_b_32 = {{16{in_b[15]}}, in_b};
            else            op_b_32 = {16'b0, in_b};
            
            fifo_expected[write_ptr] = op_a_32 * op_b_32;
            fifo_id[write_ptr]       = tx_count;
            write_ptr = (write_ptr + 1) % FIFO_DEPTH;
            tx_count = tx_count + 1;

            // Envia ao DUT
            start        <= 1'b1;
            multiplicand <= in_a;
            multiplier   <= in_b;
            sign_mode    <= in_mode;
            @(negedge clk);
            start <= 1'b0;
        end
    endtask

    // Monitor
    always @(posedge clk) begin
        if (done) begin
            if (read_ptr == write_ptr) begin
                $display("ERRO: Done inesperado (FIFO vazia)");
                error_count = error_count + 1;
            end else begin
                if (product !== fifo_expected[read_ptr]) begin
                    $display("ERRO [ID %0d]: Esperado %d, Recebido %d", 
                        fifo_id[read_ptr], fifo_expected[read_ptr], product);
                    error_count = error_count + 1;
                end
                read_ptr = (read_ptr + 1) % FIFO_DEPTH;
            end
        end
    end

    integer i;
    reg signed [15:0] ra, rb;

    initial begin
        clk = 0; rst_n = 0; start = 0;
        write_ptr = 0; read_ptr = 0; error_count = 0; tx_count = 0;

        #20 rst_n = 1; #20;

        $display("=== INICIO TESTE COM VCD ===");
        
        // 1. Casos de Canto
        drive_transaction(16'd10, 16'd10, 2'b11); 
        drive_transaction(16'd32767, 16'd1, 2'b11);    
        drive_transaction(-16'd32768, 16'd1, 2'b11);   

        // 2. Burst (Pipeline Stress)
        for (i = 0; i < 50; i = i + 1) begin
            ra = $random; rb = $random;
            drive_transaction(ra, rb, 2'b11);
        end

        #2000;
        
        if (read_ptr != write_ptr) $display("TIMEOUT: Itens pendentes na FIFO.");
        
        if (error_count == 0 && read_ptr == write_ptr) 
            $display("SUCESSO: VCD gerado. Abra 'booth_pipeline.vcd' no GTKWave.");
        else 
            $display("FALHA: %0d erros encontrados.", error_count);
            
        $finish;
    end
endmodule

sim/booth_radix8_multiplier_su_4_pipeline_144.vcd
$date
	Wed Dec 10 13:58:51 2025
$end
$version
	Icarus Verilog
$end
$timescale
	1ps
$end
$scope module tb_booth_pipeline $end
$var wire 32 ! product [31:0] $end
$var wire 1 " done $end
$var wire 1 # busy $end
$var parameter 32 $ FIFO_DEPTH $end
$var reg 1 % clk $end
$var reg 16 & multiplicand [15:0] $end
$var reg 16 ' multiplier [15:0] $end
$var reg 16 ( ra [15:0] $end
$var reg 16 ) rb [15:0] $end
$var reg 1 * rst_n $end
$var reg 2 + sign_mode [1:0] $end
$var reg 1 , start $end
$var integer 32 - error_count [31:0] $end
$var integer 32 . i [31:0] $end
$var integer 32 / read_ptr [31:0] $end
$var integer 32 0 tx_count [31:0] $end
$var integer 32 1 write_ptr [31:0] $end
$scope module dut $end
$var wire 1 # busy $end
$var wire 1 % clk $end
$var wire 1 2 core_ready $end
$var wire 1 3 fire_core $end
$var wire 16 4 multiplicand [15:0] $end
$var wire 16 5 multiplier [15:0] $end
$var wire 1 * rst_n $end
$var wire 1 6 s1 $end
$var wire 1 7 s2 $end
$var wire 2 8 sign_mode [1:0] $end
$var wire 1 , start $end
$var wire 16 9 w_p3 [15:0] $end
$var wire 16 : w_p2 [15:0] $end
$var wire 16 ; w_p1 [15:0] $end
$var wire 16 < w_p0 [15:0] $end
$var wire 1 = core_done_pulse $end
$var wire 18 > calc_sum_p1_p2 [17:0] $end
$var parameter 32 ? WIDTH $end
$var reg 2 @ active_sign_mode [1:0] $end
$var reg 16 A buf_mcand [15:0] $end
$var reg 16 B buf_mult [15:0] $end
$var reg 2 C buf_sign_mode [1:0] $end
$var reg 1 D buf_valid $end
$var reg 1 E core_active $end
$var reg 3 F core_timer [2:0] $end
$var reg 1 " done $end
$var reg 24 G pipe_base [23:0] $end
$var reg 8 H pipe_p0_low [7:0] $end
$var reg 18 I pipe_sum_p1_p2 [17:0] $end
$var reg 1 J pipe_valid $end
$var reg 32 K product [31:0] $end
$var reg 16 L r_mcand_in [15:0] $end
$var reg 16 M r_mult_in [15:0] $end
$var reg 2 N r_sign_mode_in [1:0] $end
$var reg 1 O r_start_in $end
$scope module u0 $end
$var wire 1 % clk $end
$var wire 1 P inv $end
$var wire 1 3 load $end
$var wire 11 Q m_1x [10:0] $end
$var wire 8 R multiplicand [7:0] $end
$var wire 8 S multiplier [7:0] $end
$var wire 11 T operand_inv [10:0] $end
$var wire 1 U sign_bit_a $end
$var wire 1 V sign_bit_b $end
$var wire 2 W sign_mode [1:0] $end
$var wire 1 = valid_out $end
$var wire 11 X sum_result [10:0] $end
$var wire 16 Y product [15:0] $end
$var wire 21 Z prod_reg_init [20:0] $end
$var wire 11 [ mcand_extended [10:0] $end
$var wire 11 \ m_4x [10:0] $end
$var wire 11 ] m_2x [10:0] $end
$var wire 11 ^ calc_3x [10:0] $end
$var wire 4 _ booth_bits [3:0] $end
$var wire 11 ` acc_upper [10:0] $end
$var parameter 32 a ACC_WIDTH $end
$var parameter 32 b REG_WIDTH $end
$var parameter 32 c SHIFT_BITS $end
$var parameter 32 d WIDTH $end
$var reg 1 e active $end
$var reg 3 f cycle_cnt [2:0] $end
$var reg 11 g m_3x_reg [10:0] $end
$var reg 11 h mag_sel [10:0] $end
$var reg 11 i mcand_ext_reg [10:0] $end
$var reg 21 j prod_reg [20:0] $end
$var reg 1 k sel_1x $end
$var reg 1 l sel_2x $end
$var reg 1 m sel_3x $end
$var reg 1 n sel_4x $end
$upscope $end
$scope module u1 $end
$var wire 1 % clk $end
$var wire 1 o inv $end
$var wire 1 3 load $end
$var wire 11 p m_1x [10:0] $end
$var wire 8 q multiplicand [7:0] $end
$var wire 8 r multiplier [7:0] $end
$var wire 11 s operand_inv [10:0] $end
$var wire 1 t sign_bit_a $end
$var wire 1 u sign_bit_b $end
$var wire 2 v sign_mode [1:0] $end
$var wire 1 w valid_out $end
$var wire 11 x sum_result [10:0] $end
$var wire 16 y product [15:0] $end
$var wire 21 z prod_reg_init [20:0] $end
$var wire 11 { mcand_extended [10:0] $end
$var wire 11 | m_4x [10:0] $end
$var wire 11 } m_2x [10:0] $end
$var wire 11 ~ calc_3x [10:0] $end
$var wire 4 !" booth_bits [3:0] $end
$var wire 11 "" acc_upper [10:0] $end
$var parameter 32 #" ACC_WIDTH $end
$var parameter 32 $" REG_WIDTH $end
$var parameter 32 %" SHIFT_BITS $end
$var parameter 32 &" WIDTH $end
$var reg 1 '" active $end
$var reg 3 (" cycle_cnt [2:0] $end
$var reg 11 )" m_3x_reg [10:0] $end
$var reg 11 *" mag_sel [10:0] $end
$var reg 11 +" mcand_ext_reg [10:0] $end
$var reg 21 ," prod_reg [20:0] $end
$var reg 1 -" sel_1x $end
$var reg 1 ." sel_2x $end
$var reg 1 /" sel_3x $end
$var reg 1 0" sel_4x $end
$upscope $end
$scope module u2 $end
$var wire 1 % clk $end
$var wire 1 1" inv $end
$var wire 1 3 load $end
$var wire 11 2" m_1x [10:0] $end
$var wire 8 3" multiplicand [7:0] $end
$var wire 8 4" multiplier [7:0] $end
$var wire 11 5" operand_inv [10:0] $end
$var wire 1 6" sign_bit_a $end
$var wire 1 7" sign_bit_b $end
$var wire 2 8" sign_mode [1:0] $end
$var wire 1 9" valid_out $end
$var wire 11 :" sum_result [10:0] $end
$var wire 16 ;" product [15:0] $end
$var wire 21 <" prod_reg_init [20:0] $end
$var wire 11 =" mcand_extended [10:0] $end
$var wire 11 >" m_4x [10:0] $end
$var wire 11 ?" m_2x [10:0] $end
$var wire 11 @" calc_3x [10:0] $end
$var wire 4 A" booth_bits [3:0] $end
$var wire 11 B" acc_upper [10:0] $end
$var parameter 32 C" ACC_WIDTH $end
$var parameter 32 D" REG_WIDTH $end
$var parameter 32 E" SHIFT_BITS $end
$var parameter 32 F" WIDTH $end
$var reg 1 G" active $end
$var reg 3 H" cycle_cnt [2:0] $end
$var reg 11 I" m_3x_reg [10:0] $end
$var reg 11 J" mag_sel [10:0] $end
$var reg 11 K" mcand_ext_reg [10:0] $end
$var reg 21 L" prod_reg [20:0] $end
$var reg 1 M" sel_1x $end
$var reg 1 N" sel_2x $end
$var reg 1 O" sel_3x $end
$var reg 1 P" sel_4x $end
$upscope $end
$scope module u3 $end
$var wire 1 % clk $end
$var wire 1 Q" inv $end
$var wire 1 3 load $end
$var wire 11 R" m_1x [10:0] $end
$var wire 8 S" multiplicand [7:0] $end
$var wire 8 T" multiplier [7:0] $end
$var wire 11 U" operand_inv [10:0] $end
$var wire 1 V" sign_bit_a $end
$var wire 1 W" sign_bit_b $end
$var wire 2 X" sign_mode [1:0] $end
$var wire 1 Y" valid_out $end
$var wire 11 Z" sum_result [10:0] $end
$var wire 16 [" product [15:0] $end
$var wire 21 \" prod_reg_init [20:0] $end
$var wire 11 ]" mcand_extended [10:0] $end
$var wire 11 ^" m_4x [10:0] $end
$var wire 11 _" m_2x [10:0] $end
$var wire 11 `" calc_3x [10:0] $end
$var wire 4 a" booth_bits [3:0] $end
$var wire 11 b" acc_upper [10:0] $end
$var parameter 32 c" ACC_WIDTH $end
$var parameter 32 d" REG_WIDTH $end
$var parameter 32 e" SHIFT_BITS $end
$var parameter 32 f" WIDTH $end
$var reg 1 g" active $end
$var reg 3 h" cycle_cnt [2:0] $end
$var reg 11 i" m_3x_reg [10:0] $end
$var reg 11 j" mag_sel [10:0] $end
$var reg 11 k" mcand_ext_reg [10:0] $end
$var reg 21 l" prod_reg [20:0] $end
$var reg 1 m" sel_1x $end
$var reg 1 n" sel_2x $end
$var reg 1 o" sel_3x $end
$var reg 1 p" sel_4x $end
$upscope $end
$upscope $end
$scope task drive_transaction $end
$var reg 16 q" in_a [15:0] $end
$var reg 16 r" in_b [15:0] $end
$var reg 2 s" in_mode [1:0] $end
$var reg 32 t" op_a_32 [31:0] $end
$var reg 32 u" op_b_32 [31:0] $end
$upscope $end
$upscope $end
$enddefinitions $end
$comment Show the parameter values. $end
$dumpall
b1000 f"
b1001 e"
b10101 d"
b1011 c"
b1000 F"
b1001 E"
b10101 D"
b1011 C"
b1000 &"
b1001 %"
b10101 $"
b1011 #"
b1000 d
b1001 c
b10101 b
b1011 a
b10000 ?
b100000000 $
$end
#0
$dumpvars
bx u"
bx t"
bx s"
bx r"
bx q"
xp"
xo"
xn"
xm"
bx l"
bx k"
bx j"
bx i"
bx h"
xg"
bx b"
bx a"
b0 `"
bx0 _"
bx00 ^"
b0 ]"
b0 \"
bx ["
bx Z"
xY"
b0 X"
0W"
0V"
bx U"
b0 T"
b0 S"
bx R"
xQ"
xP"
xO"
xN"
xM"
bx L"
bx K"
bx J"
bx I"
bx H"
xG"
bx B"
bx A"
b0 @"
bx0 ?"
bx00 >"
b0 ="
b0 <"
bx ;"
bx :"
x9"
b0 8"
07"
06"
bx 5"
b0 4"
b0 3"
bx 2"
x1"
x0"
x/"
x."
x-"
bx ,"
bx +"
bx *"
bx )"
bx ("
x'"
bx ""
bx !"
b0 ~
bx0 }
bx00 |
b0 {
b0 z
bx y
bx x
xw
b0 v
0u
0t
bx s
b0 r
b0 q
bx p
xo
xn
xm
xl
xk
bx j
bx i
bx h
bx g
bx f
xe
bx `
bx _
b0 ^
bx0 ]
bx00 \
b0 [
b0 Z
bx Y
bx X
b0 W
0V
0U
bx T
b0 S
b0 R
bx Q
xP
0O
b0 N
b0 M
b0 L
b0 K
0J
b0 I
b0 H
b0 G
b0 F
0E
0D
b0 C
b0 B
b0 A
b0 @
bx >
x=
bx <
bx ;
bx :
bx 9
bx 8
07
06
bx 5
bx 4
03
12
b0 1
b0 0
b0 /
bx .
b0 -
0,
bx +
0*
bx )
bx (
bx '
bx &
0%
0#
0"
b0 !
$end
#3333
1%
#6666
0%
#9999
1%
#13332
0%
#16665
1%
#19998
0%
#20000
1*
#23331
1%
#26664
0%
#29997
1%
#33330
0%
#36663
1%
#39996
0%
#40000
b11 +
b11 8
b1010 '
b1010 5
b1010 &
b1010 4
1,
b1 0
b1 1
b1010 u"
b1010 t"
b11 s"
b1010 r"
b1010 q"
#43329
1#
b11 N
b1010 M
b1010 L
1O
1%
#46662
0,
b1 r"
b111111111111111 q"
0%
#49995
b10 v
b1 8"
b10100 Z
b10100 z
b11110 ^
b1010 [
b11110 @"
b1010 ="
13
b1010 S
b1010 r
b1010 R
b1010 3"
0O
1D
b11 C
b11 X"
b1010 B
b1010 A
1%
#53328
0%
#56661
b10100 X
b10100 T
b0 x
b1010 >
b0 s
b0 :"
b0 5"
b0 Z"
b0 U"
0P
0o
01"
0Q"
0n
0m
1l
0k
b10100 ]
b101000 \
0=
00"
0/"
1."
0-"
b0 }
b0 |
0w
0P"
0O"
0N"
0M"
b10100 ?"
b101000 >"
09"
0p"
0o"
0n"
0m"
b0 _"
b0 ^"
0Y"
06
07
b100 _
b0 `
b1010 <
b1010 Y
b10100 h
b100 !"
b0 ""
b1010 ;
b1010 y
b0 *"
b0 A"
b0 B"
b0 :
b0 ;"
b0 J"
b0 a"
b0 b"
b0 9
b0 ["
b0 j"
02
03
0#
b10100 j
b11110 g
b1010 Q
b1010 i
b0 f
1e
b10100 ,"
b0 )"
b0 p
b0 +"
b0 ("
1'"
b0 L"
b11110 I"
b1010 2"
b1010 K"
b0 H"
1G"
b0 l"
b0 i"
b0 R"
b0 k"
b0 h"
1g"
b11 @
1E
0D
1%
#59994
b1 '
b1 5
b111111111111111 &
b111111111111111 4
1,
b10 0
b10 1
b1 u"
b111111111111111 t"
0%
#63327
b1010 T
b1010 h
0."
1-"
b1 >
0l
1k
b10 !"
b1 ;
b1 y
b10 _
b1100 X
b10 `
b10100000001 <
b10100000001 Y
1#
b1 h"
b1 H"
b1 ("
b10 ,"
b1 f
b101000000010 j
b1 M
b111111111111111 L
1O
b1 F
1%
#66660
0,
b1000000000000000 q"
0%
#69993
b0 T
b0 h
0k
0-"
b0 >
b10 Z
b10 z
b1011111101 ^
b11111111 [
b101111101 ~
b1111111 {
b1011111101 @"
b11111111 ="
b101111101 `"
b1111111 ]"
b0 _
b1 X
b1 `
b1100100000 <
b1100100000 Y
b0 !"
b0 ;
b0 y
b1 S
b1 r
b11111111 R
b1111111 q
b11111111 3"
b1111111 S"
b10 f
b11001000000 j
b10 ("
b0 ,"
b10 H"
b10 h"
b10 F
1D
b1 B
b111111111111111 A
0O
1%
#73326
0%
#76659
b11111010111 T
1P
b101000 h
13
1Y"
19"
1w
1=
1n
12
b1000 _
b11111011000 X
b0 `
b1100100 <
b1100100 Y
b11 h"
b11 H"
b11 ("
b11 f
b11001000 j
b11 F
1%
#79992
0%
#83325
b11111111 X
b11111111 T
b1111111 x
b1111111 s
0P
b11111111 h
b1111111 *"
0n
1k
b111111110 ]
b1111111100 \
0=
1-"
b1 >
b11111110 }
b111111100 |
0w
b111111110 ?"
b1111111100 >"
09"
b11111110 _"
b111111100 ^"
0Y"
02
b10 _
b1 <
b1 Y
b10 !"
b1 ;
b1 y
03
0#
b10 j
b1011111101 g
b11111111 Q
b11111111 i
b0 f
b10 ,"
b101111101 )"
b1111111 p
b1111111 +"
b0 ("
b1011111101 I"
b11111111 2"
b11111111 K"
b0 H"
b101111101 i"
b1111111 R"
b1111111 k"
b0 h"
1J
b1100100 H
b0 F
0D
1%
#86658
b1000000000000000 &
b1000000000000000 4
1,
b11 0
b11 1
b11111111111111111000000000000000 t"
0%
#89991
b0 s
b0 T
b0 *"
b0 h
0-"
b1111111000000 >
0k
b0 !"
b1111 x
b1111 ""
b1111111000000 ;
b1111111000000 y
b0 _
b11111 X
b11111 `
b11111111000000 <
b11111111000000 Y
1#
b1 h"
b1 H"
b1 ("
b11111110000000 ,"
b1 f
b111111110000000 j
b1000000000000000 L
1O
b1 F
1"
b1100100 !
b1100100 K
0J
1%
#93324
0,
b101111010000001 r"
b11010100100100 q"
b101111010000001 )
b11010100100100 (
b0 .
0%
#96657
1t
1V"
b1111111000 >
b0 ^
b0 [
b11010000000 ~
b11110000000 {
b0 @"
b0 ="
b11010000000 `"
b11110000000 ]"
b11 X
b11 `
b11111111000 <
b11111111000 Y
b1 x
b1 ""
b1111111000 ;
b1111111000 y
b0 R
b10000000 q
b0 3"
b10000000 S"
b10 f
b111111110000 j
b10 ("
b11111110000 ,"
b10 H"
b10 h"
0"
b10 F
1D
b1000000000000000 A
0O
b1 /
1%
#99990
0%
#103323
b11110000000 s
b11100000000 T
1o
b1111111 *"
1P
b11111111 h
13
1Y"
19"
1w
1-"
b1111111 >
1=
1k
12
b1110 !"
b11110000001 x
b0 ""
b1111111 ;
b1111111 y
b1110 _
b11100000001 X
b0 `
b11111111 <
b11111111 Y
b11 h"
b11 H"
b11 ("
b11111110 ,"
b11 f
b111111110 j
b11 F
1%
#106656
0%
#109989
0P
0o
b0 ]
b0 \
b0 X
b0 T
0=
b1 >
b11100000000 }
b11000000000 |
b11110000000 x
b11110000000 s
0w
b0 ?"
b0 >"
09"
b11100000000 _"
b11000000000 ^"
0Y"
02
b10 _
b1 <
b1 Y
b0 h
b10 !"
b1 ;
b1 y
b11110000000 *"
03
0#
b10 j
b0 g
b0 Q
b0 i
b0 f
b10 ,"
b11010000000 )"
b11110000000 p
b11110000000 +"
b0 ("
b0 I"
b0 2"
b0 K"
b0 H"
b11010000000 i"
b11110000000 R"
b11110000000 k"
b0 h"
1J
b11111111 H
b1111111 I
b0 F
0D
1%
#113322
b101111010000001 '
b101111010000001 5
b11010100100100 &
b11010100100100 4
1,
b100 0
b100 1
b101111010000001 u"
b11010100100100 t"
0%
#116655
b0 s
b0 *"
16
0-"
b111110000000000000 >
0k
b0 !"
b11111110000 x
b11111110000 ""
b1110000000000000 ;
b1110000000000000 y
b0 _
b0 <
b0 Y
1#
b1 h"
b1 H"
b1 ("
b111111100000000000000 ,"
b1 f
b0 j
b101111010000001 M
b11010100100100 L
1O
b1 F
1"
b111111111111111 !
b111111111111111 K
0J
1%
#119988
0,
b101011001100011 r"
b1101011000001001 q"
b101011001100011 )
b1101011000001001 (
b1 .
0%
#123321
0t
0V"
b111111110000000000 >
b100000010 Z
b100000010 z
b10111100 <"
b10111100 \"
b1101100 ^
b100100 [
b10011111 ~
b110101 {
b1101100 @"
b100100 ="
b10011111 `"
b110101 ]"
b11111111110 x
b11111111110 ""
b1111110000000000 ;
b1111110000000000 y
b10000001 S
b10000001 r
b1011110 4"
b1011110 T"
b100100 R
b110101 q
b100100 3"
b110101 S"
b10 f
b10 ("
b111111111100000000000 ,"
b10 H"
b10 h"
0"
b10 F
1D
b101111010000001 B
b11010100100100 A
0O
b10 /
1%
#126654
0%
#129987
13
1Y"
19"
1w
b111111111110000000 >
1=
12
b11111111111 x
b11111111111 ""
b1111111110000000 ;
b1111111110000000 y
b11 h"
b11 H"
b11 ("
b111111111111100000000 ,"
b11 f
b11 F
1%
#133320
0%
#136653
b100100 X
b100100 T
b110101 s
b11110111000 :"
b11110110111 5"
b11110010110 Z"
b11110010101 U"
b100100 h
06
b110101 *"
11"
b1001000 J"
1Q"
b1101010 j"
1k
b1001000 ]
b10010000 \
0=
1-"
b1101010 }
b11010100 |
0w
1N"
b11011111 >
b1001000 ?"
b10010000 >"
09"
1n"
b1101010 _"
b11010100 ^"
0Y"
02
b10 _
b10000001 <
b10000001 Y
b10 !"
b110101 x
b0 ""
b10000001 ;
b10000001 y
b1100 A"
b1011110 :
b1011110 ;"
b1100 a"
b1011110 9
b1011110 ["
03
0#
b100000010 j
b1101100 g
b100100 Q
b100100 i
b0 f
b100000010 ,"
b10011111 )"
b110101 p
b110101 +"
b0 ("
b10111100 L"
b1101100 I"
b100100 2"
b100100 K"
b0 H"
b10111100 l"
b10011111 i"
b110101 R"
b110101 k"
b0 h"
1J
b0 H
b111111111110000000 I
b0 F
0D
1%
#139986
b101011001100011 '
b101011001100011 5
b1101011000001001 &
b1101011000001001 4
1,
b101 0
b101 1
b101011001100011 u"
b11111111111111111101011000001001 t"
0%
#143319
b11010100 U"
b10010000 5"
b0 s
b0 T
0Q"
b11010100 j"
01"
b10010000 J"
17
b0 *"
b0 h
1p"
0n"
1P"
0N"
0-"
b111111101101011011 >
0k
b111 a"
b11000110 Z"
b11111110010 b"
b1110010110001011 9
b1110010110001011 ["
b111 A"
b10000111 :"
b11111110111 B"
b1110111000001011 :
b1110111000001011 ;"
b0 !"
b110 x
b110 ""
b110101010000 ;
b110101010000 y
b0 _
b100 X
b100 `
b100100010000 <
b100100010000 Y
1#
b1 h"
b111111100101100010111 l"
b1 H"
b111111101110000010111 L"
b1 ("
b1101010100000 ,"
b1 f
b1001000100000 j
b101011001100011 M
b1101011000001001 L
1O
b1 F
1"
b11111111111111111000000000000000 !
b11111111111111111000000000000000 K
0J
1%
