rtl/8Bit/functions.vh
// =========================================================================
// FUNÇÕES AUXILIARES
// =========================================================================

// -------------------------------------------------------------------------
// Calcula 3×multiplicando (otimização Booth: 3A = A + 2A)
// -------------------------------------------------------------------------
function automatic [ACC_WIDTH-1:0] f_calc_3x;
    input [WIDTH-1:0] val_in;  // Valor de entrada
    input             s_bit;   // Bit de sinal para extensão
    reg [ACC_WIDTH-1:0] val_ext;
begin
    // Estende o valor com sinal
    val_ext = { {(ACC_WIDTH-WIDTH){s_bit}}, val_in };
    // Calcula 3x = x + (x << 1)
    f_calc_3x = val_ext + (val_ext <<< 1);
end
endfunction

// -------------------------------------------------------------------------
// Estende o multiplicando com bit de sinal
// -------------------------------------------------------------------------
function automatic [ACC_WIDTH-1:0] f_extend_mcand;
    input [WIDTH-1:0] val_in;  // Valor a estender
    input             s_bit;   // Bit de sinal
begin
    f_extend_mcand = { {(ACC_WIDTH-WIDTH){s_bit}}, val_in };
end
endfunction

// -------------------------------------------------------------------------
// Inicializa o registrador de produto com o multiplicador
// Formato: [ACC_bits | sign_bit | multiplier | 0]
// -------------------------------------------------------------------------
function automatic [REG_WIDTH-1:0] f_init_prod_reg;
    input [WIDTH-1:0] mult_in;  // Multiplicador
    input             s_bit;    // Bit de sinal
begin
    f_init_prod_reg = {
        {ACC_WIDTH{1'b0}},  // Parte alta zerada (acumulador)
        s_bit,              // Bit de sinal estendido
        mult_in,            // Multiplicador
        1'b0                // Bit extra para janela de Booth
    };
end
endfunction

// -------------------------------------------------------------------------
// DECODIFICADOR BOOTH RADIX-4
// Analisa janela de 4 bits e gera sinais de controle
// -------------------------------------------------------------------------
// Codificação da saída [4:0]:
//   [4]   = sinal da operação (1=subtração, 0=adição)
//   [3:0] = magnitude one-hot (0=±0, 1=±1x, 2=±2x, 3=±3x, 4=±4x)
// -------------------------------------------------------------------------
function automatic [4:0] f_booth_decoder;
    input [3:0] window;     // Janela de 4 bits [i+2:i-1]
    reg [2:0] recoded;
begin
    // Recodificação: inverte bits se MSB=1 (número negativo)
    recoded = window[2:0] ^ {3{window[3]}};

    // Determina sinal: subtração se negativo e não é -0
    f_booth_decoder[4] = window[3] & ~(&window[2:0]);

    // Inicializa magnitude
    f_booth_decoder[3:0] = 4'b0000;

    // Decodifica magnitude baseado nos bits recodificados
    case (recoded)
        3'b001, 3'b010: f_booth_decoder[0] = 1'b1;  // ±1x
        3'b011, 3'b100: f_booth_decoder[1] = 1'b1;  // ±2x
        3'b101, 3'b110: f_booth_decoder[2] = 1'b1;  // ±3x
        3'b111:         f_booth_decoder[3] = 1'b1;  // ±4x
        default:        ;                            // 0x (nada)
    endcase
end
endfunction

// =========================================================================
// FUNÇÕES ARITMÉTICAS MODULARIZADAS
// =========================================================================

// -------------------------------------------------------------------------
// 1. FUNÇÃO BASE (KERNEL) - O que há de comum
// Realiza apenas a seleção (MUX) e a inversão (XOR)
// -------------------------------------------------------------------------
function automatic [ACC_WIDTH-1:0] f_booth_mux_inv;
    input [ACC_WIDTH-1:0] val_1x;
    input [ACC_WIDTH-1:0] val_3x;
    input [4:0]           ctrl;   // {inv, sel_4x, sel_3x, sel_2x, sel_1x}
    reg [ACC_WIDTH-1:0]   magnitude;
begin
    // Lógica de Seleção (Mux One-Hot)
    magnitude = ({ACC_WIDTH{ctrl[0]}} & val_1x)          | // 1x
                ({ACC_WIDTH{ctrl[1]}} & (val_1x <<< 1))  | // 2x
                ({ACC_WIDTH{ctrl[2]}} & val_3x)          | // 3x
                ({ACC_WIDTH{ctrl[3]}} & (val_1x <<< 2));   // 4x

    // Lógica de Inversão (Complemento de 1)
    // Se ctrl[4] for 1, inverte todos os bits.
    f_booth_mux_inv = magnitude ^ {ACC_WIDTH{ctrl[4]}};
end
endfunction

// -------------------------------------------------------------------------
// 2. FUNÇÃO SELECT OP (Para Pipeline)
// Wrapper simples: Apenas retorna o operando preparado.
// -------------------------------------------------------------------------
function automatic [ACC_WIDTH-1:0] f_select_op;
    input [ACC_WIDTH-1:0] val_1x;
    input [ACC_WIDTH-1:0] val_3x;
    input [4:0]           ctrl;
begin
    // Reutiliza a lógica comum
    f_select_op = f_booth_mux_inv(val_1x, val_3x, ctrl);
end
endfunction

// -------------------------------------------------------------------------
// 3. FUNÇÃO ALU CALC (Para Ciclo Único / V3)
// Obtém o operando da função base e realiza a soma completa.
// -------------------------------------------------------------------------
function automatic [ACC_WIDTH-1:0] f_alu_calc;
    input [ACC_WIDTH-1:0] acc_val;
    input [ACC_WIDTH-1:0] val_1x;
    input [ACC_WIDTH-1:0] val_3x;
    input [4:0]           ctrl;
    reg [ACC_WIDTH-1:0]   operand_prepared;
begin
    // Passo 1: Obtém o operando (Mux + Inversão) da função comum
    operand_prepared = f_booth_mux_inv(val_1x, val_3x, ctrl);

    // Passo 2: Soma Final (Acumulador + Operando + Carry In)
    // O bit 'ctrl[4]' (inv) age como o +1 do Complemento de 2
    f_alu_calc = acc_val + operand_prepared + { {(ACC_WIDTH-1){1'b0}}, ctrl[4] };
end
endfunction

rtl/8Bit/core.v
`timescale 1ns / 1ps
`default_nettype none

// =============================================================================
// MULTIPLICADOR BOOTH RADIX-4 DE 8 BITS
// =============================================================================
// Implementa multiplicação de inteiros com sinal usando o algoritmo de Booth
// Radix-4, que processa 2 bits por iteração, reduzindo o número de ciclos.
//
// Suporta operações: signed×signed, unsigned×unsigned, signed×unsigned
// =============================================================================

module booth_mult8 #(
    parameter integer WIDTH = 8  // Largura dos operandos (padrão: 8 bits)
)(
    // Sinais de controle
    input  wire                        clk,          // Clock do sistema
    input  wire                        rst_n,        // Reset assíncrono ativo embaixo
    input  wire                        start,        // Inicia a multiplicação

    // Operandos de entrada
    input  wire signed [WIDTH-1:0]     multiplicand, // Multiplicando (A)
    input  wire signed [WIDTH-1:0]     multiplier,   // Multiplicador (B)
    input  wire [1:0]                  sign_mode,    // [1]:sinal de A, [0]:sinal de B

    // Resultado
    output wire signed [(2*WIDTH)-1:0] product,      // Produto final (A × B)
    output reg                         done          // Sinaliza conclusão
);
    // =========================================================================
    // PARÂMETROS INTERNOS
    // =========================================================================
    localparam integer SHIFT_BITS = WIDTH + 1;      // Bits a deslocar por iteração
    localparam integer ACC_WIDTH  = WIDTH + 3;      // Largura do acumulador
    localparam integer REG_WIDTH  = (2*WIDTH) + 5;  // Largura total do registrador produto

    // =========================================================================
    // REGISTRADORES E SINAIS INTERNOS
    // =========================================================================

    // Registradores de dados
    reg signed [ACC_WIDTH-1:0] r_mcand_ext;  // Multiplicando estendido (1x)
    reg signed [ACC_WIDTH-1:0] m_3x_reg;     // Multiplicando pré-calculado (3x)
    reg signed [REG_WIDTH-1:0] prod_reg;     // Registrador de produto/acumulador

    // Controle de estado
    reg        active;       // Flag de multiplicação ativa
    reg [2:0]  iter_shift;   // Contador de iterações (shift register)

    // Sinais combinacionais do datapath
    wire [4:0]                  w_booth_ctrl;   // Controle decodificado de Booth
    wire signed [ACC_WIDTH-1:0] w_sum_result;   // Resultado da ALU

    // =========================================================================
    // SINAIS PARA TRATAMENTO DE SINAL DOS OPERANDOS
    // =========================================================================
    // Determina se cada operando é com sinal baseado em sign_mode
    wire w_sign_bit_a = sign_mode[1] & multiplicand[WIDTH-1];  // MSB de A se signed
    wire w_sign_bit_b = sign_mode[0] & multiplier[WIDTH-1];    // MSB de B se signed
   
    // =========================================================================
    // FUNÇÕES AUXILIARES
    // =========================================================================

    `include "functions.vh"


    // =========================================================================
    // DATAPATH COMBINACIONAL
    // =========================================================================

    // Decodifica janela de Booth dos 4 bits inferiores do registrador
    assign w_booth_ctrl = f_booth_decoder(prod_reg[3:0]);

    // Calcula nova soma: acumulador ± multiplicando escalado
    assign w_sum_result = f_alu_calc(
        prod_reg[REG_WIDTH-1 : SHIFT_BITS+1],  // Parte alta (acumulador)
        r_mcand_ext,                            // 1x multiplicando
        m_3x_reg,                               // 3x multiplicando
        w_booth_ctrl                            // Controles de Booth
    );

    // Extrai resultado final (descarta bits de controle)
    assign product = prod_reg[WIDTH*2:1];

    // =========================================================================
    // MÁQUINA DE ESTADOS E LÓGICA SEQUENCIAL
    // =========================================================================
    always @(posedge clk or negedge rst_n) begin
        if (!rst_n) begin
            // Reset assíncrono: inicializa todos os registradores
            active      <= 1'b0;
            done        <= 1'b0;
            iter_shift  <= 3'b0;
            r_mcand_ext <= {ACC_WIDTH{1'b0}};
            m_3x_reg    <= {ACC_WIDTH{1'b0}};
            prod_reg    <= {REG_WIDTH{1'b0}};

        end else begin
            // Pulso de done dura apenas 1 ciclo
            done <= 1'b0;

            if (active) begin
                // -------------------------------------------------------------
                // ESTADO ATIVO: Processa iterações de Booth
                // -------------------------------------------------------------

                // Atualiza registrador: [novo_acc | parte_baixa >> 2]
                // Extensão de sinal de 3 bits para preservar aritmética signed
                prod_reg <= {
                    {3{w_sum_result[ACC_WIDTH-1]}},  // Extensão de sinal
                    w_sum_result,                     // Novo acumulador
                    prod_reg[SHIFT_BITS:3]            // Desloca 2 bits (Radix-4)
                };

                // Avança contador de iterações (shift right)
                iter_shift <= iter_shift >> 1;

                // Verifica conclusão (quando LSB do contador chega a 1)
                if (iter_shift[0]) begin
                    active <= 1'b0;
                    done   <= 1'b1;
                end

            end else if (start) begin
                // -------------------------------------------------------------
                // ESTADO IDLE + START: Inicialização da multiplicação
                // -------------------------------------------------------------

                // Pré-calcula valores necessários do multiplicando
                r_mcand_ext <= f_extend_mcand(multiplicand, w_sign_bit_a);
                m_3x_reg    <= f_calc_3x(multiplicand, w_sign_bit_a);

                // Inicializa registrador de produto com multiplicador
                prod_reg    <= f_init_prod_reg(multiplier, w_sign_bit_b);

                // Inicia processamento
                active      <= 1'b1;
                iter_shift  <= 3'b100;  // 4 iterações para 8 bits (100₂ >> ... >> 001₂)
            end
        end
    end

endmodule

// =============================================================================
// NOTAS DE USO
// =============================================================================
// sign_mode: [1]=sinal_A, [0]=sinal_B
//   2'b11 = signed × signed
//   2'b00 = unsigned × unsigned
//   2'b10 = signed × unsigned
//   2'b01 = unsigned × signed
//
// Latência: 4 ciclos de clock (para WIDTH=8)
// Throughput: 1 operação a cada 5 ciclos (4 + 1 setup)

`default_nettype wire

tb/tb_booth_mult8.v
// tb_booth_mult8.v
// Testbench Verilog-2001 para module booth_mult8 (corrigido)
// - 4 configurações de sign_mode (2 bits): [1]=multiplicand signed, [0]=multiplier signed
// - Casos de borda + 500 testes randômicos por configuração
// - Verificação automática do produto esperado
// - Timeout esperando done
`timescale 1ns/1ps

module tb_booth_mult8;

    // --- clock / reset / control signals ---
    reg clk;
    reg rst_n;
    reg start;

    // --- DUT inputs (8-bit each) ---
    reg [7:0] multiplicand_i;
    reg [7:0] multiplier_i;
    reg [1:0] sign_mode; // [1] -> multiplicand signed when 1, [0] -> multiplier signed when 1

    // --- DUT outputs ---
    wire signed [15:0] product;
    wire done;

    // Instantiate DUT (assumes module name and ports as provided)
    booth_mult8 dut (
        .clk(clk),
        .rst_n(rst_n),
        .start(start),
        .multiplicand(multiplicand_i),
        .multiplier(multiplier_i),
        .sign_mode(sign_mode),
        .product(product),
        .done(done)
    );

    // --- testbench helpers / bookkeeping ---
    integer i;
    integer seed;
    integer timeout_cycles;
    integer pass_count;
    integer fail_count;
    integer total_tests;

    // Expected product (computed in testbench using integer arithmetic)
    reg signed [15:0] expected;
    integer Ai;
    integer Bi;
    integer Prod;

    // Clock generator
    initial begin
        clk = 0;
        forever #5 clk = ~clk; // 10 ns period
    end

    // Test sequence
    initial begin
        // initialize
        seed = 32'hDEADBEEF;
        rst_n = 0;
        start = 0;
        multiplicand_i = 8'h00;
        multiplier_i   = 8'h00;
        sign_mode = 2'b00;
        pass_count = 0;
        fail_count = 0;
        total_tests = 0;
        timeout_cycles = 200; // timeout per test (cycles) - ajuste se necessário

        // apply reset pulse (keep reset for a short time)
        #20;
        rst_n = 1; // release reset (assumes active-low)

        // Run test campaigns for each sign_mode
        run_all_sign_configs();

        // Summary
        $display("------------------------------------------------------------");
        $display("TEST SUMMARY: total=%0d  PASS=%0d  FAIL=%0d", total_tests, pass_count, fail_count);
        if (fail_count == 0) begin
            $display("RESULT: ALL TESTS PASSED");
        end else begin
            $display("RESULT: SOME TESTS FAILED");
        end
        $display("------------------------------------------------------------");

        // finish
        #50;
        $finish;
    end

    // Task to run tests for all 4 sign configurations
    task run_all_sign_configs;
        integer cfg;
        begin
            for (cfg = 0; cfg < 4; cfg = cfg + 1) begin
                sign_mode = cfg[1:0];
                $display("\n=== Running tests for sign_mode = %0b (multiplicand_signed=%0b, multiplier_signed=%0b) ===",
                         sign_mode, sign_mode[1], sign_mode[0]);

                // Run explicit edge cases first
                run_edge_cases_for_config();

                // Then run 500 random tests
                run_random_tests_for_config(500);
            end
        end
    endtask

    integer aidx, bidx;
    reg [7:0] edge_vals [0:11];
    // Task: run predefined edge cases for current sign_mode
    task run_edge_cases_for_config;
        begin
            // List of explicit edge values to test for each operand
            edge_vals[0] = 8'h00; // 0
            edge_vals[1] = 8'h01; // 1
            edge_vals[2] = 8'h7F; // 127
            edge_vals[3] = 8'h80; // -128 (if signed) or 128 (unsigned)
            edge_vals[4] = 8'hFF; // -1 (if signed) or 255 (unsigned)
            edge_vals[5] = 8'hFE; // -2 or 254
            edge_vals[6] = 8'h55; // pattern
            edge_vals[7] = 8'hAA; // pattern
            edge_vals[8] = 8'h0F;
            edge_vals[9] = 8'hF0;
            edge_vals[10]= 8'hC0;
            edge_vals[11]= 8'h3F;

            for (aidx = 0; aidx < 12; aidx = aidx + 1) begin
                for (bidx = 0; bidx < 12; bidx = bidx + 1) begin
                    multiplicand_i = edge_vals[aidx];
                    multiplier_i   = edge_vals[bidx];
                    total_tests = total_tests + 1;
                    run_single_test_and_check();
                end
            end
        end
    endtask

    // Task: run N random tests for current sign_mode
    task run_random_tests_for_config;
        input integer n;
        integer j;
        begin
            for (j = 0; j < n; j = j + 1) begin
                multiplicand_i = $random(seed) & 8'hFF;
                multiplier_i   = $random(seed) & 8'hFF;
                total_tests = total_tests + 1;
                run_single_test_and_check();
            end
        end
    endtask

    // Task: apply start pulse, wait for done (with timeout), compute expected, compare and record result
    task run_single_test_and_check;
        integer cycles_waited;
        begin
            // compute expected using integer arithmetic with sign_mode interpretation
            if (sign_mode[1] == 1'b1) begin
                Ai = $signed(multiplicand_i);
            end else begin
                Ai = multiplicand_i;
            end

            if (sign_mode[0] == 1'b1) begin
                Bi = $signed(multiplier_i);
            end else begin
                Bi = multiplier_i;
            end

            // compute product in integer (32-bit signed)
            Prod = Ai * Bi;

            // expected is lower 16 bits (signed interpretation)
            expected = Prod[15:0];

            // Apply start pulse (one clock)
            @(posedge clk);
            start = 1;
            @(posedge clk);
            start = 0;

            // wait for done with timeout
            cycles_waited = 0;
            while (done !== 1'b1 && cycles_waited < timeout_cycles) begin
                @(posedge clk);
                cycles_waited = cycles_waited + 1;
            end

            if (done !== 1'b1) begin
                $display("ERROR: timeout waiting for done. sign_mode=%0b A=0x%02h B=0x%02h expected=0x%04h",
                         sign_mode, multiplicand_i, multiplier_i, expected);
                fail_count = fail_count + 1;
            end else begin
                // Compare DUT product to expected bitwise
                if (product !== expected) begin
                    $display("FAIL: sign_mode=%0b multiplicand=0x%02h multiplier=0x%02h | DUT=0x%04h expected=0x%04h Ai=%0d Bi=%0d Prod=%0d",
                             sign_mode, multiplicand_i, multiplier_i, product, expected, Ai, Bi, Prod);
                    fail_count = fail_count + 1;
                end else begin
                    pass_count = pass_count + 1;
                end
            end

            // small gap between tests
            @(posedge clk);
        end
    endtask

    // Monitor progress periodically
    initial begin
	$dumpfile("simulation.vcd");
	$dumpvars(0,tb_booth_mult8);
        forever begin
            #50000; // every some simulated time show progress
            $display("[PROGRESS] tests so far=%0d pass=%0d fail=%0d", total_tests, pass_count, fail_count);
        end
    end

endmodule

sim/8Bit/core/simulation.vcd
$date
	Tue Dec 16 13:57:20 2025
$end
$version
	Icarus Verilog
$end
$timescale
	1ps
$end
$scope module tb_booth_mult8 $end
$var wire 16 ! product [15:0] $end
$var wire 1 " done $end
$var reg 1 # clk $end
$var reg 16 $ expected [15:0] $end
$var reg 8 % multiplicand_i [7:0] $end
$var reg 8 & multiplier_i [7:0] $end
$var reg 1 ' rst_n $end
$var reg 2 ( sign_mode [1:0] $end
$var reg 1 ) start $end
$var integer 32 * Ai [31:0] $end
$var integer 32 + Bi [31:0] $end
$var integer 32 , Prod [31:0] $end
$var integer 32 - aidx [31:0] $end
$var integer 32 . bidx [31:0] $end
$var integer 32 / fail_count [31:0] $end
$var integer 32 0 pass_count [31:0] $end
$var integer 32 1 seed [31:0] $end
$var integer 32 2 timeout_cycles [31:0] $end
$var integer 32 3 total_tests [31:0] $end
$scope module dut $end
$var wire 1 # clk $end
$var wire 8 4 multiplicand [7:0] $end
$var wire 8 5 multiplier [7:0] $end
$var wire 1 ' rst_n $end
$var wire 2 6 sign_mode [1:0] $end
$var wire 1 ) start $end
$var wire 1 7 w_sign_bit_a $end
$var wire 1 8 w_sign_bit_b $end
$var wire 11 9 w_sum_result [10:0] $end
$var wire 5 : w_booth_ctrl [4:0] $end
$var wire 16 ; product [15:0] $end
$var parameter 32 < ACC_WIDTH $end
$var parameter 32 = REG_WIDTH $end
$var parameter 32 > SHIFT_BITS $end
$var parameter 32 ? WIDTH $end
$var reg 1 @ active $end
$var reg 1 " done $end
$var reg 3 A iter_shift [2:0] $end
$var reg 11 B m_3x_reg [10:0] $end
$var reg 21 C prod_reg [20:0] $end
$var reg 11 D r_mcand_ext [10:0] $end
$scope function f_alu_calc $end
$upscope $end
$scope function f_booth_decoder $end
$upscope $end
$scope function f_booth_mux_inv $end
$upscope $end
$scope function f_calc_3x $end
$upscope $end
$scope function f_extend_mcand $end
$upscope $end
$scope function f_init_prod_reg $end
$upscope $end
$scope function f_select_op $end
$upscope $end
$upscope $end
$scope task run_all_sign_configs $end
$var integer 32 E cfg [31:0] $end
$upscope $end
$scope task run_edge_cases_for_config $end
$upscope $end
$scope task run_random_tests_for_config $end
$var integer 32 F j [31:0] $end
$var integer 32 G n [31:0] $end
$upscope $end
$scope task run_single_test_and_check $end
$var integer 32 H cycles_waited [31:0] $end
$upscope $end
$upscope $end
$enddefinitions $end
$comment Show the parameter values. $end
$dumpall
b1000 ?
b1001 >
b10101 =
b1011 <
$end
#0
$dumpvars
bx H
bx G
bx F
bx E
b0 D
b0 C
b0 B
b0 A
0@
b0 ;
b0 :
b0 9
08
07
b0 6
b0 5
b0 4
b0 3
b11001000 2
b11011110101011011011111011101111 1
b0 0
b0 /
bx .
bx -
bx ,
bx +
bx *
0)
b0 (
0'
b0 &
b0 %
bx $
0#
0"
b0 !
$end
#5000
1#
#10000
0#
#15000
1#
#20000
0#
b0 $
b0 ,
b0 +
b0 *
b1 3
b0 .
b0 -
b0 E
1'
#25000
b100 A
1@
1)
1#
#30000
0#
#35000
b10 A
b0 H
0)
1#
#40000
0#
#45000
b1 A
b1 H
1#
#50000
0#
#55000
1"
0@
b0 A
b10 H
1#
#60000
0#
#65000
0"
b1 0
b11 H
1#
#70000
0#
#75000
b1 +
b10 3
b1 &
b1 5
b1 .
1#
#80000
0#
#85000
b1 :
b1 !
b1 ;
b100 A
1@
b10 C
1)
1#
#90000
0#
#95000
b0 :
b0 !
b0 ;
b10 A
b0 C
b0 H
0)
1#
#100000
0#
#105000
b1 A
b1 H
1#
#110000
0#
#115000
1"
0@
b0 A
b10 H
1#
#120000
0#
#125000
0"
b10 0
b11 H
1#
#130000
0#
#135000
b1111111 +
b11 3
b1111111 &
b1111111 5
b10 .
1#
#140000
0#
#145000
b10001 :
b1111111 !
b1111111 ;
b100 A
1@
b11111110 C
1)
1#
#150000
0#
#155000
b0 :
b1111 !
b1111 ;
b10 A
b11111 C
b0 H
0)
1#
#160000
0#
#165000
b10 :
b1 !
b1 ;
b1 A
b11 C
b1 H
1#
#170000
0#
#175000
b0 :
b0 !
b0 ;
1"
0@
b0 A
b0 C
b10 H
1#
#180000
0#
#185000
0"
b11 0
b11 H
1#
#190000
0#
#195000
b10000000 +
b100 3
b10000000 &
b10000000 5
b11 .
1#
#200000
0#
#205000
b10000000 !
b10000000 ;
b100 A
1@
b100000000 C
1)
1#
#210000
0#
#215000
b10000 !
b10000 ;
b10 A
b100000 C
b0 H
0)
1#
#220000
0#
#225000
b10 :
b10 !
b10 ;
b1 A
b100 C
b1 H
1#
#230000
0#
#235000
b0 :
b0 !
b0 ;
1"
0@
b0 A
b0 C
b10 H
1#
#240000
0#
#245000
0"
b100 0
b11 H
1#
#250000
0#
#255000
b11111111 +
b101 3
b11111111 &
b11111111 5
b100 .
1#
#260000
0#
#265000
b10001 :
b11111111 !
b11111111 ;
b100 A
1@
b111111110 C
1)
1#
#270000
0#
#275000
b0 :
b11111 !
b11111 ;
b10 A
b111111 C
b0 H
0)
1#
#280000
0#
#285000
b1000 :
b11 !
b11 ;
b1 A
b111 C
b1 H
1#
#290000
0#
#295000
b0 :
b0 !
b0 ;
1"
0@
b0 A
b0 C
b10 H
1#
#300000
0#
#305000
0"
b101 0
b11 H
1#
#310000
0#
#315000
b11111110 +
b110 3
b11111110 &
b11111110 5
b101 .
1#
#320000
0#
#325000
b10010 :
b11111110 !
b11111110 ;
b100 A
1@
b111111100 C
1)
1#
#330000
0#
#335000
b0 :
b11111 !
b11111 ;
b10 A
b111111 C
b0 H
0)
1#
#340000
0#
#345000
b1000 :
b11 !
b11 ;
b1 A
b111 C
b1 H
1#
#350000
0#
#355000
b0 :
b0 !
b0 ;
1"
0@
b0 A
b0 C
b10 H
1#
#360000
0#
#365000
0"
b110 0
b11 H
1#
#370000
0#
#375000
b1010101 +
b111 3
b1010101 &
b1010101 5
b110 .
1#
#380000
0#
#385000
b10100 :
b1010101 !
b1010101 ;
b100 A
1@
b10101010 C
1)
1#
#390000
0#
#395000
b100 :
b1010 !
b1010 ;
b10 A
b10101 C
b0 H
0)
1#
#400000
0#
#405000
b1 :
b1 !
b1 ;
b1 A
b10 C
b1 H
1#
#410000
0#
#415000
b0 :
b0 !
b0 ;
1"
0@
b0 A
b0 C
b10 H
1#
#420000
0#
#425000
0"
b111 0
b11 H
1#
#430000
0#
#435000
b10101010 +
b1000 3
b10101010 &
b10101010 5
b111 .
1#
#440000
0#
#445000
b10 :
b10101010 !
b10101010 ;
b100 A
1@
b101010100 C
1)
1#
#450000
0#
#455000
b10100 :
b10101 !
b10101 ;
b10 A
b101010 C
b0 H
0)
1#
#460000
0#
#465000
b100 :
b10 !
b10 ;
b1 A
b101 C
b1 H
1#
#470000
0#
#475000
b0 :
b0 !
b0 ;
1"
0@
b0 A
b0 C
b10 H
1#
#480000
0#
#485000
0"
b1000 0
b11 H
1#
#490000
0#
#495000
b1111 +
b1001 3
b1111 &
b1111 5
b1000 .
1#
#500000
0#
#505000
b10001 :
b1111 !
b1111 ;
b100 A
1@
b11110 C
1)
1#
#510000
0#
#515000
b10 :
b1 !
b1 ;
b10 A
b11 C
b0 H
0)
1#
#520000
0#
#525000
b0 :
b0 !
b0 ;
b1 A
b0 C
b1 H
1#
#530000
0#
#535000
1"
0@
b0 A
b10 H
1#
#540000
0#
#545000
0"
b1001 0
b11 H
1#
#550000
0#
#555000
b11110000 +
b1010 3
b11110000 &
b11110000 5
b1001 .
1#
#560000
0#
#565000
b11110000 !
b11110000 ;
b100 A
1@
b111100000 C
1)
1#
#570000
0#
#575000
b10010 :
b11110 !
b11110 ;
b10 A
b111100 C
b0 H
0)
1#
#580000
0#
#585000
b1000 :
b11 !
b11 ;
b1 A
b111 C
b1 H
1#
#590000
0#
#595000
b0 :
b0 !
b0 ;
1"
0@
b0 A
b0 C
b10 H
1#
#600000
0#
#605000
0"
b1010 0
b11 H
1#
#610000
0#
#615000
b11000000 +
b1011 3
b11000000 &
b11000000 5
b1010 .
1#
#620000
0#
#625000
b11000000 !
b11000000 ;
b100 A
1@
b110000000 C
1)
1#
#630000
0#
#635000
b11000 !
b11000 ;
b10 A
b110000 C
b0 H
0)
1#
#640000
0#
#645000
b100 :
b11 !
b11 ;
b1 A
b110 C
b1 H
1#
#650000
0#
#655000
b0 :
b0 !
b0 ;
1"
0@
b0 A
b0 C
b10 H
1#
#660000
0#
#665000
0"
b1011 0
b11 H
1#
#670000
0#
#675000
b111111 +
b1100 3
b111111 &
b111111 5
b1011 .
1#
#680000
0#
#685000
b10001 :
b111111 !
b111111 ;
b100 A
1@
b1111110 C
1)
1#
#690000
0#
#695000
b0 :
b111 !
b111 ;
b10 A
b1111 C
b0 H
0)
1#
#700000
0#
#705000
b1 :
b0 !
b0 ;
b1 A
b1 C
b1 H
1#
#710000
0#
#715000
b0 :
1"
0@
b0 A
b0 C
b10 H
1#
#720000
0#
#725000
0"
b1100 0
b11 H
1#
#730000
0#
#735000
b0 +
b1 *
b1101 3
b0 &
b0 5
b1 %
b1 4
b1 -
b0 .
1#
#740000
0#
#745000
b100 A
1@
b11 B
b1 D
1)
1#
#750000
0#
#755000
b10 A
b0 H
0)
1#
#760000
0#
#765000
b1 A
b1 H
1#
#770000
0#
#775000
1"
0@
b0 A
b10 H
1#
#780000
0#
#785000
0"
b1101 0
b11 H
1#
#790000
0#
#795000
b1 $
b1 ,
b1 +
b1110 3
b1 &
b1 5
b1 .
1#
#800000
0#
#805000
b1 9
b1 :
b1 !
b1 ;
b100 A
1@
b10 C
1)
1#
#810000
0#
#815000
b0 9
b0 :
b1000000 !
b1000000 ;
b10 A
b10000000 C
b0 H
0)
1#
#820000
0#
#825000
b1000 !
b1000 ;
b1 A
b10000 C
b1 H
1#
#830000
0#
#835000
b1 9
b1 :
b1 !
b1 ;
1"
0@
b0 A
b10 C
b10 H
1#
#840000
0#
#845000
0"
b1110 0
b11 H
1#
#850000
0#
#855000
b1111111 $
b1111111 ,
b1111111 +
b1111 3
b1111111 &
b1111111 5
b10 .
1#
#860000
0#
#865000
b11111111111 9
b10001 :
b1111111 !
b1111111 ;
b100 A
1@
b11111110 C
1)
1#
#870000
0#
#875000
b0 :
b11111111111 9
b1111111111001111 !
b1111111111001111 ;
b10 A
b111111111111110011111 C
b0 H
0)
1#
#880000
0#
#885000
b1 9
b10 :
b1111111111111001 !
b1111111111111001 ;
b1 A
b111111111111111110011 C
b1 H
1#
#890000
0#
#895000
b10001 :
b11111111111 9
b1111111 !
b1111111 ;
1"
0@
b0 A
b11111110 C
b10 H
1#
#900000
0#
#905000
0"
b1111 0
b11 H
1#
#910000
0#
#915000
b10000000 $
b10000000 ,
b10000000 +
b10000 3
b10000000 &
b10000000 5
b11 .
1#
#920000
0#
#925000
b0 9
b0 :
b10000000 !
b10000000 ;
b100 A
1@
b100000000 C
1)
1#
#930000
0#
#935000
b10000 !
b10000 ;
b10 A
b100000 C
b0 H
0)
1#
#940000
0#
#945000
b10 9
b10 :
b10 !
b10 ;
b1 A
b100 C
b1 H
1#
#950000
0#
#955000
b0 9
b0 :
b10000000 !
b10000000 ;
1"
0@
b0 A
b100000000 C
b10 H
1#
#960000
0#
#965000
0"
b10000 0
b11 H
1#
#970000
0#
#975000
b11111111 $
b11111111 ,
b11111111 +
b10001 3
b11111111 &
b11111111 5
b100 .
1#
#980000
0#
#985000
b11111111111 9
b10001 :
b11111111 !
b11111111 ;
b100 A
1@
b111111110 C
1)
1#
#990000
0#
#995000
b0 :
b11111111111 9
b1111111111011111 !
b1111111111011111 ;
b10 A
b111111111111110111111 C
b0 H
0)
1#
#1000000
0#
#1005000
b11 9
b1000 :
b1111111111111011 !
b1111111111111011 ;
b1 A
b111111111111111110111 C
b1 H
1#
#1010000
0#
#1015000
b10001 :
b11111111111 9
b11111111 !
b11111111 ;
1"
0@
b0 A
b111111110 C
b10 H
1#
#1020000
0#
#1025000
0"
b10001 0
b11 H
1#
#1030000
0#
#1035000
b11111110 $
b11111110 ,
b11111110 +
b10010 3
b11111110 &
b11111110 5
b101 .
1#
#1040000
0#
#1045000
b11111111110 9
b10010 :
b11111110 !
b11111110 ;
b100 A
1@
b111111100 C
1)
1#
#1050000
0#
#1055000
b0 :
b11111111111 9
b1111111110011111 !
b1111111110011111 ;
b10 A
b111111111111100111111 C
b0 H
0)
1#
#1060000
0#
#1065000
b11 9
b1000 :
b1111111111110011 !
b1111111111110011 ;
b1 A
b111111111111111100111 C
b1 H
1#
#1070000
0#
#1075000
b10010 :
b11111111110 9
b11111110 !
b11111110 ;
1"
0@
b0 A
b111111100 C
b10 H
1#
#1080000
0#
#1085000
0"
b10010 0
b11 H
1#
#1090000
0#
#1095000
b1010101 $
b1010101 ,
b1010101 +
b10011 3
b1010101 &
b1010101 5
b110 .
1#
#1100000
0#
#1105000
b11111111101 9
b10100 :
b1010101 !
b1010101 ;
b100 A
1@
b10101010 C
1)
1#
#1110000
0#
#1115000
b100 :
b10 9
b1111111101001010 !
b1111111101001010 ;
b10 A
b111111111111010010101 C
b0 H
0)
1#
#1120000
0#
#1125000
b1 :
b1 9
b10101001 !
b10101001 ;
b1 A
b101010010 C
b1 H
1#
#1130000
0#
#1135000
b11111111101 9
b10100 :
b1010101 !
b1010101 ;
1"
0@
b0 A
b10101010 C
b10 H
1#
#1140000
0#
#1145000
0"
b10011 0
b11 H
1#
#1150000
0#
#1155000
b10101010 $
b10101010 ,
b10101010 +
b10100 3
b10101010 &
b10101010 5
b111 .
1#
#1160000
0#
#1165000
b10 9
b10 :
b10101010 !
b10101010 ;
b100 A
1@
b101010100 C
1)
1#
#1170000
0#
#1175000
b11111111101 9
b10100 :
b10010101 !
b10010101 ;
b10 A
b100101010 C
b0 H
0)
1#
#1180000
0#
#1185000
b100 :
b10 9
b1111111101010010 !
b1111111101010010 ;
b1 A
b111111111111010100101 C
b1 H
1#
#1190000
0#
