rtl/generic_booth_radix8.v
`timescale 1ns / 1ps
`default_nettype none

module booth_mult_generic #(
    parameter integer WIDTH = 8
)(
    input  wire                  clk,
    input  wire                  rst_n,
    input  wire signed [WIDTH-1:0] multiplicand,
    input  wire signed [WIDTH-1:0] multiplier,
    input  wire [1:0]            sign_mode,
    output reg signed [(2*WIDTH)-1:0] product
);

    // ========================================================================
    // CONSTANTES
    // ========================================================================
    localparam integer NUM_PPS = (WIDTH + 3) / 3;
    localparam integer EXT_A_WIDTH = WIDTH + 4; 
    localparam integer OUT_WIDTH = 2 * WIDTH;

    // ========================================================================
    // ESTÁGIO 1: Pré-cálculo 3A
    // ========================================================================
    reg signed [EXT_A_WIDTH-1:0] r1_A_1x;
    reg signed [EXT_A_WIDTH-1:0] r1_A_3x;
    reg [(NUM_PPS*3)+3:0]        r1_B_coded; 

    wire s_bit_a = sign_mode[1] & multiplicand[WIDTH-1];
    wire s_bit_b = sign_mode[0] & multiplier[WIDTH-1];
    wire signed [EXT_A_WIDTH-1:0] A_ext = { {(EXT_A_WIDTH-WIDTH){s_bit_a}}, multiplicand };

    always @(posedge clk or negedge rst_n) begin
        if (!rst_n) begin
            r1_A_1x    <= 0;
            r1_A_3x    <= 0;
            r1_B_coded <= 0;
        end else begin
            r1_A_1x <= A_ext;
            r1_A_3x <= A_ext + (A_ext <<< 1);
            r1_B_coded <= { {(NUM_PPS*3 - WIDTH + 4){s_bit_b}}, multiplier, 1'b0 };
        end
    end

    // ========================================================================
    // ESTÁGIO 2: Geração PPs + Vetor de Correção
    // ========================================================================
    // Tratamos o conjunto de bits '+1' (inversão) como um vetor extra a ser somado.
    
    // Total de itens para somar = NUM_PPS + 1 (Vetor de Correção)
    localparam integer NUM_ITEMS_L0 = NUM_PPS + 1;
    
    reg signed [OUT_WIDTH-1:0] r2_items [0:NUM_ITEMS_L0-1];

    function signed [OUT_WIDTH-1:0] get_booth_val (
        input [3:0] group_bits,
        input signed [EXT_A_WIDTH-1:0] in_1x,
        input signed [EXT_A_WIDTH-1:0] in_3x,
        input integer shift_amount
    );
        reg sel_1x, sel_2x, sel_3x, sel_4x;
        reg [2:0] recoded;
        reg signed [EXT_A_WIDTH-1:0] mag;
        reg inv;
        reg signed [OUT_WIDTH-1:0] mag_shifted;
    begin
        recoded = group_bits[2:0] ^ {3{group_bits[3]}};
        inv     = group_bits[3] & ~(&group_bits[2:0]); 
        sel_1x = (recoded == 3'b001 || recoded == 3'b010);
        sel_2x = (recoded == 3'b011 || recoded == 3'b100);
        sel_3x = (recoded == 3'b101 || recoded == 3'b110);
        sel_4x = (recoded == 3'b111);

        mag = ({EXT_A_WIDTH{sel_1x}} & in_1x) |
              ({EXT_A_WIDTH{sel_2x}} & (in_1x <<< 1)) |
              ({EXT_A_WIDTH{sel_3x}} & in_3x) |
              ({EXT_A_WIDTH{sel_4x}} & (in_1x <<< 2));
        mag_shifted = mag; 
        // Apenas XOR, o +1 vai pro vetor de correção
        get_booth_val = (mag_shifted ^ {OUT_WIDTH{inv}}) <<< shift_amount;
    end
    endfunction
    
    function get_booth_inv (input [3:0] group_bits);
        get_booth_inv = group_bits[3] & ~(&group_bits[2:0]);
    endfunction

    integer i;
    reg [OUT_WIDTH-1:0] correction_accum;
    
    always @(posedge clk or negedge rst_n) begin
        if (!rst_n) begin
            for (i=0; i<NUM_ITEMS_L0; i=i+1) r2_items[i] <= 0;
        end else begin
            // 1. Gera os PPs normais
            correction_accum = 0;
            for (i=0; i<NUM_PPS; i=i+1) begin
                r2_items[i] <= get_booth_val(r1_B_coded[i*3 +: 4], r1_A_1x, r1_A_3x, i*3);
                
                // Monta o vetor de correção (Hot Bits)
                if (get_booth_inv(r1_B_coded[i*3 +: 4]))
                    correction_accum = correction_accum | (1'b1 <<< (i*3));
            end
            // 2. O último item é o vetor de correção
            r2_items[NUM_PPS] <= correction_accum;
        end
    end

    // ========================================================================
    // ARVORE DE SOMA BINARIA (PIPELINED)
    // ========================================================================
    // A cada estágio, o número de itens cai pela metade.
    // Usamos 'generate' ou constantes fixas? Para manter genérico, vamos usar 
    // arrays fixos grandes o suficiente e lógica "generate-like" procedural.
    
    // Definição dos Níveis da Árvore (Suporta até ~32 PPs -> 128 bits width)
    localparam CNT_L1 = (NUM_ITEMS_L0 + 1) / 2;
    localparam CNT_L2 = (CNT_L1 + 1) / 2;
    localparam CNT_L3 = (CNT_L2 + 1) / 2;
    localparam CNT_L4 = (CNT_L3 + 1) / 2; // Final

    reg signed [OUT_WIDTH-1:0] r_tree_L1 [0:CNT_L1-1];
    reg signed [OUT_WIDTH-1:0] r_tree_L2 [0:CNT_L2-1];
    reg signed [OUT_WIDTH-1:0] r_tree_L3 [0:CNT_L3-1];
    reg signed [OUT_WIDTH-1:0] r_tree_L4 [0:CNT_L4-1]; // Deve ser 1 item aqui se <= 16 PPs iniciais

    integer k;

    // ESTÁGIO 3: Nível 1 da Árvore
    always @(posedge clk) begin
        for (k=0; k<CNT_L1; k=k+1) begin
            if (k*2 + 1 < NUM_ITEMS_L0)
                r_tree_L1[k] <= r2_items[k*2] + r2_items[k*2 + 1];
            else // Sobra um ímpar
                r_tree_L1[k] <= r2_items[k*2];
        end
    end

    // ESTÁGIO 4: Nível 2 da Árvore
    always @(posedge clk) begin
        for (k=0; k<CNT_L2; k=k+1) begin
            if (k*2 + 1 < CNT_L1)
                r_tree_L2[k] <= r_tree_L1[k*2] + r_tree_L1[k*2 + 1];
            else
                r_tree_L2[k] <= r_tree_L1[k*2];
        end
    end

    // ESTÁGIO 5: Nível 3 da Árvore
    always @(posedge clk) begin
        for (k=0; k<CNT_L3; k=k+1) begin
            if (k*2 + 1 < CNT_L2)
                r_tree_L3[k] <= r_tree_L2[k*2] + r_tree_L2[k*2 + 1];
            else
                r_tree_L3[k] <= r_tree_L2[k*2];
        end
    end

    // ESTÁGIO 6: Nível 4 da Árvore (Para 32-bit width, isso finaliza em 1 item)
    // Se WIDTH for enorme (64 bits), talvez precise de mais um estágio, mas 
    // para 32 bits (12 itens iniciais), L4 terá apenas 1 item.
    always @(posedge clk) begin
        for (k=0; k<CNT_L4; k=k+1) begin
            if (k*2 + 1 < CNT_L3)
                r_tree_L4[k] <= r_tree_L3[k*2] + r_tree_L3[k*2 + 1];
            else
                r_tree_L4[k] <= r_tree_L3[k*2];
        end
    end

    // ========================================================================
    // SAÍDA
    // ========================================================================
    always @(posedge clk or negedge rst_n) begin
        if (!rst_n) product <= 0;
        else        product <= r_tree_L4[0];
    end

endmodule
`default_nettype wire

tb/tb_generic_booth_readix8.v
`timescale 1ns / 1ps

// Defina a largura aqui para testar
`define TEST_WIDTH 32

module tb_booth_generic;

    reg clk;
    reg rst_n;
    reg signed [`TEST_WIDTH-1:0] mcand_in;
    reg signed [`TEST_WIDTH-1:0] mult_in;
    reg [1:0] sign_mode_in;
    
    wire signed [(2*`TEST_WIDTH)-1:0] product_out;

    integer errors = 0;
    integer tests_run = 0;
    
    localparam LATENCY = 7;
    
    // Arrays largos o suficiente para armazenar resultados de 32 bits (64 out)
    reg signed [(2*`TEST_WIDTH)-1:0] expected_pipe [0:LATENCY];
    reg [`TEST_WIDTH-1:0]            debug_a_pipe  [0:LATENCY];
    reg [`TEST_WIDTH-1:0]            debug_b_pipe  [0:LATENCY];
    reg [1:0]                        debug_mode_pipe [0:LATENCY];
    reg                              valid_pipe    [0:LATENCY];

    // DUT Genérico
    booth_mult_generic #(.WIDTH(`TEST_WIDTH)) dut (
        .clk(clk),
        .rst_n(rst_n),
        .multiplicand(mcand_in),
        .multiplier(mult_in),
        .sign_mode(sign_mode_in),
        .product(product_out)
    );

    initial clk = 0; 
    always #5 clk = ~clk;

    // Golden Model Genérico
    function signed [(2*`TEST_WIDTH)-1:0] calc_expected;
        input [`TEST_WIDTH-1:0] a, b;
        input [1:0] mode;
        reg signed [`TEST_WIDTH:0] a_conv, b_conv; // +1 bit para sign handling seguro
        reg signed [(2*`TEST_WIDTH)+1:0] res;
    begin
        if (mode[1]) a_conv = $signed(a); else a_conv = $signed({1'b0, a});
        if (mode[0]) b_conv = $signed(b); else b_conv = $signed({1'b0, b});
        res = a_conv * b_conv;
        calc_expected = res[(2*`TEST_WIDTH)-1:0];
    end
    endfunction

    // Lógica de verificação (Idêntica, só mudam as larguras)
    integer k;
    always @(posedge clk) begin
        if (!rst_n) begin
            for(k=0; k<=LATENCY; k=k+1) valid_pipe[k] <= 0;
        end else begin
            if (valid_pipe[LATENCY-1]) begin
                if (product_out !== expected_pipe[LATENCY-1]) begin
                    $display("ERRO em %0d bits: A=%h B=%h | Exp=%h Rec=%h", 
                             `TEST_WIDTH, debug_a_pipe[LATENCY-1], debug_b_pipe[LATENCY-1],
                             expected_pipe[LATENCY-1], product_out);
                    errors = errors + 1;
                end
                tests_run = tests_run + 1;
            end
            for (k = LATENCY; k > 0; k = k - 1) begin
                expected_pipe[k]   <= expected_pipe[k-1];
                debug_a_pipe[k]    <= debug_a_pipe[k-1];
                debug_b_pipe[k]    <= debug_b_pipe[k-1];
                debug_mode_pipe[k] <= debug_mode_pipe[k-1];
                valid_pipe[k]      <= valid_pipe[k-1];
            end
            expected_pipe[0]   <= calc_expected(mcand_in, mult_in, sign_mode_in);
            debug_a_pipe[0]    <= mcand_in;
            debug_b_pipe[0]    <= mult_in;
            debug_mode_pipe[0] <= sign_mode_in;
            valid_pipe[0]      <= 1'b1;
        end
    end

    initial begin
        $dumpfile("simulacao.vcd");   // nome do arquivo
	$dumpvars(0, tb_booth_generic);   
        rst_n = 0;
        #20; @(posedge clk); rst_n = 1;
        $display("Iniciando Teste Genérico com WIDTH=%0d", `TEST_WIDTH);
        
        // Testes Aleatórios
        repeat(1000) begin
            mcand_in <= $random;
            mult_in <= $random;
            sign_mode_in <= $random;
            @(posedge clk);
        end
        
        repeat(10) @(posedge clk);
        if (errors == 0) $display("SUCESSO: %0d testes passaram.", tests_run);
        else $display("FALHAS: %0d erros.", errors);
        $finish;
    end
endmodule

sim/8Bit/compact/simulacao.vcd
$date
	Tue Dec 16 09:36:45 2025
$end
$version
	Icarus Verilog
$end
$timescale
	1ps
$end
$scope module tb_booth_generic $end
$var wire 64 ! product_out [63:0] $end
$var parameter 32 " LATENCY $end
$var reg 1 # clk $end
$var reg 32 $ mcand_in [31:0] $end
$var reg 32 % mult_in [31:0] $end
$var reg 1 & rst_n $end
$var reg 2 ' sign_mode_in [1:0] $end
$var integer 32 ( errors [31:0] $end
$var integer 32 ) k [31:0] $end
$var integer 32 * tests_run [31:0] $end
$scope function calc_expected $end
$var reg 32 + a [31:0] $end
$var reg 33 , a_conv [32:0] $end
$var reg 32 - b [31:0] $end
$var reg 33 . b_conv [32:0] $end
$var reg 2 / mode [1:0] $end
$var reg 66 0 res [65:0] $end
$upscope $end
$scope module dut $end
$var wire 1 # clk $end
$var wire 32 1 multiplicand [31:0] $end
$var wire 32 2 multiplier [31:0] $end
$var wire 1 & rst_n $end
$var wire 1 3 s_bit_a $end
$var wire 1 4 s_bit_b $end
$var wire 2 5 sign_mode [1:0] $end
$var wire 36 6 A_ext [35:0] $end
$var parameter 33 7 CNT_L1 $end
$var parameter 34 8 CNT_L2 $end
$var parameter 35 9 CNT_L3 $end
$var parameter 36 : CNT_L4 $end
$var parameter 32 ; EXT_A_WIDTH $end
$var parameter 32 < NUM_ITEMS_L0 $end
$var parameter 32 = NUM_PPS $end
$var parameter 32 > OUT_WIDTH $end
$var parameter 32 ? WIDTH $end
$var reg 64 @ correction_accum [63:0] $end
$var reg 64 A product [63:0] $end
$var reg 36 B r1_A_1x [35:0] $end
$var reg 36 C r1_A_3x [35:0] $end
$var reg 37 D r1_B_coded [36:0] $end
$var integer 32 E i [31:0] $end
$var integer 32 F k [31:0] $end
$scope function get_booth_inv $end
$var reg 4 G group_bits [3:0] $end
$upscope $end
$scope function get_booth_val $end
$var reg 4 H group_bits [3:0] $end
$var reg 36 I in_1x [35:0] $end
$var reg 36 J in_3x [35:0] $end
$var reg 1 K inv $end
$var reg 36 L mag [35:0] $end
$var reg 64 M mag_shifted [63:0] $end
$var reg 3 N recoded [2:0] $end
$var reg 1 O sel_1x $end
$var reg 1 P sel_2x $end
$var reg 1 Q sel_3x $end
$var reg 1 R sel_4x $end
$var integer 32 S shift_amount [31:0] $end
$upscope $end
$upscope $end
$upscope $end
$enddefinitions $end
$comment Show the parameter values. $end
$dumpall
b100000 ?
b1000000 >
b1011 =
b1100 <
b100100 ;
b1 :
b10 9
b11 8
b110 7
b111 "
$end
#0
$dumpvars
bx S
xR
xQ
xP
xO
bx N
bx M
bx L
xK
bx J
bx I
bx H
bx G
bx F
b1100 E
b0 D
b0 C
b0 B
b0 A
bx @
bx 6
bx 5
x4
x3
bx 2
bx 1
bx 0
bx /
bx .
bx -
bx ,
bx +
b0 *
bx )
b0 (
bx '
0&
bx %
bx $
0#
b0 !
$end
#5000
b1100 E
b110 F
b1000 )
1#
#10000
0#
#15000
b1100 E
b1000 )
b1 F
1#
#20000
0#
#25000
14
03
b10010000101010011010100100100 6
bx !
bx A
bx0 D
bx C
bx B
b1 '
b1 5
b11000000100010010101111010000001 %
b11000000100010010101111010000001 2
b10010000101010011010100100100 $
b10010000101010011010100100100 1
b0 G
b0 M
b0 L
0R
0Q
0P
0O
0K
b0 N
b0 H
b0 I
b0 J
b11110 S
b1011 E
b0 @
b110 F
b0xxxxxxxxxxxxxxxxxxxxxxxxxxxxxxxx .
b0xxxxxxxxxxxxxxxxxxxxxxxxxxxxxxxx ,
b0 )
1&
1#
#30000
0#
#35000
04
b10110001111100000101011001100011 6
b1111110000001000100101011110100000010 D
b110110001111111001111101101100 C
b10010000101010011010100100100 B
b110101110010111101100001101 %
b110101110010111101100001101 2
b10110001111100000101011001100011 $
b10110001111100000101011001100011 1
bx G
bx M
bx L
xR
xQ
xP
xO
xK
bx N
bx H
bx I
bx J
b11110 S
b1011 E
b111111101110000100011001101011110101010110011101101111111100100100 0
b111000000100010010101111010000001 .
b10010000101010011010100100100 ,
b10010000101010011010100100100 +
b11000000100010010101111010000001 -
b1 /
b0 )
b1 F
1#
#40000
0#
#45000
14
b10110010110000101000010001100101 6
b0 !
b0 A
b1101011100101111011000011010 D
b1000010101110100010000001100101001 C
b10110001111100000101011001100011 B
b10001001001101110101001000010010 %
b10001001001101110101001000010010 2
b10110010110000101000010001100101 $
b10110010110000101000010001100101 1
b1000000001000000001001000000000 @
b1110 G
b10010000101010011010100100100 M
b10010000101010011010100100100 L
0R
0Q
0P
1O
1K
b1 N
b1110 H
b10010000101010011010100100100 I
b110110001111111001111101101100 J
b11110 S
b1011 E
b110 F
b10010101100100011100011110001000010010000001111010000000111 0
b110101110010111101100001101 .
b10110001111100000101011001100011 ,
b10110001111100000101011001100011 +
b110101110010111101100001101 -
b0 )
1#
#50000
0#
#55000
04
b110110101111100110100001101 6
b1111100010010011011101010010000100100 D
b1000011000010001111000110100101111 C
b10110010110000101000010001100101 B
b111011001000111111000101110110 %
b111011001000111111000101110110 2
b110110101111100110100001101 $
b110110101111100110100001101 1
0R
0P
0K
b0 G
b0 M
b0 L
0Q
0O
b0 N
b0 H
b10110001111100000101011001100011 I
b1000010101110100010000001100101001 J
b11110 S
b1011 E
b1001001000000001001000001 @
b111010110100001110001101011000111001011110110010001010100100011010 0
b110001001001101110101001000010010 .
b10110010110000101000010001100101 ,
b10110010110000101000010001100101 +
b10001001001101110101001000010010 -
b0 )
b1 F
1#
#60000
0#
#65000
b1110110110101000101011111101101 6
b1110110010001111110001011101100 D
b10100100001110110011100100111 C
b110110101111100110100001101 B
b1000110001011011111011110001100 %
b1000110001011011111011110001100 2
b1110110110101000101011111101101 $
b1110110110101000101011111101101 1
0Q
1K
0O
b1100 G
b101100101100001010000100011001010 M
b101100101100001010000100011001010 L
1P
b11 N
b1100 H
b10110010110000101000010001100101 I
b1000011000010001111000110100101111 J
b11110 S
b1011 E
b1000000000001001001000000000000 @
b110 F
b110010100101100100011011101010111010010001100000011111110 0
b111011001000111111000101110110 .
b110110101111100110100001101 ,
b110110101111100110100001101 +
b111011001000111111000101110110 -
b0 )
1#
#70000
0#
#75000
13
b111111100011001101110010010011000110 6
b10001100010110111110111100011000 D
b101100100011111010000011111000111 C
b1110110110101000101011111101101 B
b10 '
b10 5
b11100010111101111000010011000101 %
b11100010111101111000010011000101 2
b11100011001101110010010011000110 $
b11100011001101110010010011000110 1
0Q
0K
b1 G
0P
1O
b1 N
b1 H
b110110101111100110100001101 M
b110110101111100110100001101 L
b110110101111100110100001101 I
b10100100001110110011100100111 J
b11110 S
b1011 E
b1000000000000001000001001001 @
b10000010010011011001100100011000011111100111101100000010011100 0
b1000110001011011111011110001100 .
b1110110110101000101011111101101 ,
b1110110110101000101011111101101 +
b1000110001011011111011110001100 -
b0 )
b1 F
1#
#80000
0#
#85000
03
b1110010101011111111011111100101 6
bx !
bx A
b111000101111011110000100110001010 D
b111110101001101001010110111001010010 C
b111111100011001101110010010011000110 B
b10111011110100100111001001110111 %
b10111011110100100111001001110111 2
b1110010101011111111011111100101 $
b1110010101011111111011111100101 1
0Q
0P
b10 G
b1110110110101000101011111101101 M
b1110110110101000101011111101101 L
0R
1O
0K
b10 N
b10 H
b1110110110101000101011111101101 I
b101100100011111010000011111000111 J
b11110 S
b1011 E
b1000000000001000001000001 @
b110 F
b111110011001111010110110011011110110001111011011110110010001011110 0
b11100010111101111000010011000101 .
b111100011001101110010010011000110 ,
b11100011001101110010010011000110 +
b11100010111101111000010011000101 -
b10 /
b0 )
1#
#90000
0#
#95000
b1000111111011001101101110001111 6
b101110111101001001110010011101110 D
b101011000000011111110011110101111 C
b1110010101011111111011111100101 B
b1111101110000100011001101011110101010110011101101111111100100100 !
b1111101110000100011001101011110101010110011101101111111100100100 A
b1111001001100000110100111110010 %
b1111001001100000110100111110010 2
b1000111111011001101101110001111 $
b1000111111011001101101110001111 1
1R
0P
b111 G
b1111111111111111111111111111111110001100110111001001001100011000 M
b111110001100110111001001001100011000 L
0Q
0O
0K
b111 N
b111 H
b111111100011001101110010010011000110 I
b111110101001101001010110111001010010 J
b11110 S
b1011 E
b1000000001001000000000000001 @
b101010000100100110100011011010101001101000010100011010101110011 0
b10111011110100100111001001110111 .
b1110010101011111111011111100101 ,
b1110010101011111111011111100101 +
b10111011110100100111001001110111 -
b0 )
b1 *
b1 F
1#
#100000
0#
#105000
b11110100000000000111101011101000 6
b10010101100100011100011110001000010010000001111010000000111 !
b10010101100100011100011110001000010010000001111010000000111 A
b11110010011000001101001111100100 D
b11010111110001101001001010101101 C
b1000111111011001101101110001111 B
b0 '
b0 5
b11100010110010100100111011000101 %
b11100010110010100100111011000101 2
b11110100000000000111101011101000 $
b11110100000000000111101011101000 1
1Q
0P
b101 G
b101011000000011111110011110101111 M
b101011000000011111110011110101111 L
0R
0O
0K
b101 N
b101 H
b1110010101011111111011111100101 I
b101011000000011111110011110101111 J
b11110 S
b1011 E
b1000001001001001000000001001 @
b110 F
b10001000001100100011011111001111100101110001010011010000101110 0
b1111001001100000110100111110010 .
b1000111111011001101101110001111 ,
b1000111111011001101101110001111 +
b1111001001100000110100111110010 -
b0 )
b10 *
1#
#110000
0#
#115000
14
b11011110100011100010100010111101 6
b111000101100101001001110110001010 D
b1011011100000000010111000010111000 C
b11110100000000000111101011101000 B
b1010110100001110001101011000111001011110110010001010100100011010 !
b1010110100001110001101011000111001011110110010001010100100011010 A
b1 '
b1 5
b10010110101010110101100000101101 %
b10010110101010110101100000101101 2
b11011110100011100010100010111101 $
b11011110100011100010100010111101 1
0R
0O
0K
b11 G
b10001111110110011011011100011110 M
b10001111110110011011011100011110 L
0Q
1P
b11 N
b11 H
b1000111111011001101101110001111 I
b11010111110001101001001010101101 J
b11110 S
b1011 E
b1000000001000001001000001000 @
b1101100000101001001111111111010110110100111000010100010010001000 0
b11100010110010100100111011000101 .
b11110100000000000111101011101000 ,
b11110100000000000111101011101000 +
b11100010110010100100111011000101 -
b0 /
b0 )
b11 *
b1 F
1#
#120000
0#
#125000
04
b10110001111011110110001001100011 6
b110010100101100100011011101010111010010001100000011111110 !
b110010100101100100011011101010111010010001100000011111110 A
b1111100101101010101101011000001011010 D
b1010011011101010100111101000110111 C
b11011110100011100010100010111101 B
b0 '
b0 5
b101011100111000011100001010 %
b101011100111000011100001010 2
b10110001111011110110001001100011 $
b10110001111011110110001001100011 1
1R
0O
b111 G
b1111010000000000011110101110100000 M
b1111010000000000011110101110100000 L
0Q
0P
0K
b111 N
b111 H
b11110100000000000111101011101000 I
b1011011100000000010111000010111000 J
b11110 S
b1011 E
b1000001000001001001000000001 @
b110 F
b111010010001101110000110001011111011110001001111010010000100111001 0
b110010110101010110101100000101101 .
b11011110100011100010100010111101 ,
b11011110100011100010100010111101 +
b10010110101010110101100000101101 -
b1 /
b0 )
b100 *
1#
#130000
0#
#135000
b10000011001000010000100100000 6
b1010111001110000111000010100 D
b1000010101110011100010011100101001 C
b10110001111011110110001001100011 B
b10000010010011011001100100011000011111100111101100000010011100 !
b10000010010011011001100100011000011111100111101100000010011100 A
b1 '
b1 5
b1010101011110000100010110101010 %
b1010101011110000100010110101010 2
b10000011001000010000100100000 $
b10000011001000010000100100000 1
0O
1P
b1100 G
b110111101000111000101000101111010 M
b110111101000111000101000101111010 L
0R
0Q
1K
b11 N
b1100 H
b11011110100011100010100010111101 I
b1010011011101010100111101000110111 J
b11110 S
b1011 E
b1000001001000001001001000001001 @
b1111001001111110010101000101010001101101010000110011011110 0
b101011100111000011100001010 .
b10110001111011110110001001100011 ,
b10110001111011110110001001100011 +
b101011100111000011100001010 -
b0 /
b0 )
b101 *
b1 F
1#
#140000
0#
#145000
14
b11001011001000000011111010010110 6
b1110011001111010110110011011110110001111011011110110010001011110 !
b1110011001111010110110011011110110001111011011110110010001011110 A
b10101010111100001000101101010100 D
b110001001011000110001101100000 C
b10000011001000010000100100000 B
b10001001100000111011100000010011 %
b10001001100000111011100000010011 2
b11001011001000000011111010010110 $
b11001011001000000011111010010110 1
0Q
0R
0P
0O
b0 G
b0 M
b0 L
0K
b0 N
b0 H
b10110001111011110110001001100011 I
b1000010101110011100010011100101001 J
b11110 S
b1011 E
b1000001001000000001000000 @
b110 F
b10101111000111100100110010100000110011010111001111101000000 0
b1010101011110000100010110101010 .
b10000011001000010000100100000 ,
b10000011001000010000100100000 +
b1010101011110000100010110101010 -
b1 /
b0 )
b110 *
1#
#150000
0#
#155000
04
b10101001101001111101011001010011 6
b1111100010011000001110111000000100110 D
b1001100001011000001011101111000010 C
b11001011001000000011111010010110 B
b101010000100100110100011011010101001101000010100011010101110011 !
b101010000100100110100011011010101001101000010100011010101110011 A
b110101100111111101110101101011 %
b110101100111111101110101101011 2
b10101001101001111101011001010011 $
b10101001101001111101011001010011 1
0R
1O
0Q
0K
b10 G
b10000011001000010000100100000 M
b10000011001000010000100100000 L
0P
b10 N
b10 H
b10000011001000010000100100000 I
b110001001011000110001101100000 J
b11110 S
b1011 E
b1000001000001000001001000 @
b111010000111111100100001100111011010001101001000100111010100100010 0
b110001001100000111011100000010011 .
b11001011001000000011111010010110 ,
b11001011001000000011111010010110 +
b10001001100000111011100000010011 -
b0 )
b111 *
b1 F
1#
#160000
0#
#165000
14
b10000001000101110100101000000010 6
b10001000001100100011011111001111100101110001010011010000101110 !
b10001000001100100011011111001111100101110001010011010000101110 A
b1101011001111111011101011010110 D
b111111100111101111000001011111001 C
b10101001101001111101011001010011 B
b11010111010101100011111010101110 %
b11010111010101100011111010101110 2
b10000001000101110100101000000010 $
b10000001000101110100101000000010 1
0R
1K
1P
b1100 G
b110010110010000000111110100101100 M
b110010110010000000111110100101100 L
0Q
0O
b11 N
b1100 H
b11001011001000000011111010010110 I
b1001100001011000001011101111000010 J
b11110 S
b1011 E
b1000000001000001000001000000000 @
b110 F
b10001110001001101100010101101000011001101110010011101110110001 0
b110101100111111101110101101011 .
b10101001101001111101011001010011 ,
b10101001101001111101011001010011 +
b110101100111111101110101101011 -
b0 )
b1000 *
1#
#170000
0#
#175000
13
04
b111111100111110001010111001011001111 6
b1111110101110101011000111110101011100 D
b110000011010001011101111000000110 C
b10000001000101110100101000000010 B
b1101100000101001001111111111010110110100111000010100010010001000 !
b1101100000101001001111111111010110110100111000010100010010001000 A
b10 '
b10 5
b10001100001000100100100100011 %
b10001100001000100100100100011 2
b11100111110001010111001011001111 $
b11100111110001010111001011001111 1
1O
b1 G
b10101001101001111101011001010011 M
b10101001101001111101011001010011 L
0Q
0P
0K
b1 N
b1 H
b10101001101001111101011001010011 I
b111111100111101111000001011111001 J
b11110 S
b1011 E
b1001001000000001001001001000 @
b111110101101111110110000101001001111101100011011001100100101011100 0
b111010111010101100011111010101110 .
b10000001000101110100101000000010 ,
b10000001000101110100101000000010 +
b11010111010101100011111010101110 -
b0 )
b1001 *
b1 F
1#
#180000
0#
#185000
b111111100101011100110000101011001010 6
b1010010001101110000110001011111011110001001111010010000100111001 !
b1010010001101110000110001011111011110001001111010010000100111001 A
b100011000010001001001001000110 D
b111110110111010100000101100001101101 C
b111111100111110001010111001011001111 B
b10011110001100010100110000111100 %
b10011110001100010100110000111100 2
b11100101011100110000101011001010 $
b11100101011100110000101011001010 1
0R
0Q
b1110 G
b10000001000101110100101000000010 M
b10000001000101110100101000000010 L
0P
1O
1K
b1 N
b1110 H
b10000001000101110100101000000010 I
b110000011010001011101111000000110 J
b11110 S
b1011 E
b1000001000001001000001000001001 @
b110 F
b111111111001010111100101111000001011101111011101111011100101001101 0
b10001100001000100100100100011 .
b111100111110001010111001011001111 ,
b11100111110001010111001011001111 +
b10001100001000100100100100011 -
b10 /
b0 )
b1010 *
1#
#190000
0#
#195000
03
b1000101001011100110000110001010 6
b100111100011000101001100001111000 D
b111110110000010110010010000001011110 C
b111111100101011100110000101011001010 B
b1111001001111110010101000101010001101101010000110011011110 !
b1111001001111110010101000101010001101101010000110011011110 A
b0 '
b0 5
b100000110001001011001101000001 %
b100000110001001011001101000001 2
b1000101001011100110000110001010 $
b1000101001011100110000110001010 1
0P
0R
b0 G
b0 M
b0 L
0Q
0O
0K
b0 N
b0 H
b111111100111110001010111001011001111 I
b111110110111010100000101100001101101 J
b11110 S
b1011 E
b1000000001001001001000 @
b111110111110010111111000111100010110101010110101000111111101011000 0
b10011110001100010100110000111100 .
b111100101011100110000101011001010 ,
b11100101011100110000101011001010 +
b10011110001100010100110000111100 -
b0 )
b1011 *
b1 F
1#
#200000
0#
#205000
14
b111100001000001111001101111000 6
b10101111000111100100110010100000110011010111001111101000000 !
b10101111000111100100110010100000110011010111001111101000000 A
b1000001100010010110011010000010 D
b11001111100010110010010010011110 C
b1000101001011100110000110001010 B
b11 '
b11 5
b11000100100010100001001010001001 %
b11000100100010100001001010001001 2
b111100001000001111001101111000 $
b111100001000001111001101111000 1
0Q
1P
0O
b100 G
b1111111111111111111111111111111111001010111001100001010110010100 M
b111111001010111001100001010110010100 L
0R
0K
b100 N
b100 H
b111111100101011100110000101011001010 I
b111110110000010110010010000001011110 J
b11110 S
b1011 E
b1000001000001001000000001 @
b110 F
b100011011010111101000010010011101100101000100100001000001010 0
b100000110001001011001101000001 .
b1000101001011100110000110001010 ,
b1000101001011100110000110001010 +
b100000110001001011001101000001 -
b0 /
b0 )
b1100 *
1#
#210000
0#
#215000
04
b1011011000000100110010110110110 6
b1111110001001000101000010010100010010 D
b10110100011000101101101001101000 C
b111100001000001111001101111000 B
b1010000111111100100001100111011010001101001000100111010100100010 !
b1010000111111100100001100111011010001101001000100111010100100010 A
b10 '
b10 5
b1100011010010111111100111000110 %
b1100011010010111111100111000110 2
b1011011000000100110010110110110 $
b1011011000000100110010110110110 1
0R
0Q
0K
b1 G
b1000101001011100110000110001010 M
b1000101001011100110000110001010 L
0P
1O
b1 N
b1 H
b1000101001011100110000110001010 I
b11001111100010110010010010011110 J
b11110 S
b1011 E
b1000001000000000000001000000 @
b111111001000001000101101010000110110011101011100001011101100111000 0
b111000100100010100001001010001001 .
b111100001000001111001101111000 ,
b111100001000001111001101111000 +
b11000100100010100001001010001001 -
b11 /
b0 )
b1101 *
b1 F
1#
#220000
0#
#225000
13
b111111011110011101010000001010111100 6
b10001110001001101100010101101000011001101110010011101110110001 !
b10001110001001101100010101101000011001101110010011101110110001 A
b11000110100101111111001110001100 D
b100010001000001110011000100100010 C
b1011011000000100110010110110110 B
b11 '
b11 5
b10101000011111101110100101010 %
b10101000011111101110100101010 2
b11011110011101010000001010111100 $
b11011110011101010000001010111100 1
0Q
0R
1K
0P
1O
b1110 G
b111100001000001111001101111000 M
b111100001000001111001101111000 L
b1 N
b1110 H
b111100001000001111001101111000 I
b10110100011000101101101001101000 J
b11110 S
b1011 E
b1000001001000001000000000000000 @
b110 F
b10001101001100111011111101010011100111000110101011000011000100 0
b1100011010010111111100111000110 .
b1011011000000100110010110110110 ,
b1011011000000100110010110110110 +
b1100011010010111111100111000110 -
b10 /
b0 )
b1110 *
1#
#230000
0#
