rtl/8Bit/booth_radix8_pipeline.v
`timescale 1ns / 1ps
`default_nettype none

module booth_mult8_pipeline_opt (
    input  wire                  clk,
    input  wire                  rst_n,
    input  wire signed [7:0]     multiplicand,
    input  wire signed [7:0]     multiplier,
    input  wire [1:0]            sign_mode,
    output reg signed [15:0]     product
);

    // ========================================================================
    // ESTÁGIO 1: Pré-cálculo (Mantido)
    // ========================================================================
    localparam EXT_A_WIDTH = 12; 
    
    reg signed [EXT_A_WIDTH-1:0] r1_A_1x;
    reg signed [EXT_A_WIDTH-1:0] r1_A_3x;
    reg        [10:0]            r1_B_coded; 
    
    wire s_bit_a = sign_mode[1] & multiplicand[7];
    wire s_bit_b = sign_mode[0] & multiplier[7];
    wire signed [EXT_A_WIDTH-1:0] A_ext = { {(EXT_A_WIDTH-8){s_bit_a}}, multiplicand };

    always @(posedge clk or negedge rst_n) begin
        if (!rst_n) begin
            r1_A_1x    <= 0;
            r1_A_3x    <= 0;
            r1_B_coded <= 0;
        end else begin
            r1_A_1x <= A_ext;
            r1_A_3x <= A_ext + (A_ext <<< 1);
            r1_B_coded <= { s_bit_b, s_bit_b, multiplier, 1'b0 };
        end
    end

    // ========================================================================
    // ESTÁGIO 2: Geração de PPs (PURAMENTE LÓGICO - SEM SOMA)
    // ========================================================================
    // Separa o valor (1's complement) do bit de ajuste (+1)
    
    reg signed [15:0] r2_pp0_val;
    reg signed [15:0] r2_pp1_val;
    reg signed [15:0] r2_pp2_val;
    reg               r2_inv0, r2_inv1, r2_inv2;

    // Função modificada: Retorna apenas o XOR, sem somar o carry
    function signed [15:0] get_booth_val (
        input [3:0]                  group_bits,
        input signed [EXT_A_WIDTH-1:0] in_1x,
        input signed [EXT_A_WIDTH-1:0] in_3x
    );
        reg sel_1x, sel_2x, sel_3x, sel_4x;
        reg [2:0] recoded;
        reg signed [EXT_A_WIDTH-1:0] mag;
        reg inv;
        reg signed [15:0] mag_extended; 
    begin
        recoded = group_bits[2:0] ^ {3{group_bits[3]}};
        inv     = group_bits[3] & ~(&group_bits[2:0]); 

        sel_1x = (recoded == 3'b001 || recoded == 3'b010);
        sel_2x = (recoded == 3'b011 || recoded == 3'b100);
        sel_3x = (recoded == 3'b101 || recoded == 3'b110);
        sel_4x = (recoded == 3'b111);

        mag = ({EXT_A_WIDTH{sel_1x}} & in_1x) |
              ({EXT_A_WIDTH{sel_2x}} & (in_1x <<< 1)) |
              ({EXT_A_WIDTH{sel_3x}} & in_3x) |
              ({EXT_A_WIDTH{sel_4x}} & (in_1x <<< 2));

        mag_extended = mag; // Sign extension ocorre aqui
        
        // AQUI ESTÁ A OTIMIZAÇÃO: Apenas XOR. A soma acontece no próximo clock.
        get_booth_val = mag_extended ^ {16{inv}};
    end
    endfunction
    
    // Função auxiliar para extrair apenas o bit de inversão
    function get_booth_inv (input [3:0] group_bits);
        get_booth_inv = group_bits[3] & ~(&group_bits[2:0]);
    endfunction

    always @(posedge clk or negedge rst_n) begin
        if (!rst_n) begin
            r2_pp0_val <= 0; r2_inv0 <= 0;
            r2_pp1_val <= 0; r2_inv1 <= 0;
            r2_pp2_val <= 0; r2_inv2 <= 0;
        end else begin
            r2_pp0_val <= get_booth_val(r1_B_coded[3:0], r1_A_1x, r1_A_3x);
            r2_inv0    <= get_booth_inv(r1_B_coded[3:0]);

            r2_pp1_val <= get_booth_val(r1_B_coded[6:3], r1_A_1x, r1_A_3x);
            r2_inv1    <= get_booth_inv(r1_B_coded[6:3]);

            r2_pp2_val <= get_booth_val(r1_B_coded[9:6], r1_A_1x, r1_A_3x);
            r2_inv2    <= get_booth_inv(r1_B_coded[9:6]);
        end
    end

    // ========================================================================
    // ESTÁGIO 3: Árvore de Soma Balanceada
    // ========================================================================
    // Caminho A: PP0 + PP1
    // Caminho B: PP2 + Bits de Correção (Hot Bits)
    
    reg signed [15:0] r3_sum_A;
    reg signed [15:0] r3_sum_B;

    always @(posedge clk or negedge rst_n) begin
        if (!rst_n) begin
            r3_sum_A <= 0;
            r3_sum_B <= 0;
        end else begin
            // Adder 1
            r3_sum_A <= r2_pp0_val + (r2_pp1_val <<< 3);
            
            // Adder 2: Soma o PP2 com o vetor formado pelos bits de inversão
            // inv0 na pos 0, inv1 na pos 3, inv2 na pos 6
            r3_sum_B <= (r2_pp2_val <<< 6) + 
                        { 9'b0, r2_inv2, 2'b0, r2_inv1, 2'b0, r2_inv0 };
        end
    end

    // ========================================================================
    // ESTÁGIO 4: Soma Final
    // ========================================================================
    
    always @(posedge clk or negedge rst_n) begin
        if (!rst_n) begin
            product <= 16'sd0;
        end else begin
            // Adder 3 (Final)
            product <= r3_sum_A + r3_sum_B;
        end
    end

endmodule
`default_nettype wire

tb/tb_booth_radix8_8_pipeline.v
`timescale 1ns / 1ps

module tb_booth_mult8_pipeline_opt;

    // ------------------------------------------------------------------------
    // Sinais e Constantes
    // ------------------------------------------------------------------------
    reg clk;
    reg rst_n;
    reg signed [7:0] mcand_in;
    reg signed [7:0] mult_in;
    reg [1:0] sign_mode_in;
    
    wire signed [15:0] product_out;

    integer errors = 0;
    integer tests_run = 0;

    localparam MODE_UU = 2'b00;
    localparam MODE_US = 2'b01;
    localparam MODE_SU = 2'b10;
    localparam MODE_SS = 2'b11;

    // ATENÇÃO: Latência atualizada para 4 ciclos (Retiming para 223 MHz)
    localparam LATENCY = 4;

    // Arrays para pipeline de verificação
    reg signed [15:0] expected_pipe [0:LATENCY];
    reg [15:0]        debug_a_pipe  [0:LATENCY];
    reg [15:0]        debug_b_pipe  [0:LATENCY];
    reg [1:0]         debug_mode_pipe [0:LATENCY];
    reg               valid_pipe    [0:LATENCY];

    // ------------------------------------------------------------------------
    // GERAÇÃO DE VCD
    // ------------------------------------------------------------------------
    initial begin
        $dumpfile("booth_opt_223mhz.vcd");
        $dumpvars(0, tb_booth_mult8_pipeline_opt);
    end

    // ------------------------------------------------------------------------
    // Instanciação do DUT Otimizado
    // ------------------------------------------------------------------------
    booth_mult8_pipeline_opt dut (
        .clk(clk),
        .rst_n(rst_n),
        .multiplicand(mcand_in),
        .multiplier(mult_in),
        .sign_mode(sign_mode_in),
        .product(product_out)
    );

    // ------------------------------------------------------------------------
    // Clock (Simulando alta frequência, embora funcionalmente não mude a lógica)
    // ------------------------------------------------------------------------
    initial clk = 0;
    always #2.23 clk = ~clk; // ~224 MHz period (apenas cosmético na simulação funcional)

    // ------------------------------------------------------------------------
    // Golden Model
    // ------------------------------------------------------------------------
    function signed [15:0] calc_expected;
        input [7:0] a, b;
        input [1:0] mode;
        reg signed [8:0] a_conv, b_conv;
        reg signed [17:0] res;
    begin
        if (mode[1]) a_conv = $signed(a); else a_conv = $signed({1'b0, a});
        if (mode[0]) b_conv = $signed(b); else b_conv = $signed({1'b0, b});
        res = a_conv * b_conv;
        calc_expected = res[15:0];
    end
    endfunction

    // ------------------------------------------------------------------------
    // Verificação e Shift Register
    // ------------------------------------------------------------------------
    integer k;
    always @(posedge clk) begin
        if (!rst_n) begin
            for (k=0; k<=LATENCY; k=k+1) valid_pipe[k] <= 0;
        end else begin
            // 1. Verificação (LATENCY-1 devido ao atraso do NBA <=)
            if (valid_pipe[LATENCY-1]) begin
                if (product_out !== expected_pipe[LATENCY-1]) begin
                    $display("ERRO Time %0t | Mode %b | A: %h B: %h", $time, 
                             debug_mode_pipe[LATENCY-1], debug_a_pipe[LATENCY-1], debug_b_pipe[LATENCY-1]);
                    $display("    Exp: %h (%d) | Obt: %h (%d)", 
                             expected_pipe[LATENCY-1], expected_pipe[LATENCY-1], 
                             product_out, product_out);
                    errors = errors + 1;
                end
                tests_run = tests_run + 1;
            end

            // 2. Shift Register
            for (k = LATENCY; k > 0; k = k - 1) begin
                expected_pipe[k]   <= expected_pipe[k-1];
                debug_a_pipe[k]    <= debug_a_pipe[k-1];
                debug_b_pipe[k]    <= debug_b_pipe[k-1];
                debug_mode_pipe[k] <= debug_mode_pipe[k-1];
                valid_pipe[k]      <= valid_pipe[k-1];
            end

            // 3. Load Input
            expected_pipe[0]   <= calc_expected(mcand_in, mult_in, sign_mode_in);
            debug_a_pipe[0]    <= {8'b0, mcand_in};
            debug_b_pipe[0]    <= {8'b0, mult_in};
            debug_mode_pipe[0] <= sign_mode_in;
            valid_pipe[0]      <= 1'b1;
        end
    end

    // ------------------------------------------------------------------------
    // Sequência de Teste
    // ------------------------------------------------------------------------
    reg [7:0] corners [0:7];
    initial begin
        corners[0]=8'h00; corners[1]=8'h01; corners[2]=8'h7F; corners[3]=8'h80;
        corners[4]=8'hFF; corners[5]=8'hAA; corners[6]=8'h55; corners[7]=8'h02;

        rst_n = 0; mcand_in = 0; mult_in = 0; sign_mode_in = 0;
        #20; @(posedge clk); rst_n = 1;

        $display("=== INICIANDO VERIFICACAO (LATENCY=4) ===");
        run_phase(MODE_UU, "UU");
        run_phase(MODE_US, "US");
        run_phase(MODE_SU, "SU");
        run_phase(MODE_SS, "SS");

        repeat(6) @(posedge clk); // Drain pipe (4+2 ciclos)
        
        if (errors == 0) 
            $display("\nSUCESSO TOTAL: %0d testes passaram. Arquitetura Solida!", tests_run);
        else 
            $display("\nFALHA: %0d erros encontrados.", errors);
            
        $finish;
    end

    task run_phase;
        input [1:0] mode;
        input [15:0] name;
        integer i, j;
    begin
        $display("Testando %s...", name);
        for(i=0;i<8;i=i+1) for(j=0;j<8;j=j+1) drive(corners[i], corners[j], mode);
        for(i=0;i<100;i=i+1) drive($random, $random, mode);
    end
    endtask

    task drive;
        input [7:0] a, b;
        input [1:0] m;
    begin
        mcand_in <= a; mult_in <= b; sign_mode_in <= m;
        @(posedge clk);
    end
    endtask

endmodule

sim/8Bit/pipeline/booth_opt_223mhz.vcd
$date
	Tue Dec 16 09:40:10 2025
$end
$version
	Icarus Verilog
$end
$timescale
	1ps
$end
$scope module tb_booth_mult8_pipeline_opt $end
$var wire 16 ! product_out [15:0] $end
$var parameter 32 " LATENCY $end
$var parameter 2 # MODE_SS $end
$var parameter 2 $ MODE_SU $end
$var parameter 2 % MODE_US $end
$var parameter 2 & MODE_UU $end
$var reg 1 ' clk $end
$var reg 8 ( mcand_in [7:0] $end
$var reg 8 ) mult_in [7:0] $end
$var reg 1 * rst_n $end
$var reg 2 + sign_mode_in [1:0] $end
$var integer 32 , errors [31:0] $end
$var integer 32 - k [31:0] $end
$var integer 32 . tests_run [31:0] $end
$scope function calc_expected $end
$var reg 8 / a [7:0] $end
$var reg 9 0 a_conv [8:0] $end
$var reg 8 1 b [7:0] $end
$var reg 9 2 b_conv [8:0] $end
$var reg 2 3 mode [1:0] $end
$var reg 18 4 res [17:0] $end
$upscope $end
$scope module dut $end
$var wire 1 ' clk $end
$var wire 8 5 multiplicand [7:0] $end
$var wire 8 6 multiplier [7:0] $end
$var wire 1 * rst_n $end
$var wire 1 7 s_bit_a $end
$var wire 1 8 s_bit_b $end
$var wire 2 9 sign_mode [1:0] $end
$var wire 12 : A_ext [11:0] $end
$var parameter 32 ; EXT_A_WIDTH $end
$var reg 16 < product [15:0] $end
$var reg 12 = r1_A_1x [11:0] $end
$var reg 12 > r1_A_3x [11:0] $end
$var reg 11 ? r1_B_coded [10:0] $end
$var reg 1 @ r2_inv0 $end
$var reg 1 A r2_inv1 $end
$var reg 1 B r2_inv2 $end
$var reg 16 C r2_pp0_val [15:0] $end
$var reg 16 D r2_pp1_val [15:0] $end
$var reg 16 E r2_pp2_val [15:0] $end
$var reg 16 F r3_sum_A [15:0] $end
$var reg 16 G r3_sum_B [15:0] $end
$scope function get_booth_inv $end
$var reg 4 H group_bits [3:0] $end
$upscope $end
$scope function get_booth_val $end
$var reg 4 I group_bits [3:0] $end
$var reg 12 J in_1x [11:0] $end
$var reg 12 K in_3x [11:0] $end
$var reg 1 L inv $end
$var reg 12 M mag [11:0] $end
$var reg 16 N mag_extended [15:0] $end
$var reg 3 O recoded [2:0] $end
$var reg 1 P sel_1x $end
$var reg 1 Q sel_2x $end
$var reg 1 R sel_3x $end
$var reg 1 S sel_4x $end
$upscope $end
$upscope $end
$scope task drive $end
$var reg 8 T a [7:0] $end
$var reg 8 U b [7:0] $end
$var reg 2 V m [1:0] $end
$upscope $end
$scope task run_phase $end
$var reg 2 W mode [1:0] $end
$var reg 16 X name [15:0] $end
$var integer 32 Y i [31:0] $end
$var integer 32 Z j [31:0] $end
$upscope $end
$upscope $end
$enddefinitions $end
$comment Show the parameter values. $end
$dumpall
b1100 ;
b0 &
b1 %
b10 $
b11 #
b100 "
$end
#0
$dumpvars
bx Z
bx Y
bx X
bx W
bx V
bx U
bx T
xS
xR
xQ
xP
bx O
bx N
bx M
xL
bx K
bx J
bx I
bx H
b0 G
b0 F
b0 E
b0 D
b0 C
0B
0A
0@
b0 ?
b0 >
b0 =
b0 <
b0 :
b0 9
08
07
b0 6
b0 5
bx 4
bx 3
bx 2
bx 1
bx 0
bx /
b0 .
bx -
b0 ,
b0 +
0*
b0 )
b0 (
0'
b0 !
$end
#2230
b101 -
1'
#4460
0'
#6690
b101 -
1'
#8920
0'
#11150
b101 -
1'
#13380
0'
#15610
b101 -
1'
#17840
0'
#20070
b0 H
b0 N
b0 M
0S
0R
0Q
0P
0L
b0 O
b0 I
b0 J
b0 K
b0 V
b0 U
b0 T
b0 Z
b0 Y
b0 4
b0 2
b0 0
b0 /
b0 1
b0 3
b0 -
b101010101010101 X
b0 W
1*
1'
#22300
0'
#24530
b1 )
b1 6
b1 U
b1 Z
b0 -
1'
#26760
0'
#28990
b10 ?
b1111111 )
b1111111 6
b1111111 U
b10 Z
b1 2
b1 1
b0 -
1'
#31220
0'
#33450
b11111110 ?
b10000000 )
b10000000 6
b0 H
0P
b0 O
b0 I
b10000000 U
b11 Z
b1111111 2
b1111111 1
b0 -
1'
#35680
0'
#37910
1@
b1111111111111111 C
b100000000 ?
b11111111 )
b11111111 6
1Q
b11 H
0P
0L
b11 O
b11 I
b11111111 U
b100 Z
b10000000 2
b10000000 1
b0 -
b1 .
1'
#40140
0'
#42370
b111111110 ?
0@
b0 C
b1 G
b1111111111111111 F
b10101010 )
b10101010 6
b100 H
1Q
b100 O
b100 I
b10101010 U
b101 Z
b11111111 2
b11111111 1
b0 -
b10 .
1'
#44600
0'
#46830
b0 G
b0 F
1@
b1111111111111111 C
b101010100 ?
b1010101 )
b1010101 6
1S
b111 H
0Q
0P
0L
b111 O
b111 I
b1010101 U
b110 Z
b10101010 2
b10101010 1
b0 -
b11 .
1'
#49060
0'
#51290
b10101010 ?
1A
b1111111111111111 D
0@
b0 C
b1 G
b1111111111111111 F
b10 )
b10 6
1R
0L
b101 H
0S
0Q
b101 O
b101 I
b10 U
b111 Z
b1010101 2
b1010101 1
b0 -
b100 .
1'
#53520
0'
#55750
b1 :
b1000 G
b1111111111111000 F
0A
b0 D
1@
b1111111111111111 C
b100 ?
b0 )
b0 6
b1 (
b1 5
0R
1P
b10 O
b10 H
0L
b10 I
b0 U
b1 T
b1 Y
b0 Z
b10 2
b10 1
b0 -
b101 .
1'
#57980
0'
#60210
b0 ?
b11 >
b1 =
0@
b0 C
b1 G
b1111111111111111 F
b1 )
b1 6
b0 H
0Q
0P
b0 O
b0 I
b1 U
b1 Z
b0 2
b1 0
b1 /
b0 1
b0 -
b110 .
1'
#62440
0'
#64670
b0 G
b0 F
b10 ?
b1111111 )
b1111111 6
b1 J
b11 K
b1111111 U
b10 Z
b1 4
b1 2
b1 1
b0 -
b111 .
1'
#66900
0'
#69130
b11111110 ?
b1 C
b10000000 )
b10000000 6
b0 H
b0 N
b0 M
0P
b0 O
b0 I
b10000000 U
b11 Z
b1111111 4
b1111111 2
b1111111 1
b0 -
b1000 .
1'
#71360
0'
#73590
b1 F
b10 E
1@
b1111111111111110 C
b100000000 ?
b11111111 )
b11111111 6
1Q
b11 H
b10 N
b10 M
0P
0L
b11 O
b11 I
b11111111 U
b100 Z
b10000000 4
b10000000 2
b10000000 1
b0 -
b1001 .
1'
#75820
0'
#78050
b111111110 ?
0@
b0 C
b10000001 G
b1111111111111110 F
b1 !
b1 <
b10101010 )
b10101010 6
b100 H
b10 N
b10 M
1Q
b100 O
b100 I
b10101010 U
b101 Z
b11111111 4
b11111111 2
b11111111 1
b0 -
b1010 .
1'
#80280
0'
#82510
b1111111 !
b1111111 <
b10000000 G
b0 F
b100 E
1@
b1111111111111110 C
b101010100 ?
b1010101 )
b1010101 6
1S
b111 H
b100 N
b100 M
0Q
0P
0L
b111 O
b111 I
b1010101 U
b110 Z
b10101010 4
b10101010 2
b10101010 1
b0 -
b1011 .
1'
#84740
0'
#86970
b10101010 ?
b11 E
1A
b1111111111111100 D
0@
b10 C
b100000001 G
b1111111111111110 F
b10000000 !
b10000000 <
b10 )
b10 6
1R
0L
b101 H
b11 N
b11 M
0S
0Q
b101 O
b101 I
b10 U
b111 Z
b1010101 4
b1010101 2
b1010101 1
b0 -
b1100 .
1'
#89200
0'
#91430
b1111111 :
b11111111 !
b11111111 <
b11001000 G
b1111111111100010 F
b1 E
0A
b11 D
1@
b1111111111111100 C
b100 ?
b0 )
b0 6
b1111111 (
b1111111 5
b1 N
b1 M
0R
1P
b10 O
b10 H
0L
b10 I
b0 U
b1111111 T
b10 Y
b0 Z
b10 4
b10 2
b10 1
b0 -
b1101 .
1'
#93660
0'
#95890
b0 ?
b101111101 >
b1111111 =
b0 E
b0 D
0@
b10 C
b1000001 G
b10100 F
b10101010 !
b10101010 <
b1 )
b1 6
b0 H
b0 N
b0 M
0Q
0P
b0 O
b0 I
b1 U
b1 Z
b0 4
b0 2
b1111111 0
b1111111 /
b0 1
b0 -
b1110 .
1'
#98120
0'
#100350
b1010101 !
b1010101 <
b0 G
b10 F
b0 C
b10 ?
b1111111 )
b1111111 6
b1111111 J
b101111101 K
b1111111 U
b10 Z
b1111111 4
b1 2
b1 1
b0 -
b1111 .
1'
#102580
0'
#104810
b11111110 ?
b1111111 C
b0 F
b10 !
b10 <
b10000000 )
b10000000 6
b0 H
b0 N
b0 M
0P
b0 O
b0 I
b10000000 U
b11 Z
b11111100000001 4
b1111111 2
b1111111 1
b0 -
b10000 .
1'
#107040
0'
#109270
b0 !
b0 <
b1111111 F
b11111110 E
1@
b1111111110000000 C
b100000000 ?
b11111111 )
b11111111 6
1Q
b11 H
b11111110 N
b11111110 M
0P
0L
b11 O
b11 I
b11111111 U
b100 Z
b11111110000000 4
b10000000 2
b10000000 1
b0 -
b10001 .
1'
#111500
0'
#113730
b111111110 ?
0@
b0 C
b11111110000001 G
b1111111110000000 F
b1111111 !
b1111111 <
b10101010 )
b10101010 6
b100 H
b11111110 N
b11111110 M
1Q
b100 O
b100 I
b10101010 U
b101 Z
b111111010000001 4
b11111111 2
b11111111 1
b0 -
b10010 .
1'
#115960
0'
#118190
b11111100000001 !
b11111100000001 <
b11111110000000 G
b0 F
b111111100 E
1@
b1111111110000000 C
b101010100 ?
b1010101 )
b1010101 6
1S
b111 H
b111111100 N
b111111100 M
0Q
0P
0L
b111 O
b111 I
b1010101 U
b110 Z
b101010001010110 4
b10101010 2
b10101010 1
b0 -
b10011 .
1'
#120420
0'
#122650
b10101010 ?
b101111101 E
1A
b1111111010000010 D
0@
b11111110 C
b111111100000001 G
b1111111110000000 F
b11111110000000 !
b11111110000000 <
b10 )
b10 6
1R
0L
b101 H
b101111101 N
b101111101 M
0S
0Q
b101 O
b101 I
b10 U
b111 Z
b10101000101011 4
b1010101 2
b1010101 1
b0 -
b10100 .
1'
#124880
0'
#127110
b10000000 :
b111111010000001 !
b111111010000001 <
b101111101001000 G
b1111010100001110 F
b1111111 E
0A
b101111101 D
1@
b1111111010000010 C
b100 ?
b0 )
b0 6
b10000000 (
b10000000 5
b1111111 N
b1111111 M
0R
1P
b10 O
b10 H
0L
b10 I
b0 U
b10000000 T
b11 Y
b0 Z
b11111110 4
b10 2
b10 1
b0 -
b10101 .
1'
#129340
0'
#131570
b0 ?
b110000000 >
b10000000 =
b0 E
b0 D
0@
b11111110 C
b1111111000001 G
b101001101010 F
b101010001010110 !
b101010001010110 <
b1 )
b1 6
b0 H
b0 N
b0 M
0Q
0P
b0 O
b0 I
b1 U
b1 Z
b0 4
b0 2
b10000000 0
b10000000 /
b0 1
b0 -
b10110 .
1'
#133800
0'
#136030
b10101000101011 !
b10101000101011 <
b0 G
b11111110 F
b0 C
b10 ?
b1111111 )
b1111111 6
b10000000 J
b110000000 K
b1111111 U
b10 Z
b10000000 4
b1 2
b1 1
b0 -
b10111 .
1'
#138260
0'
#140490
b11111110 ?
b10000000 C
b0 F
b11111110 !
b11111110 <
b10000000 )
b10000000 6
b0 H
b0 N
b0 M
0P
b0 O
b0 I
b10000000 U
b11 Z
b11111110000000 4
b1111111 2
b1111111 1
b0 -
b11000 .
1'
#142720
0'
#144950
b0 !
b0 <
b10000000 F
b100000000 E
1@
b1111111101111111 C
b100000000 ?
b11111111 )
b11111111 6
1Q
b11 H
b100000000 N
b100000000 M
0P
0L
b11 O
b11 I
b11111111 U
b100 Z
b100000000000000 4
b10000000 2
b10000000 1
b0 -
b11001 .
1'
#147180
0'
#149410
b111111110 ?
0@
b0 C
b100000000000001 G
b1111111101111111 F
b10000000 !
b10000000 <
b10101010 )
b10101010 6
b100 H
b100000000 N
b100000000 M
1Q
b100 O
b100 I
b10101010 U
b101 Z
b111111110000000 4
b11111111 2
b11111111 1
b0 -
b11010 .
1'
#151640
0'
#153870
b11111110000000 !
b11111110000000 <
b100000000000000 G
b0 F
b1000000000 E
1@
b1111111101111111 C
b101010100 ?
b1010101 )
b1010101 6
1S
b111 H
b1000000000 N
b1000000000 M
0Q
0P
0L
b111 O
b111 I
b1010101 U
b110 Z
b101010100000000 4
b10101010 2
b10101010 1
b0 -
b11011 .
1'
#156100
0'
#158330
b10101010 ?
b110000000 E
1A
b1111111001111111 D
0@
b100000000 C
b1000000000000001 G
b1111111101111111 F
b100000000000000 !
b100000000000000 <
b10 )
b10 6
1R
0L
b101 H
b110000000 N
b110000000 M
0S
0Q
b101 O
b101 I
b10 U
b111 Z
b10101010000000 4
b1010101 2
b1010101 1
b0 -
b11100 .
1'
#160560
0'
#162790
b11111111 :
b111111110000000 !
b111111110000000 <
b110000000001000 G
b1111010011111000 F
b10000000 E
0A
b110000000 D
1@
b1111111001111111 C
b100 ?
b0 )
b0 6
b11111111 (
b11111111 5
b10000000 N
b10000000 M
0R
1P
b10 O
b10 H
0L
b10 I
b0 U
b11111111 T
b100 Y
b0 Z
b100000000 4
b10 2
b10 1
b0 -
b11101 .
1'
#165020
0'
#167250
b0 ?
b1011111101 >
b11111111 =
b0 E
b0 D
0@
b100000000 C
b10000000000001 G
b101001111111 F
b101010100000000 !
b101010100000000 <
b1 )
b1 6
b0 H
b0 N
b0 M
0Q
0P
b0 O
b0 I
b1 U
b1 Z
b0 4
b0 2
b11111111 0
b11111111 /
b0 1
b0 -
b11110 .
1'
#169480
0'
#171710
b10101010000000 !
b10101010000000 <
b0 G
b100000000 F
b0 C
b10 ?
b1111111 )
b1111111 6
b11111111 J
b1011111101 K
b1111111 U
b10 Z
b11111111 4
b1 2
b1 1
b0 -
b11111 .
1'
#173940
0'
#176170
b11111110 ?
b11111111 C
b0 F
b100000000 !
b100000000 <
b10000000 )
b10000000 6
b0 H
b0 N
b0 M
0P
b0 O
b0 I
b10000000 U
b11 Z
b111111010000001 4
b1111111 2
b1111111 1
b0 -
b100000 .
1'
#178400
0'
#180630
b0 !
b0 <
b11111111 F
b111111110 E
1@
b1111111100000000 C
b100000000 ?
b11111111 )
b11111111 6
1Q
b11 H
b111111110 N
b111111110 M
0P
0L
b11 O
b11 I
b11111111 U
b100 Z
b111111110000000 4
b10000000 2
b10000000 1
b0 -
b100001 .
1'
#182860
0'
#185090
b111111110 ?
0@
b0 C
b111111110000001 G
b1111111100000000 F
b11111111 !
b11111111 <
b10101010 )
b10101010 6
b100 H
b111111110 N
b111111110 M
1Q
b100 O
b100 I
b10101010 U
b101 Z
b1111111000000001 4
b11111111 2
b11111111 1
b0 -
b100010 .
1'
#187320
0'
#189550
b111111010000001 !
b111111010000001 <
b111111110000000 G
b0 F
b1111111100 E
1@
b1111111100000000 C
b101010100 ?
b1010101 )
b1010101 6
1S
b111 H
b1111111100 N
b1111111100 M
0Q
0P
0L
b111 O
b111 I
b1010101 U
b110 Z
b1010100101010110 4
b10101010 2
b10101010 1
b0 -
b100011 .
1'
#191780
0'
#194010
b10101010 ?
b1011111101 E
1A
b1111110100000010 D
0@
b111111110 C
b1111111100000001 G
b1111111100000000 F
b111111110000000 !
b111111110000000 <
b10 )
b10 6
1R
0L
b101 H
b1011111101 N
b1011111101 M
0S
0Q
b101 O
b101 I
b10 U
b111 Z
b101010010101011 4
b1010101 2
b1010101 1
b0 -
b100100 .
1'
#196240
0'
#198470
b10101010 :
b1111111000000001 !
b1111111000000001 <
b1011111101001000 G
b1110101000001110 F
b11111111 E
0A
b1011111101 D
1@
b1111110100000010 C
b100 ?
b0 )
b0 6
b10101010 (
b10101010 5
b11111111 N
b11111111 M
0R
1P
b10 O
b10 H
0L
b10 I
b0 U
b10101010 T
b101 Y
b0 Z
b111111110 4
b10 2
b10 1
b0 -
b100101 .
1'
#200700
0'
#202930
b0 ?
b111111110 >
b10101010 =
b0 E
b0 D
0@
b111111110 C
b11111111000001 G
b1010011101010 F
b1010100101010110 !
b1010100101010110 <
b1 )
b1 6
b0 H
b0 N
b0 M
0Q
0P
b0 O
b0 I
b1 U
b1 Z
b0 4
b0 2
b10101010 0
b10101010 /
b0 1
b0 -
b100110 .
1'
#205160
0'
#207390
b101010010101011 !
b101010010101011 <
b0 G
b111111110 F
b0 C
b10 ?
b1111111 )
b1111111 6
b10101010 J
b111111110 K
b1111111 U
b10 Z
b10101010 4
b1 2
b1 1
b0 -
b100111 .
1'
#209620
0'
#211850
b11111110 ?
b10101010 C
b0 F
b111111110 !
b111111110 <
b10000000 )
b10000000 6
b0 H
b0 N
b0 M
0P
b0 O
b0 I
b10000000 U
b11 Z
b101010001010110 4
b1111111 2
b1111111 1
b0 -
b101000 .
1'
#214080
0'
#216310
b0 !
b0 <
b10101010 F
b101010100 E
1@
b1111111101010101 C
b100000000 ?
b11111111 )
b11111111 6
1Q
b11 H
b101010100 N
b101010100 M
0P
0L
b11 O
b11 I
b11111111 U
b100 Z
b101010100000000 4
b10000000 2
b10000000 1
b0 -
b101001 .
1'
#218540
0'
#220770
b111111110 ?
0@
b0 C
b101010100000001 G
b1111111101010101 F
b10101010 !
b10101010 <
b10101010 )
b10101010 6
b100 H
b101010100 N
b101010100 M
1Q
b100 O
b100 I
b10101010 U
b101 Z
b1010100101010110 4
b11111111 2
b11111111 1
b0 -
b101010 .
1'
#223000
0'
#225230
b101010001010110 !
b101010001010110 <
b101010100000000 G
b0 F
b1010101000 E
1@
b1111111101010101 C
b101010100 ?
b1010101 )
b1010101 6
1S
b111 H
b1010101000 N
b1010101000 M
0Q
0P
0L
b111 O
b111 I
b1010101 U
b110 Z
b111000011100100 4
b10101010 2
b10101010 1
b0 -
b101011 .
1'
#227460
0'
#229690
b10101010 ?
b111111110 E
1A
b1111111000000001 D
0@
b101010100 C
b1010101000000001 G
b1111111101010101 F
b101010100000000 !
b101010100000000 <
b10 )
b10 6
1R
0L
b101 H
b111111110 N
b111111110 M
0S
0Q
b101 O
b101 I
b10 U
b111 Z
b11100001110010 4
b1010101 2
b1010101 1
b0 -
b101100 .
1'
#231920
0'
#234150
b1010101 :
b1010100101010110 !
b1010100101010110 <
b111111110001000 G
b1111000101011100 F
b10101010 E
0A
b111111110 D
1@
b1111111000000001 C
b100 ?
b0 )
b0 6
b1010101 (
b1010101 5
b10101010 N
b10101010 M
0R
1P
b10 O
b10 H
0L
b10 I
b0 U
b1010101 T
b110 Y
b0 Z
b101010100 4
b10 2
b10 1
b0 -
b101101 .
1'
#236380
0'
#238610
b0 ?
b11111111 >
b1010101 =
b0 E
b0 D
0@
b101010100 C
b10101010000001 G
b110111110001 F
b111000011100100 !
b111000011100100 <
b1 )
b1 6
b0 H
b0 N
b0 M
0Q
0P
b0 O
b0 I
b1 U
b1 Z
b0 4
b0 2
b1010101 0
b1010101 /
b0 1
b0 -
b101110 .
1'
#240840
0'
#243070
b11100001110010 !
b11100001110010 <
b0 G
b101010100 F
b0 C
b10 ?
b1111111 )
b1111111 6
b1010101 J
b11111111 K
b1111111 U
b10 Z
b1010101 4
b1 2
b1 1
b0 -
b101111 .
1'
#245300
0'
#247530
b11111110 ?
b1010101 C
b0 F
b101010100 !
b101010100 <
b10000000 )
b10000000 6
b0 H
b0 N
b0 M
0P
b0 O
b0 I
b10000000 U
b11 Z
b10101000101011 4
b1111111 2
b1111111 1
b0 -
b110000 .
1'
#249760
0'
#251990
b0 !
b0 <
b1010101 F
b10101010 E
1@
b1111111110101010 C
b100000000 ?
b11111111 )
b11111111 6
1Q
b11 H
b10101010 N
b10101010 M
0P
0L
b11 O
b11 I
b11111111 U
b100 Z
b10101010000000 4
b10000000 2
b10000000 1
b0 -
b110001 .
1'
#254220
0'
#256450
b111111110 ?
0@
b0 C
b10101010000001 G
b1111111110101010 F
b1010101 !
b1010101 <
b10101010 )
b10101010 6
b100 H
b10101010 N
b10101010 M
1Q
b100 O
b100 I
b10101010 U
b101 Z
b101010010101011 4
b11111111 2
b11111111 1
b0 -
b110010 .
1'
#258680
0'
#260910
b10101000101011 !
b10101000101011 <
b10101010000000 G
b0 F
b101010100 E
1@
b1111111110101010 C
b101010100 ?
b1010101 )
b1010101 6
1S
b111 H
b101010100 N
b101010100 M
0Q
0P
0L
b111 O
b111 I
b1010101 U
b110 Z
b11100001110010 4
b10101010 2
b10101010 1
b0 -
b110011 .
1'
#263140
0'
