rtl/8Bit/functions.vh
// =========================================================================
// FUNÇÕES AUXILIARES
// =========================================================================

// -------------------------------------------------------------------------
// Calcula 3×multiplicando (otimização Booth: 3A = A + 2A)
// -------------------------------------------------------------------------
function automatic [ACC_WIDTH-1:0] f_calc_3x;
    input [WIDTH-1:0] val_in;  // Valor de entrada
    input             s_bit;   // Bit de sinal para extensão
    reg [ACC_WIDTH-1:0] val_ext;
begin
    // Estende o valor com sinal
    val_ext = { {(ACC_WIDTH-WIDTH){s_bit}}, val_in };
    // Calcula 3x = x + (x << 1)
    f_calc_3x = val_ext + (val_ext <<< 1);
end
endfunction

// -------------------------------------------------------------------------
// Estende o multiplicando com bit de sinal
// -------------------------------------------------------------------------
function automatic [ACC_WIDTH-1:0] f_extend_mcand;
    input [WIDTH-1:0] val_in;  // Valor a estender
    input             s_bit;   // Bit de sinal
begin
    f_extend_mcand = { {(ACC_WIDTH-WIDTH){s_bit}}, val_in };
end
endfunction

// -------------------------------------------------------------------------
// Inicializa o registrador de produto com o multiplicador
// Formato: [ACC_bits | sign_bit | multiplier | 0]
// -------------------------------------------------------------------------
function automatic [REG_WIDTH-1:0] f_init_prod_reg;
    input [WIDTH-1:0] mult_in;  // Multiplicador
    input             s_bit;    // Bit de sinal
begin
    f_init_prod_reg = {
        {ACC_WIDTH{1'b0}},  // Parte alta zerada (acumulador)
        s_bit,              // Bit de sinal estendido
        mult_in,            // Multiplicador
        1'b0                // Bit extra para janela de Booth
    };
end
endfunction

// -------------------------------------------------------------------------
// DECODIFICADOR BOOTH RADIX-4
// Analisa janela de 4 bits e gera sinais de controle
// -------------------------------------------------------------------------
// Codificação da saída [4:0]:
//   [4]   = sinal da operação (1=subtração, 0=adição)
//   [3:0] = magnitude one-hot (0=±0, 1=±1x, 2=±2x, 3=±3x, 4=±4x)
// -------------------------------------------------------------------------
function automatic [4:0] f_booth_decoder;
    input [3:0] window;     // Janela de 4 bits [i+2:i-1]
    reg [2:0] recoded;
begin
    // Recodificação: inverte bits se MSB=1 (número negativo)
    recoded = window[2:0] ^ {3{window[3]}};

    // Determina sinal: subtração se negativo e não é -0
    f_booth_decoder[4] = window[3] & ~(&window[2:0]);

    // Inicializa magnitude
    f_booth_decoder[3:0] = 4'b0000;

    // Decodifica magnitude baseado nos bits recodificados
    case (recoded)
        3'b001, 3'b010: f_booth_decoder[0] = 1'b1;  // ±1x
        3'b011, 3'b100: f_booth_decoder[1] = 1'b1;  // ±2x
        3'b101, 3'b110: f_booth_decoder[2] = 1'b1;  // ±3x
        3'b111:         f_booth_decoder[3] = 1'b1;  // ±4x
        default:        ;                            // 0x (nada)
    endcase
end
endfunction

// =========================================================================
// FUNÇÕES ARITMÉTICAS MODULARIZADAS
// =========================================================================

// -------------------------------------------------------------------------
// 1. FUNÇÃO BASE (KERNEL) - O que há de comum
// Realiza apenas a seleção (MUX) e a inversão (XOR)
// -------------------------------------------------------------------------
function automatic [ACC_WIDTH-1:0] f_booth_mux_inv;
    input [ACC_WIDTH-1:0] val_1x;
    input [ACC_WIDTH-1:0] val_3x;
    input [4:0]           ctrl;   // {inv, sel_4x, sel_3x, sel_2x, sel_1x}
    reg [ACC_WIDTH-1:0]   magnitude;
begin
    // Lógica de Seleção (Mux One-Hot)
    magnitude = ({ACC_WIDTH{ctrl[0]}} & val_1x)          | // 1x
                ({ACC_WIDTH{ctrl[1]}} & (val_1x <<< 1))  | // 2x
                ({ACC_WIDTH{ctrl[2]}} & val_3x)          | // 3x
                ({ACC_WIDTH{ctrl[3]}} & (val_1x <<< 2));   // 4x

    // Lógica de Inversão (Complemento de 1)
    // Se ctrl[4] for 1, inverte todos os bits.
    f_booth_mux_inv = magnitude ^ {ACC_WIDTH{ctrl[4]}};
end
endfunction

// -------------------------------------------------------------------------
// 2. FUNÇÃO SELECT OP (Para Pipeline)
// Wrapper simples: Apenas retorna o operando preparado.
// -------------------------------------------------------------------------
function automatic [ACC_WIDTH-1:0] f_select_op;
    input [ACC_WIDTH-1:0] val_1x;
    input [ACC_WIDTH-1:0] val_3x;
    input [4:0]           ctrl;
begin
    // Reutiliza a lógica comum
    f_select_op = f_booth_mux_inv(val_1x, val_3x, ctrl);
end
endfunction

rtl/8Bit/pipeline.v
`timescale 1ns / 1ps
`default_nettype none

module booth_mult8_core_pipelined #(
    parameter integer WIDTH = 8
)(
    input  wire                  clk,
    input  wire                  rst_n,
    input  wire                  start,
    input  wire signed [WIDTH-1:0] multiplicand,
    input  wire signed [WIDTH-1:0] multiplier,
    input  wire [1:0]            sign_mode,
    output wire signed [(2*WIDTH)-1:0] product,
    output reg                   done
);

    localparam integer SHIFT_BITS = WIDTH + 1;
    localparam integer ACC_WIDTH  = WIDTH + 3;
    localparam integer REG_WIDTH  = (2*WIDTH) + 5;

    // Estados da Máquina de Estados Finita (FSM)
    localparam [1:0] S_IDLE    = 2'b00;
    localparam [1:0] S_PREP_OP = 2'b01; // Decodifica e busca operando
    localparam [1:0] S_ACCUM   = 2'b10; // Soma e desloca

    reg [1:0] state;

    // ------------------------------------------------------------------------
    // FUNÇÕES (Reutilizadas)
    // ------------------------------------------------------------------------
    `include "functions.vh"

    // -------------------------------------------------------------------------
    // 3. FUNÇÃO ALU CALC (Para Ciclo Único / V3)
    // Obtém o operando da função base e realiza a soma completa.
    // -------------------------------------------------------------------------
    function automatic [ACC_WIDTH-1:0] f_alu_calc;
        input [ACC_WIDTH-1:0] acc_val;
        input [ACC_WIDTH-1:0] val_1x;
        input [ACC_WIDTH-1:0] val_3x;
        input [4:0]           ctrl;
        reg [ACC_WIDTH-1:0]   operand_prepared;
        begin
            // Passo 1: Obtém o operando (Mux + Inversão) da função comum
            operand_prepared = f_booth_mux_inv(val_1x, val_3x, ctrl);
    
            // Passo 2: Soma Final (Acumulador + Operando + Carry In)
            // O bit 'ctrl[4]' (inv) age como o +1 do Complemento de 2
            f_alu_calc = acc_val + operand_prepared + { {(ACC_WIDTH-1){1'b0}}, ctrl[4] };
        end
    endfunction
    // ------------------------------------------------------------------------
    // REGISTRADORES
    // ------------------------------------------------------------------------
    reg signed [ACC_WIDTH-1:0] r_mcand_ext;
    reg signed [ACC_WIDTH-1:0] m_3x_reg;
    reg signed [REG_WIDTH-1:0] prod_reg;
    reg [2:0]                  iter_shift;

    // Registradores do Pipeline (O segredo da velocidade)
    reg signed [ACC_WIDTH-1:0] r_pipe_operand; // Guarda o valor a ser somado
    reg                        r_pipe_inv;     // Guarda o bit de carry/inversão

    // Wires auxiliares
    wire w_sign_bit_a = sign_mode[1] & multiplicand[WIDTH-1];
    wire w_sign_bit_b = sign_mode[0] & multiplier[WIDTH-1];

    wire [4:0] w_booth_ctrl = f_booth_decoder(prod_reg[3:0]);

    // O somador final (simples e limpo)
    wire signed [ACC_WIDTH-1:0] w_sum_result =
        prod_reg[REG_WIDTH-1 : SHIFT_BITS+1] + // Acumulador atual
        r_pipe_operand +                       // Operando capturado no ciclo anterior
        { {(ACC_WIDTH-1){1'b0}}, r_pipe_inv }; // Bit de carry in

    assign product = prod_reg[WIDTH*2:1];

    // ------------------------------------------------------------------------
    // FSM PIPELINED
    // ------------------------------------------------------------------------
    always @(posedge clk or negedge rst_n) begin
        if (!rst_n) begin
            state           <= S_IDLE;
            done            <= 1'b0;
            iter_shift      <= 3'b0;
            r_mcand_ext     <= {ACC_WIDTH{1'b0}};
            m_3x_reg        <= {ACC_WIDTH{1'b0}};
            prod_reg        <= {REG_WIDTH{1'b0}};
            r_pipe_operand  <= {ACC_WIDTH{1'b0}};
            r_pipe_inv      <= 1'b0;
        end else begin
            done <= 1'b0;

            case (state)
                S_IDLE: begin
                    if (start) begin
                        // Pré-cálculos iniciais (Igual à versão anterior)
                        r_mcand_ext <= f_extend_mcand(multiplicand, w_sign_bit_a);
                        m_3x_reg    <= f_calc_3x(multiplicand, w_sign_bit_a);
                        prod_reg    <= f_init_prod_reg(multiplier, w_sign_bit_b);

                        iter_shift  <= 3'b100;
                        state       <= S_PREP_OP; // Vai para preparação
                    end
                end

                S_PREP_OP: begin
                    // CICLO 1: Apenas olha os bits e carrega o operando.
                    // Não faz nenhuma soma aqui. Caminho crítico = Mux.
                    r_pipe_operand <= f_select_op(r_mcand_ext, m_3x_reg, w_booth_ctrl);
                    r_pipe_inv     <= w_booth_ctrl[4]; // Bit de inversão

                    state <= S_ACCUM;
                end

                S_ACCUM: begin
                    // CICLO 2: Apenas soma e desloca.
                    // Caminho crítico = Somador + Shift (muito rápido no iCE40).
                    prod_reg   <= { {3{w_sum_result[ACC_WIDTH-1]}}, w_sum_result, prod_reg[SHIFT_BITS:3] };
                    iter_shift <= iter_shift >> 1;

                    if (iter_shift[0]) begin // Última iteração?
                        // Se era o bit 1 (que virou 0 após shift), terminamos
                        // Mas espera, iter_shift >> 1 acontece AO MESMO TEMPO.
                        // Se iter_shift atual for 1, o próximo será 0.
                    end

                    // Lógica de loop correta:
                    if (iter_shift[0]) begin
                        state <= S_IDLE;
                        done  <= 1'b1;
                    end else begin
                        state <= S_PREP_OP; // Volta para buscar o próximo operando
                    end
                end
            endcase
        end
    end
endmodule
`default_nettype wire

tb/tb_booth_radix8_8_pipeline.v
`timescale 1ns / 1ps

module tb_booth_handshake;

    // ------------------------------------------------------------------------
    // Sinais
    // ------------------------------------------------------------------------
    reg clk;
    reg rst_n;
    reg start;                  // ADICIONADO: Sinal Start
    reg signed [7:0] mcand_in;
    reg signed [7:0] mult_in;
    reg [1:0] sign_mode_in;

    wire signed [15:0] product_out;
    wire done;                  // ADICIONADO: Sinal Done

    integer errors = 0;
    integer tests_run = 0;

    localparam MODE_UU = 2'b00;
    localparam MODE_US = 2'b01;
    localparam MODE_SU = 2'b10;
    localparam MODE_SS = 2'b11;

    // ------------------------------------------------------------------------
    // DUT (Device Under Test)
    // ------------------------------------------------------------------------
    booth_mult8_core_pipelined dut (
        .clk(clk),
        .rst_n(rst_n),
        .start(start),          // CONECTADO
        .multiplicand(mcand_in),
        .multiplier(mult_in),
        .sign_mode(sign_mode_in),
        .product(product_out),
        .done(done)             // CONECTADO
    );

    // ------------------------------------------------------------------------
    // Clock
    // ------------------------------------------------------------------------
    initial clk = 0;
    always #2.23 clk = ~clk; 

    // ------------------------------------------------------------------------
    // Golden Model (Cálculo Esperado)
    // ------------------------------------------------------------------------
    function signed [15:0] calc_expected;
        input [7:0] a, b;
        input [1:0] mode;
        reg signed [8:0] a_conv, b_conv;
        reg signed [17:0] res;
    begin
        if (mode[1]) a_conv = $signed(a); else a_conv = $signed({1'b0, a});
        if (mode[0]) b_conv = $signed(b); else b_conv = $signed({1'b0, b});
        res = a_conv * b_conv;
        calc_expected = res[15:0];
    end
    endfunction

    // ------------------------------------------------------------------------
    // Sequência de Teste Principal
    // ------------------------------------------------------------------------
    reg [7:0] corners [0:7];
    initial begin
        $dumpfile("booth_handshake.vcd");
        $dumpvars(0, tb_booth_handshake);

        // Casos de canto (Corner cases)
        corners[0]=8'h00; corners[1]=8'h01; corners[2]=8'h7F; corners[3]=8'h80;
        corners[4]=8'hFF; corners[5]=8'hAA; corners[6]=8'h55; corners[7]=8'h02;

        // Inicialização
        rst_n = 0; start = 0; mcand_in = 0; mult_in = 0; sign_mode_in = 0;
        #20; 
        @(posedge clk); 
        rst_n = 1;
        #20;

        $display("=== INICIANDO VERIFICACAO (HANDSHAKE) ===");
        run_phase(MODE_UU, "UU (Unsigned x Unsigned)");
        run_phase(MODE_US, "US (Unsigned x Signed)");
        run_phase(MODE_SU, "SU (Signed x Unsigned)");
        run_phase(MODE_SS, "SS (Signed x Signed)");

        if (errors == 0)
            $display("\nSUCESSO TOTAL: %0d testes passaram.", tests_run);
        else
            $display("\nFALHA: %0d erros encontrados.", errors);

        $finish;
    end

    // Tarefa para rodar um grupo de testes
    task run_phase;
        input [1:0] mode;
        input [25*8:1] name; // String name
        integer i, j;
    begin
        $display("Testando %s...", name);
        // Teste exaustivo dos corners
        for(i=0;i<8;i=i+1) 
            for(j=0;j<8;j=j+1) 
                check_transaction(corners[i], corners[j], mode);
        
        // Testes aleatórios
        for(i=0;i<50;i=i+1) 
            check_transaction($random, $random, mode);
    end
    endtask

    // ------------------------------------------------------------------------
    // Transação Individual (O SEGREDO ESTÁ AQUI)
    // ------------------------------------------------------------------------
    task check_transaction;
        input [7:0] a, b;
        input [1:0] mode;
        reg signed [15:0] expected;
    begin
        // 1. Configura as entradas
        @(posedge clk);
        mcand_in <= a; 
        mult_in <= b; 
        sign_mode_in <= mode;
        
        // 2. Pulsa o START
        start <= 1;
        @(posedge clk);
        start <= 0;

        // 3. Espera pelo DONE (Handshake)
        // O hardware leva vários ciclos. Esperamos até 'done' subir.
        @(posedge done); 
        
        // 4. Verifica o resultado (na borda seguinte para estabilizar)
        expected = calc_expected(a, b, mode);
        
        // Pequeno delay delta para garantir leitura correta
        #1; 
        if (product_out !== expected) begin
            $display("ERRO | Mode %b | A: %h (%d) B: %h (%d)", mode, a, $signed(a), b, $signed(b));
            $display("       Exp: %h (%d) | Obt: %h (%d)", expected, expected, product_out, product_out);
            errors = errors + 1;
        end
        tests_run = tests_run + 1;
        
        // Espera um ciclo antes da próxima transação (opcional)
        @(posedge clk);
    end
    endtask

endmodule

sim/8Bit/pipeline/booth_handshake.vcd
$date
	Tue Dec 16 14:16:09 2025
$end
$version
	Icarus Verilog
$end
$timescale
	1ps
$end
$scope module tb_booth_handshake $end
$var wire 16 ! product_out [15:0] $end
$var wire 1 " done $end
$var parameter 2 # MODE_SS $end
$var parameter 2 $ MODE_SU $end
$var parameter 2 % MODE_US $end
$var parameter 2 & MODE_UU $end
$var reg 1 ' clk $end
$var reg 8 ( mcand_in [7:0] $end
$var reg 8 ) mult_in [7:0] $end
$var reg 1 * rst_n $end
$var reg 2 + sign_mode_in [1:0] $end
$var reg 1 , start $end
$var integer 32 - errors [31:0] $end
$var integer 32 . tests_run [31:0] $end
$scope function calc_expected $end
$var reg 8 / a [7:0] $end
$var reg 9 0 a_conv [8:0] $end
$var reg 8 1 b [7:0] $end
$var reg 9 2 b_conv [8:0] $end
$var reg 2 3 mode [1:0] $end
$var reg 18 4 res [17:0] $end
$upscope $end
$scope module dut $end
$var wire 1 ' clk $end
$var wire 8 5 multiplicand [7:0] $end
$var wire 8 6 multiplier [7:0] $end
$var wire 1 * rst_n $end
$var wire 2 7 sign_mode [1:0] $end
$var wire 1 , start $end
$var wire 1 8 w_sign_bit_a $end
$var wire 1 9 w_sign_bit_b $end
$var wire 11 : w_sum_result [10:0] $end
$var wire 5 ; w_booth_ctrl [4:0] $end
$var wire 16 < product [15:0] $end
$var parameter 32 = ACC_WIDTH $end
$var parameter 32 > REG_WIDTH $end
$var parameter 32 ? SHIFT_BITS $end
$var parameter 2 @ S_ACCUM $end
$var parameter 2 A S_IDLE $end
$var parameter 2 B S_PREP_OP $end
$var parameter 32 C WIDTH $end
$var reg 1 " done $end
$var reg 3 D iter_shift [2:0] $end
$var reg 11 E m_3x_reg [10:0] $end
$var reg 21 F prod_reg [20:0] $end
$var reg 11 G r_mcand_ext [10:0] $end
$var reg 1 H r_pipe_inv $end
$var reg 11 I r_pipe_operand [10:0] $end
$var reg 2 J state [1:0] $end
$scope function f_alu_calc $end
$upscope $end
$scope function f_booth_decoder $end
$upscope $end
$scope function f_booth_mux_inv $end
$upscope $end
$scope function f_calc_3x $end
$upscope $end
$scope function f_extend_mcand $end
$upscope $end
$scope function f_init_prod_reg $end
$upscope $end
$scope function f_select_op $end
$upscope $end
$upscope $end
$scope task check_transaction $end
$var reg 8 K a [7:0] $end
$var reg 8 L b [7:0] $end
$var reg 16 M expected [15:0] $end
$var reg 2 N mode [1:0] $end
$upscope $end
$scope task run_phase $end
$var reg 2 O mode [1:0] $end
$var reg 200 P name [200:1] $end
$var integer 32 Q i [31:0] $end
$var integer 32 R j [31:0] $end
$upscope $end
$upscope $end
$enddefinitions $end
$comment Show the parameter values. $end
$dumpall
b1000 C
b1 B
b0 A
b10 @
b1001 ?
b10101 >
b1011 =
b0 &
b1 %
b10 $
b11 #
$end
#0
$dumpvars
bx R
bx Q
bx P
bx O
bx N
bx M
bx L
bx K
b0 J
b0 I
0H
b0 G
b0 F
b0 E
b0 D
b0 <
b0 ;
b0 :
09
08
b0 7
b0 6
b0 5
bx 4
bx 3
bx 2
bx 1
bx 0
bx /
b0 .
b0 -
0,
b0 +
0*
b0 )
b0 (
0'
0"
b0 !
$end
#2230
1'
#4460
0'
#6690
1'
#8920
0'
#11150
1'
#13380
0'
#15610
1'
#17840
0'
#20070
1*
1'
#22300
0'
#24530
1'
#26760
0'
#28990
1'
#31220
0'
#33450
1'
#35680
0'
#37910
1'
#40070
b0 N
b0 L
b0 K
b0 R
b0 Q
b10101010101010100100000001010000101010101101110011100110110100101100111011011100110010101100100001000000111100000100000010101010110111001110011011010010110011101101110011001010110010000101001 P
b0 O
#40140
0'
#42370
1,
1'
#44600
0'
#46830
b1 J
b100 D
0,
1'
#49060
0'
#51290
b10 J
1'
#53520
0'
#55750
b1 J
b10 D
1'
#57980
0'
#60210
b10 J
1'
#62440
0'
#64670
b1 J
b1 D
1'
#66900
0'
#69130
b10 J
1'
#71360
0'
#73590
b0 M
b0 4
b0 2
b0 0
b0 /
b0 1
b0 3
1"
b0 J
b0 D
1'
#74590
b1 .
#75820
0'
#78050
0"
b1 L
b1 R
1'
#80280
0'
#82510
1,
b1 )
b1 6
1'
#84740
0'
#86970
b1 ;
b1 !
b1 <
b1 J
b100 D
b10 F
0,
1'
#89200
0'
#91430
b10 J
1'
#93660
0'
#95890
b0 ;
b0 !
b0 <
b1 J
b10 D
b0 F
1'
#98120
0'
#100350
b10 J
1'
#102580
0'
#104810
b1 J
b1 D
1'
#107040
0'
#109270
b10 J
1'
#111500
0'
#113730
b1 2
b1 1
1"
b0 J
b0 D
1'
#114730
b10 .
#115960
0'
#118190
0"
b1111111 L
b10 R
1'
#120420
0'
#122650
1,
b1111111 )
b1111111 6
1'
#124880
0'
#127110
b10001 ;
b1111111 !
b1111111 <
b1 J
b100 D
b11111110 F
0,
1'
#129340
0'
#131570
b10 J
1H
b0 :
b11111111111 I
1'
#133800
0'
#136030
b0 ;
b1111 !
b1111 <
b1 J
b10 D
b11111 F
1'
#138260
0'
#140490
b10 J
0H
b0 :
b0 I
1'
#142720
0'
#144950
b10 ;
b1 !
b1 <
b1 J
b1 D
b11 F
1'
#147180
0'
#149410
b10 J
1'
#151640
0'
#153870
b0 ;
b1111111 2
b1111111 1
b0 !
b0 <
1"
b0 J
b0 D
b0 F
1'
#154870
b11 .
#156100
0'
#158330
0"
b10000000 L
b11 R
1'
#160560
0'
#162790
1,
b10000000 )
b10000000 6
1'
#165020
0'
#167250
b10000000 !
b10000000 <
b1 J
b100 D
b100000000 F
0,
1'
#169480
0'
#171710
b10 J
1'
#173940
0'
#176170
b10000 !
b10000 <
b1 J
b10 D
b100000 F
1'
#178400
0'
#180630
b10 J
1'
#182860
0'
#185090
b10 ;
b10 !
b10 <
b1 J
b1 D
b100 F
1'
#187320
0'
#189550
b10 J
1'
#191780
0'
#194010
b0 ;
b10000000 2
b10000000 1
b0 !
b0 <
1"
b0 J
b0 D
b0 F
1'
#195010
b100 .
#196240
0'
#198470
0"
b11111111 L
b100 R
1'
#200700
0'
#202930
1,
b11111111 )
b11111111 6
1'
#205160
0'
#207390
b10001 ;
b11111111 !
b11111111 <
b1 J
b100 D
b111111110 F
0,
1'
#209620
0'
#211850
b10 J
1H
b0 :
b11111111111 I
1'
#214080
0'
#216310
b0 ;
b11111 !
b11111 <
b1 J
b10 D
b111111 F
1'
#218540
0'
#220770
b10 J
0H
b0 :
b0 I
1'
#223000
0'
#225230
b1000 ;
b11 !
b11 <
b1 J
b1 D
b111 F
1'
#227460
0'
#229690
b10 J
1'
#231920
0'
#234150
b0 ;
b11111111 2
b11111111 1
b0 !
b0 <
1"
b0 J
b0 D
b0 F
1'
#235150
b101 .
#236380
0'
#238610
0"
b10101010 L
b101 R
1'
#240840
0'
#243070
1,
b10101010 )
b10101010 6
1'
#245300
0'
#247530
b10 ;
b10101010 !
b10101010 <
b1 J
b100 D
b101010100 F
0,
1'
#249760
0'
#251990
b10 J
1'
#254220
0'
#256450
b10100 ;
b10101 !
b10101 <
b1 J
b10 D
b101010 F
1'
#258680
0'
#260910
b10 J
1H
b0 :
b11111111111 I
1'
#263140
0'
#265370
b100 ;
b10 !
b10 <
b1 J
b1 D
b101 F
1'
#267600
0'
#269830
b10 J
0H
b0 :
b0 I
1'
#272060
0'
#274290
b0 ;
b10101010 2
b10101010 1
b0 !
b0 <
1"
b0 J
b0 D
b0 F
1'
#275290
b110 .
#276520
0'
#278750
0"
b1010101 L
b110 R
1'
#280980
0'
#283210
1,
b1010101 )
b1010101 6
1'
#285440
0'
#287670
b10100 ;
b1010101 !
b1010101 <
b1 J
b100 D
b10101010 F
0,
1'
#289900
0'
#292130
b10 J
1H
b0 :
b11111111111 I
1'
#294360
0'
#296590
b100 ;
b1010 !
b1010 <
b1 J
b10 D
b10101 F
1'
#298820
0'
#301050
b10 J
0H
b0 :
b0 I
1'
#303280
0'
#305510
b1 ;
b1 !
b1 <
b1 J
b1 D
b10 F
1'
#307740
0'
#309970
b10 J
1'
#312200
0'
#314430
b0 ;
b1010101 2
b1010101 1
b0 !
b0 <
1"
b0 J
b0 D
b0 F
1'
#315430
b111 .
#316660
0'
#318890
0"
b10 L
b111 R
1'
#321120
0'
#323350
1,
b10 )
b10 6
1'
#325580
0'
#327810
b10 ;
b10 !
b10 <
b1 J
b100 D
b100 F
0,
1'
#330040
0'
#332270
b10 J
1'
#334500
0'
#336730
b0 ;
b0 !
b0 <
b1 J
b10 D
b0 F
1'
#338960
0'
#341190
b10 J
1'
#343420
0'
#345650
b1 J
b1 D
1'
#347880
0'
#350110
b10 J
1'
#352340
0'
#354570
b10 2
b10 1
1"
b0 J
b0 D
1'
#355570
b1000 .
#356800
0'
#359030
0"
b0 L
b1 K
b1 Q
b0 R
1'
#361260
0'
#363490
1,
b0 )
b0 6
b1 (
b1 5
1'
#365720
0'
#367950
b1 J
b100 D
b11 E
b1 G
0,
1'
#370180
0'
#372410
b10 J
1'
#374640
0'
#376870
b1 J
b10 D
1'
#379100
0'
#381330
b10 J
1'
#383560
0'
#385790
b1 J
b1 D
1'
#388020
0'
#390250
b10 J
1'
#392480
0'
#394710
b0 2
b1 0
b1 /
b0 1
1"
b0 J
b0 D
1'
#395710
b1001 .
#396940
0'
#399170
0"
b1 L
b1 R
1'
#401400
0'
#403630
1,
b1 )
b1 6
1'
#405860
0'
#408090
b1 ;
b1 !
b1 <
b1 J
b100 D
b10 F
0,
1'
#410320
0'
#412550
b10 J
b1 :
b1 I
1'
#414780
0'
#417010
b0 ;
b1000000 !
b1000000 <
b1 J
b10 D
b10000000 F
1'
#419240
0'
#421470
b10 J
b0 :
b0 I
1'
#423700
0'
#425930
b1000 !
b1000 <
b1 J
b1 D
b10000 F
1'
#428160
0'
#430390
b10 J
1'
#432620
0'
#434850
b1 ;
b1 M
b1 4
b1 2
b1 1
b1 !
b1 <
1"
b0 J
b0 D
b10 F
1'
#435850
b1010 .
#437080
0'
#439310
0"
b1111111 L
b10 R
1'
#441540
0'
#443770
1,
b1111111 )
b1111111 6
1'
#446000
0'
#448230
b10001 ;
b1111111 !
b1111111 <
b1 J
b100 D
b11111110 F
0,
1'
#450460
0'
#452690
b10 J
1H
b11111111111 :
b11111111110 I
1'
#454920
0'
#457150
b0 ;
b11111111110 :
b1111111111001111 !
b1111111111001111 <
b1 J
b10 D
b111111111111110011111 F
1'
#459380
0'
#461610
b10 J
0H
b11111111111 :
b0 I
1'
#463840
0'
#466070
b10 ;
b1111111111111001 !
b1111111111111001 <
b1 J
b1 D
b111111111111111110011 F
1'
#468300
0'
#470530
b10 J
b1 :
b10 I
1'
#472760
0'
#474990
b10001 ;
b1111111 M
b1111111 4
b1111111 2
b1111111 1
b10 :
b1111111 !
b1111111 <
1"
b0 J
b0 D
b11111110 F
1'
#475990
b1011 .
#477220
0'
#479450
0"
b10000000 L
b11 R
1'
#481680
0'
#483910
1,
b10000000 )
b10000000 6
1'
#486140
0'
#488370
b0 ;
b10000000 !
b10000000 <
b1 J
b100 D
b100000000 F
0,
1'
#490600
0'
#492830
b10 J
b0 :
b0 I
1'
#495060
0'
#497290
b10000 !
b10000 <
b1 J
b10 D
b100000 F
1'
#499520
0'
#501750
b10 J
1'
#503980
0'
#506210
b10 ;
b10 !
b10 <
b1 J
b1 D
b100 F
1'
#508440
0'
#510670
b10 J
b10 :
b10 I
1'
#512900
0'
#515130
b0 ;
b10000000 M
b10000000 4
b10000000 2
b10000000 1
b10000000 !
b10000000 <
1"
b0 J
b0 D
b100000000 F
1'
#516130
b1100 .
#517360
0'
#519590
0"
b11111111 L
b100 R
1'
#521820
0'
#524050
1,
b11111111 )
b11111111 6
1'
#526280
0'
#528510
b10001 ;
b11111111 !
b11111111 <
b1 J
b100 D
b111111110 F
0,
1'
#530740
0'
#532970
b10 J
1H
b11111111111 :
b11111111110 I
1'
#535200
0'
#537430
b0 ;
b11111111110 :
b1111111111011111 !
b1111111111011111 <
b1 J
b10 D
b111111111111110111111 F
1'
#539660
0'
#541890
b10 J
0H
b11111111111 :
b0 I
1'
#544120
0'
#546350
b1000 ;
b1111111111111011 !
b1111111111111011 <
b1 J
b1 D
b111111111111111110111 F
1'
#548580
0'
#550810
b10 J
b11 :
b100 I
1'
#553040
0'
#555270
b10001 ;
b11111111 M
b11111111 4
b11111111 2
b11111111 1
b100 :
b11111111 !
b11111111 <
1"
b0 J
b0 D
b111111110 F
1'
#556270
b1101 .
#557500
0'
#559730
0"
b10101010 L
b101 R
1'
#561960
0'
#564190
1,
b10101010 )
b10101010 6
1'
#566420
0'
#568650
b10 ;
b10101010 !
b10101010 <
b1 J
b100 D
b101010100 F
0,
1'
#570880
0'
#573110
b10 J
b10 :
b10 I
1'
#575340
0'
#577570
b10100 ;
b10010101 !
b10010101 <
b1 J
b10 D
b100101010 F
1'
#579800
0'
#582030
b10 J
1H
b11111111101 :
b11111111100 I
1'
#584260
0'
#586490
b100 ;
b11111111100 :
b1111111101010010 !
b1111111101010010 <
b1 J
b1 D
b111111111111010100101 F
1'
#588720
0'
#590950
b10 J
0H
b10 :
b11 I
1'
#593180
0'
#595410
b10 ;
b10101010 M
b10101010 4
b10101010 2
b10101010 1
b11 :
b10101010 !
b10101010 <
1"
b0 J
b0 D
b101010100 F
1'
#596410
b1110 .
#597640
0'
#599870
0"
b1010101 L
b110 R
1'
#602100
0'
#604330
1,
b1010101 )
b1010101 6
1'
#606560
0'
#608790
b10100 ;
b1010101 !
b1010101 <
b1 J
b100 D
b10101010 F
0,
1'
#611020
0'
#613250
b10 J
1H
b11111111101 :
b11111111100 I
1'
#615480
0'
#617710
b100 ;
b11111111100 :
b1111111101001010 !
b1111111101001010 <
b1 J
b10 D
b111111111111010010101 F
1'
#619940
0'
#622170
b10 J
0H
b10 :
b11 I
1'
#624400
0'
#626630
b1 ;
b11 :
b10101001 !
b10101001 <
b1 J
b1 D
b101010010 F
1'
#628860
0'
#631090
b10 J
b1 :
b1 I
1'
#633320
0'
#635550
b10100 ;
b1010101 M
b1010101 4
b1010101 2
b1010101 1
b1010101 !
b1010101 <
1"
b0 J
b0 D
b10101010 F
1'
#636550
b1111 .
#637780
0'
#640010
0"
b10 L
b111 R
1'
#642240
0'
#644470
1,
b10 )
b10 6
1'
#646700
0'
#648930
b10 ;
b10 !
b10 <
b1 J
b100 D
b100 F
0,
1'
#651160
0'
#653390
b10 J
b10 :
b10 I
1'
#655620
0'
#657850
b0 ;
b10000000 !
b10000000 <
b1 J
b10 D
b100000000 F
1'
#660080
0'
#662310
b10 J
b0 :
b0 I
1'
#664540
0'
#666770
b10000 !
b10000 <
b1 J
b1 D
b100000 F
1'
#669000
0'
#671230
b10 J
1'
#673460
0'
#675690
b10 ;
b10 M
b10 4
b10 2
b10 1
b10 !
b10 <
1"
b0 J
b0 D
b100 F
1'
#676690
b10000 .
#677920
0'
#680150
0"
b0 L
b1111111 K
b10 Q
b0 R
1'
#682380
0'
#684610
1,
b0 )
b0 6
b1111111 (
b1111111 5
1'
#686840
0'
#689070
b0 ;
b0 !
b0 <
b1 J
b100 D
b0 F
b101111101 E
b1111111 G
0,
1'
#691300
0'
#693530
b10 J
1'
#695760
0'
#697990
b1 J
b10 D
1'
#700220
0'
#702450
b10 J
1'
#704680
0'
#706910
b1 J
b1 D
1'
#709140
0'
#711370
b10 J
1'
#713600
0'
#715830
b0 M
b0 4
b0 2
b1111111 0
b1111111 /
b0 1
1"
b0 J
b0 D
1'
#716830
b10001 .
#718060
0'
#720290
0"
b1 L
b1 R
1'
#722520
0'
#724750
1,
b1 )
b1 6
1'
#726980
0'
#729210
b1 ;
b1 !
b1 <
b1 J
b100 D
b10 F
0,
1'
#731440
0'
#733670
b10 J
b1111111 :
b1111111 I
1'
#735900
0'
#738130
b0 ;
b10001110 :
b1111111000000 !
b1111111000000 <
b1 J
b10 D
b11111110000000 F
1'
#740360
0'
#742590
b10 J
b1111 :
b0 I
1'
#744820
0'
#747050
b1 :
b1111111000 !
b1111111000 <
b1 J
b1 D
b11111110000 F
1'
#749280
0'
#751510
b10 J
1'
#753740
0'
#755970
b10001 ;
b1111111 M
b1111111 4
b1 2
b1 1
b0 :
b1111111 !
b1111111 <
1"
b0 J
b0 D
b11111110 F
1'
#756970
b10010 .
#758200
0'
#760430
0"
b1111111 L
b10 R
1'
#762660
0'
#764890
1,
b1111111 )
b1111111 6
1'
#767120
0'
#769350
b1 J
b100 D
0,
1'
#771580
0'
